Workbook

Sheet Start Here
A1: Start Here – the next two weeks
A2: Just the 'Now' tasks. Everything else waits on the Task List until it's its turn. Snapshot as of 1 Oct 2026.
A4: ID | B4: Section | C4: Task | D4: When | E4: Owner | F4: Done? | G4: Notes
A5: 1 | B5: 0. Monday & Claude Setup | C5: Check Monday trial status and end date | D5: Fri 2 Oct | F5: ☐ | G5: Cat – from the van
A6: 2 | B6: 0. Monday & Claude Setup | C6: Upgrade Monday to Pro, monthly billing | D6: Fri 2 Oct | F6: ☐ | G6: Cat – call Charlotte for card
A7: 3 | B7: 0. Monday & Claude Setup | C7: Invite Yahya to Monday as Member (info@infovis.co.uk) | D7: Fri 2 Oct | F7: ☐ | G7: Cat to email him once done
A8: 4 | B8: 0. Monday & Claude Setup | C8: Make sure Cat is a Monday admin | D8: Fri 2 Oct | F8: ☐
A9: 5 | B9: 0. Monday & Claude Setup | C9: Send Yahya samples: spreadsheet, task list, marketing plan, targets, enquiry tracker extract | D9: Weekend | F9: ☐ | G9: This workbook covers the task list
A10: 6 | B10: 0. Monday & Claude Setup | C10: Setup day with Yahya, Cat and Charlotte | D10: Mon 5 Oct | F10: ☐
A11: 7 | B11: 0. Monday & Claude Setup | C11: Build marketing board – one group per brand | D11: Mon 5 Oct | F11: ☐ | G11: Yahya
A12: 8 | B12: 0. Monday & Claude Setup | C12: Load this task list into Monday | D12: Mon 5 Oct | F12: ☐ | G12: Yahya
A13: 9 | B13: 0. Monday & Claude Setup | C13: Build goals & targets dashboard for the Tuesday meeting | D13: Mon 5 Oct | F13: ☐ | G13: Yahya
A14: 28 | B14: 1. All Brands | C14: Include BNC in every press release, for every brand | D14: Ongoing | F14: ☐ | G14: Use BNC's marketing systems
A15: 30 | B15: 1b. BNC Exhibition (end Oct) | C15: Confirm exhibition date, venue, stand size and what's included | D15: Now | F15: ☐ | G15: Date TBC – end of October
A16: 31 | B16: 1b. BNC Exhibition (end Oct) | C16: Find out what marketing BNC offers exhibitors – newsletters, social, website listings, press | D16: Now | F16: ☐
A17: 32 | B17: 1b. BNC Exhibition (end Oct) | C17: Get BNC logos, brand guidelines and exhibitor wording | D17: Oct | F17: ☐
A18: 33 | B18: 1b. BNC Exhibition (end Oct) | C18: Decide which brands we showcase and how – one Collective stand | D18: Oct | F18: ☐
A19: 43 | B19: 1c. Venue Sourcing | C19: Brainstorm our point of difference – every caterer wants the venues, why us? (Cat, Jessica, Lois) | D19: Now | F19: ☐ | G19: Whole Collective as one supplier: food, drink, styling, staffing, wellness, Latino
A20: 44 | B20: 1c. Venue Sourcing | C20: Write the point of difference in one line, plus 3 proof points | D20: Now | F20: ☐
A21: 45 | B21: 1c. Venue Sourcing | C21: Build the target venue list – type, capacity, current caterer, contact | D21: Now | F21: ☐
A22: 48 | B22: 1c. Venue Sourcing | C22: Christmas packages for venues | D22: Now | F22: ☐ | G22: Link with PenniBlack Christmas packages
A23: 55 | B23: 1c. Venue Sourcing | C23: Venue pipeline board in Monday – contacted, meeting, trial, on supplier list | D23: Mon 5 Oct | F23: ☐ | G23: Ask Yahya
A24: 57 | B24: 2. PenniBlack Catering & Events | C24: Christmas campaign to existing followers – social posts | D24: Oct–Dec | F24: ☐ | G24: Big follower base – use it
A25: 59 | B25: 2. PenniBlack Catering & Events | C25: Christmas packages with 'from £' prices | D25: Oct | F25: ☐
A26: 68 | B26: 3. Free Spirit Wellness | C26: Chase Momoko (Menier Venues) to confirm the date – push hard, nothing can be booked until it's set | D26: Now | F26: ☐ | G26: Hoping for Wed 21 Oct
A27: 69 | B27: 3. Free Spirit Wellness | C27: Confirm which Menier team members are coming and agree the run of show | D27: Once date set | F27: ☐ | G27: Purpose: the Menier team try it and review it
A28: 70 | B28: 3. Free Spirit Wellness | C28: Book workshop hosts – Ayurvedic scrubs, yoga, self-defence | D28: Once date set | F28: ☐ | G28: Waiting on date
A29: 80 | B29: 4. Pichi | C29: Send Momoko (Menier Venues) the full attendee list from the Pichi launch | D29: Mon 5 Oct | F29: ☐ | G29: Promised in Charlotte's email of 1 Oct – Cat
A30: 128 | B30: 9. Systems & Admin | C30: Team availability calendar in Monday – who's free to work when | D30: Oct | F30: ☐ | G30: Quick win – ask Yahya

Sheet Summary
A1: PenniBlack Collective – Task Summary
A2: Counts update automatically from the Task List tab.
A4: Section | B4: Now | C4: Next | D4: Later | E4: Total | F4: Done
A5: 0. Monday & Claude Setup | B5: =COUNTIFS('Task List'!$B$5:$B$142,$A5,'Task List'!$F$5:$F$142,"Now") -> 9 | C5: =COUNTIFS('Task List'!$B$5:$B$142,$A5,'Task List'!$F$5:$F$142,"Next") -> 4 | D5: =COUNTIFS('Task List'!$B$5:$B$142,$A5,'Task List'!$F$5:$F$142,"Later") -> 0 | E5: =SUM(B5:D5) -> 13 | F5: =COUNTIFS('Task List'!$B$5:$B$142,$A5,'Task List'!$I$5:$I$142,"Done") -> 0
A6: 1. All Brands | B6: =COUNTIFS('Task List'!$B$5:$B$142,$A6,'Task List'!$F$5:$F$142,"Now") -> 1 | C6: =COUNTIFS('Task List'!$B$5:$B$142,$A6,'Task List'!$F$5:$F$142,"Next") -> 12 | D6: =COUNTIFS('Task List'!$B$5:$B$142,$A6,'Task List'!$F$5:$F$142,"Later") -> 3 | E6: =SUM(B6:D6) -> 16 | F6: =COUNTIFS('Task List'!$B$5:$B$142,$A6,'Task List'!$I$5:$I$142,"Done") -> 0
A7: 1b. BNC Exhibition (end Oct) | B7: =COUNTIFS('Task List'!$B$5:$B$142,$A7,'Task List'!$F$5:$F$142,"Now") -> 4 | C7: =COUNTIFS('Task List'!$B$5:$B$142,$A7,'Task List'!$F$5:$F$142,"Next") -> 9 | D7: =COUNTIFS('Task List'!$B$5:$B$142,$A7,'Task List'!$F$5:$F$142,"Later") -> 0 | E7: =SUM(B7:D7) -> 13 | F7: =COUNTIFS('Task List'!$B$5:$B$142,$A7,'Task List'!$I$5:$I$142,"Done") -> 0
A8: 1c. Venue Sourcing | B8: =COUNTIFS('Task List'!$B$5:$B$142,$A8,'Task List'!$F$5:$F$142,"Now") -> 5 | C8: =COUNTIFS('Task List'!$B$5:$B$142,$A8,'Task List'!$F$5:$F$142,"Next") -> 9 | D8: =COUNTIFS('Task List'!$B$5:$B$142,$A8,'Task List'!$F$5:$F$142,"Later") -> 0 | E8: =SUM(B8:D8) -> 14 | F8: =COUNTIFS('Task List'!$B$5:$B$142,$A8,'Task List'!$I$5:$I$142,"Done") -> 0
A9: 2. PenniBlack Catering & Events | B9: =COUNTIFS('Task List'!$B$5:$B$142,$A9,'Task List'!$F$5:$F$142,"Now") -> 2 | C9: =COUNTIFS('Task List'!$B$5:$B$142,$A9,'Task List'!$F$5:$F$142,"Next") -> 8 | D9: =COUNTIFS('Task List'!$B$5:$B$142,$A9,'Task List'!$F$5:$F$142,"Later") -> 1 | E9: =SUM(B9:D9) -> 11 | F9: =COUNTIFS('Task List'!$B$5:$B$142,$A9,'Task List'!$I$5:$I$142,"Done") -> 0
A10: 3. Free Spirit Wellness | B10: =COUNTIFS('Task List'!$B$5:$B$142,$A10,'Task List'!$F$5:$F$142,"Now") -> 3 | C10: =COUNTIFS('Task List'!$B$5:$B$142,$A10,'Task List'!$F$5:$F$142,"Next") -> 7 | D10: =COUNTIFS('Task List'!$B$5:$B$142,$A10,'Task List'!$F$5:$F$142,"Later") -> 2 | E10: =SUM(B10:D10) -> 12 | F10: =COUNTIFS('Task List'!$B$5:$B$142,$A10,'Task List'!$I$5:$I$142,"Done") -> 0
A11: 4. Pichi | B11: =COUNTIFS('Task List'!$B$5:$B$142,$A11,'Task List'!$F$5:$F$142,"Now") -> 1 | C11: =COUNTIFS('Task List'!$B$5:$B$142,$A11,'Task List'!$F$5:$F$142,"Next") -> 1 | D11: =COUNTIFS('Task List'!$B$5:$B$142,$A11,'Task List'!$F$5:$F$142,"Later") -> 7 | E11: =SUM(B11:D11) -> 9 | F11: =COUNTIFS('Task List'!$B$5:$B$142,$A11,'Task List'!$I$5:$I$142,"Done") -> 0
A12: 5. Raquel's Staffing & Bar | B12: =COUNTIFS('Task List'!$B$5:$B$142,$A12,'Task List'!$F$5:$F$142,"Now") -> 0 | C12: =COUNTIFS('Task List'!$B$5:$B$142,$A12,'Task List'!$F$5:$F$142,"Next") -> 7 | D12: =COUNTIFS('Task List'!$B$5:$B$142,$A12,'Task List'!$F$5:$F$142,"Later") -> 0 | E12: =SUM(B12:D12) -> 7 | F12: =COUNTIFS('Task List'!$B$5:$B$142,$A12,'Task List'!$I$5:$I$142,"Done") -> 0
A13: 6. VENN Productions | B13: =COUNTIFS('Task List'!$B$5:$B$142,$A13,'Task List'!$F$5:$F$142,"Now") -> 0 | C13: =COUNTIFS('Task List'!$B$5:$B$142,$A13,'Task List'!$F$5:$F$142,"Next") -> 0 | D13: =COUNTIFS('Task List'!$B$5:$B$142,$A13,'Task List'!$F$5:$F$142,"Later") -> 4 | E13: =SUM(B13:D13) -> 4 | F13: =COUNTIFS('Task List'!$B$5:$B$142,$A13,'Task List'!$I$5:$I$142,"Done") -> 0
A14: 7. Be-Zing (Kids + Youth) | B14: =COUNTIFS('Task List'!$B$5:$B$142,$A14,'Task List'!$F$5:$F$142,"Now") -> 0 | C14: =COUNTIFS('Task List'!$B$5:$B$142,$A14,'Task List'!$F$5:$F$142,"Next") -> 9 | D14: =COUNTIFS('Task List'!$B$5:$B$142,$A14,'Task List'!$F$5:$F$142,"Later") -> 14 | E14: =SUM(B14:D14) -> 23 | F14: =COUNTIFS('Task List'!$B$5:$B$142,$A14,'Task List'!$I$5:$I$142,"Done") -> 0
A15: 8. The Edit (PBC Edit) | B15: =COUNTIFS('Task List'!$B$5:$B$142,$A15,'Task List'!$F$5:$F$142,"Now") -> 0 | C15: =COUNTIFS('Task List'!$B$5:$B$142,$A15,'Task List'!$F$5:$F$142,"Next") -> 0 | D15: =COUNTIFS('Task List'!$B$5:$B$142,$A15,'Task List'!$F$5:$F$142,"Later") -> 5 | E15: =SUM(B15:D15) -> 5 | F15: =COUNTIFS('Task List'!$B$5:$B$142,$A15,'Task List'!$I$5:$I$142,"Done") -> 0
A16: 9. Systems & Admin | B16: =COUNTIFS('Task List'!$B$5:$B$142,$A16,'Task List'!$F$5:$F$142,"Now") -> 1 | C16: =COUNTIFS('Task List'!$B$5:$B$142,$A16,'Task List'!$F$5:$F$142,"Next") -> 0 | D16: =COUNTIFS('Task List'!$B$5:$B$142,$A16,'Task List'!$F$5:$F$142,"Later") -> 10 | E16: =SUM(B16:D16) -> 11 | F16: =COUNTIFS('Task List'!$B$5:$B$142,$A16,'Task List'!$I$5:$I$142,"Done") -> 0
A17: Total | B17: =SUM(B5:B16) -> 26 | C17: =SUM(C5:C16) -> 66 | D17: =SUM(D5:D16) -> 46 | E17: =SUM(E5:E16) -> 138 | F17: =SUM(F5:F16) -> 0
A19: How to use
A20: • Start Here: the next two weeks only. Cat works from this, not the full list.
A21: • Task List: everything, grouped by brand. Filter by Stage = Now to see what's live. Owner, Stage and Status have dropdowns.
A22: • Every Tuesday: Cat ticks off what's done, then moves the next 3–5 tasks per person from Next to Now.
A23: • Once in Monday, each person uses 'My Work' to see only their own tasks.
A24: • Built so Yahya can import it straight into Monday: Section = group, Task = item, other columns = Monday columns.
A25: • Key dates: Free Spirit at the Menier Penthouse – hoping for Wed 21 Oct (awaiting Momoko). BNC exhibition – end of October (date TBC).
A26: • Still to check: Be-Zing Kids award ceremony details.

Sheet Team
A1: PenniBlack Collective – Team & Roles
A2: Rough seats, not fixed roles. October 2026.
A4: Name | B4: Seat | C4: Strengths | D4: Typical work | E4: Works closely with | F4: Starts | G4: Monday | H4: Claude
A5: Charlotte | B5: Founder | C5: Vision, concepts, all brands | D5: Own tasks in Monday – but doesn't run the system. Leads Be-Zing. | E5: Cat, Yahya | F5: Now | G5: Yes | H5: Premium
A6: Cat (Catrin Dimond) | B6: Chief of Marketing – runs Monday | C6: Social media, photography, video, design, concepts & styling | D6: Sets and manages everyone's tasks. Runs Tuesday meeting. Creates concepts (often off-site) and helps assemble them. Attends events, does case studies. | E6: Lois (content & web), Jessica (concepts & sales) | F6: Now | G6: Yes – Admin | H6: Premium
A7: Lois Burton | B7: Content, PR & Creative Lead | C7: Art PR degree, high-end photo & video, writing | D7: Web content, blogs, SEO, client experience (with Cat). PR. Leads Be-Zing marketing and The Edit. Attends fewer events. | E7: Cat | F7: End of October | G7: Yes | H7: Standard
A8: Jessica | B8: Sales & Events Manager | C8: Client-facing, events, strong styling eye | D8: Meets clients, sees spaces, brings concepts to life on site, styles her areas (e.g. bar). Goes to client meetings with Cat. Admin skills TBC. | E8: Cat, Lois | F8: Mid-October | G8: Yes | H8: TBC
A9: Danelle van Tonder | B9: Quotes & Client Liaison | C9: Organised, client care | D9: Quotes and client liaison – reactive. | E9: Ana | F9: Now | G9: Yes | H9: Standard
A10: Ana | B10: Quotes & Client Support (part-time) | C10: Cost calculator trained | D10: Assists Danelle on quotes and clients. Uses sales@ email. | E10: Danelle | F10: Now | G10: Yes | H10: No – review later
A11: Alex | B11: Systems & Events (flexible) | C11: Business studies student, free days | D11: Builds stock control system first (trial). Possibly more systems, packing, events, bar. | E11: Charlotte, Yahya | F11: When free | G11: TBC | H11: No
A12: Raquel | B12: Event Manager & Logistics | C12: On the ground | D12: Events, logistics, occasional site visits. Outside the admin system for now. Pichi input. | E12: Steph, Ana | F12: Now | G12: View only / later | H12: No
A13: Yahya (InfoVis) | B13: IT & Database Consultant | C13: Systems integration | D13: Monday structure, Claude connections, Xero, staff app review. | E13: Cat, Charlotte | F13: Mon 5 Oct | G13: Member | H13: Not yet
A14: Jess & Dave | B14: Collective partners – design | C14: Design & styling eye | D14: VENN Productions. Outside the admin system. | E14: Charlotte | F14: — | G14: No | H14: —
A15: Steph | B15: Runs Pichi | C15: Latino culture | D15: Pichi brainstorms and vision. Outside the admin system. | E15: Raquel, Ana, Cat | F15: — | G15: No | H15: —
A17: How they pair up
A18: • Cat + Lois: website content, blogs, writing, client experience, content & PR. They agree crossovers between them.
A19: • Cat + Jessica: concepts, styling and sales. Cat creates the concept, Jessica brings it to life at the event. Client meetings together.
A20: • Cat + Jessica + Lois: all brainstorm concepts and creative ideas.
A21: • Danelle + Ana: quotes and client liaison (reactive).
A22: • Rhythm: Cat sets tasks in Monday → Tuesday team meeting to review.

Sheet Task List
A1: PenniBlack Collective – Master Task List
A2: Stage: Now = next 2 weeks · Next = rest of Oct–Dec · Later = 2027 / once Now and Next are moving. Priority 1 = money before Christmas · 2 = build the brands · 3 = systems. Owner left blank for Cat to allocate.
A4: ID | B4: Section | C4: Workstream | D4: Task | E4: Priority | F4: Stage | G4: When | H4: Owner | I4: Status | J4: Notes
A5: 1 | B5: 0. Monday & Claude Setup | C5: Setup | D5: Check Monday trial status and end date | E5: 1 | F5: Now | G5: Fri 2 Oct | I5: Not started | J5: Cat – from the van
A6: 2 | B6: 0. Monday & Claude Setup | C6: Setup | D6: Upgrade Monday to Pro, monthly billing | E6: 1 | F6: Now | G6: Fri 2 Oct | I6: Not started | J6: Cat – call Charlotte for card
A7: 3 | B7: 0. Monday & Claude Setup | C7: Setup | D7: Invite Yahya to Monday as Member (info@infovis.co.uk) | E7: 1 | F7: Now | G7: Fri 2 Oct | I7: Not started | J7: Cat to email him once done
A8: 4 | B8: 0. Monday & Claude Setup | C8: Setup | D8: Make sure Cat is a Monday admin | E8: 1 | F8: Now | G8: Fri 2 Oct | I8: Not started
A9: 5 | B9: 0. Monday & Claude Setup | C9: Setup | D9: Send Yahya samples: spreadsheet, task list, marketing plan, targets, enquiry tracker extract | E9: 1 | F9: Now | G9: Weekend | I9: Not started | J9: This workbook covers the task list
A10: 6 | B10: 0. Monday & Claude Setup | C10: Setup | D10: Setup day with Yahya, Cat and Charlotte | E10: 1 | F10: Now | G10: Mon 5 Oct | I10: Not started
A11: 7 | B11: 0. Monday & Claude Setup | C11: Setup | D11: Build marketing board – one group per brand | E11: 1 | F11: Now | G11: Mon 5 Oct | I11: Not started | J11: Yahya
A12: 8 | B12: 0. Monday & Claude Setup | C12: Setup | D12: Load this task list into Monday | E12: 1 | F12: Now | G12: Mon 5 Oct | I12: Not started | J12: Yahya
A13: 9 | B13: 0. Monday & Claude Setup | C13: Setup | D13: Build goals & targets dashboard for the Tuesday meeting | E13: 1 | F13: Now | G13: Mon 5 Oct | I13: Not started | J13: Yahya
A14: 10 | B14: 0. Monday & Claude Setup | C14: Setup | D14: Connect Claude to Monday | E14: 1 | F14: Next | G14: Oct | I14: Not started | J14: Yahya
A15: 11 | B15: 0. Monday & Claude Setup | C15: Setup | D15: Add team to Monday (Danelle, Ana, Lois, Jessica, Alex as needed) | E15: 1 | F15: Next | G15: Oct | I15: Not started
A16: 12 | B16: 0. Monday & Claude Setup | C16: Setup | D16: Onboard Jessica – email, Monday, Claude (TBC) | E16: 1 | F16: Next | G16: Mid-Oct | I16: Not started
A17: 13 | B17: 0. Monday & Claude Setup | C17: Setup | D17: Onboard Lois – Monday, Claude Team (email done) | E17: 1 | F17: Next | G17: End Oct | I17: Not started
A18: 14 | B18: 1. All Brands | C18: Marketing plans | D18: Write a one-page marketing plan per brand: who buys, what we sell, where we find them, monthly targets | E18: 1 | F18: Next | G18: Oct | I18: Not started
A19: 15 | B19: 1. All Brands | C19: Marketing plans | D19: Set monthly targets per brand – enquiries, bookings, £ booked | E19: 1 | F19: Next | G19: Oct | I19: Not started
A20: 16 | B20: 1. All Brands | C20: Marketing plans | D20: Track goals completed vs targets – review every Tuesday | E20: 1 | F20: Next | G20: Weekly | I20: Not started
A21: 17 | B21: 1. All Brands | C21: Marketing plans | D21: Social media content calendar across all brands | E21: 1 | F21: Next | G21: Oct | I21: Not started
A22: 18 | B22: 1. All Brands | C22: Website | D22: Audit every page on every brand website – wording and what goes where | E22: 1 | F22: Next | G22: From end Oct | I22: Not started | J22: First job when Lois starts
A23: 19 | B23: 1. All Brands | C23: Website | D23: Check all website wording is right for SEO | E23: 1 | F23: Next | G23: From end Oct | I23: Not started
A24: 20 | B24: 1. All Brands | C24: Website | D24: Extend website wording where pages are thin | E24: 2 | F24: Later | G24: Nov–Dec | I24: Not started
A25: 21 | B25: 1. All Brands | C25: Website | D25: Bring case studies up to date on every site | E25: 1 | F25: Next | G25: From end Oct | I25: Not started
A26: 22 | B26: 1. All Brands | C26: Blogs | D26: Check blogs are generating SEO traffic | E26: 1 | F26: Next | G26: From end Oct | I26: Not started
A27: 23 | B27: 1. All Brands | C27: Blogs | D27: Blog calendar for each brand | E27: 2 | F27: Later | G27: Nov | I27: Not started
A28: 24 | B28: 1. All Brands | C28: Client experience | D28: Map the client journey: enquiry → quote → booking → event → follow-up | E28: 2 | F28: Later | G28: Nov | I28: Not started | J28: Cat + Lois brainstorm
A29: 25 | B29: 1. All Brands | C29: Client experience | D29: Collect reviews after every event – set a simple process | E29: 1 | F29: Next | G29: Oct | I29: Not started
A30: 26 | B30: 1. All Brands | C30: Brochures | D30: Check every brand has a brochure ready to send | E30: 1 | F30: Next | G30: Oct | I30: Not started
A31: 27 | B31: 1. All Brands | C31: Mail shots | D31: Mail shot plan for every brand – calendar and contact lists | E31: 1 | F31: Next | G31: Oct–Nov | I31: Not started
A32: 28 | B32: 1. All Brands | C32: PR | D32: Include BNC in every press release, for every brand | E32: 1 | F32: Now | G32: Ongoing | I32: Not started | J32: Use BNC's marketing systems
A33: 29 | B33: 1. All Brands | C33: PR | D33: Press release plan for each brand | E33: 1 | F33: Next | G33: Oct–Nov | I33: Not started
A34: 30 | B34: 1b. BNC Exhibition (end Oct) | C34: BNC Exhibition | D34: Confirm exhibition date, venue, stand size and what's included | E34: 1 | F34: Now | G34: Now | I34: Not started | J34: Date TBC – end of October
A35: 31 | B35: 1b. BNC Exhibition (end Oct) | C35: BNC Exhibition | D35: Find out what marketing BNC offers exhibitors – newsletters, social, website listings, press | E35: 1 | F35: Now | G35: Now | I35: Not started
A36: 32 | B36: 1b. BNC Exhibition (end Oct) | C36: BNC Exhibition | D36: Get BNC logos, brand guidelines and exhibitor wording | E36: 1 | F36: Now | G36: Oct | I36: Not started
A37: 33 | B37: 1b. BNC Exhibition (end Oct) | C37: BNC Exhibition | D37: Decide which brands we showcase and how – one Collective stand | E37: 1 | F37: Now | G37: Oct | I37: Not started
A38: 34 | B38: 1b. BNC Exhibition (end Oct) | C38: BNC Exhibition | D38: Stand concept, styling and layout | E38: 1 | F38: Next | G38: Oct | I38: Not started
A39: 35 | B39: 1b. BNC Exhibition (end Oct) | C39: BNC Exhibition | D39: Stand materials – banners, brochures, signage | E39: 1 | F39: Next | G39: Oct | I39: Not started
A40: 36 | B40: 1b. BNC Exhibition (end Oct) | C40: BNC Exhibition | D40: Tasting, demo or experience on the stand | E40: 1 | F40: Next | G40: Oct | I40: Not started
A41: 37 | B41: 1b. BNC Exhibition (end Oct) | C41: BNC Exhibition | D41: Staff rota for the stand | E41: 1 | F41: Next | G41: Oct | I41: Not started
A42: 38 | B42: 1b. BNC Exhibition (end Oct) | C42: BNC Exhibition | D42: Promote our attendance through BNC's marketing channels | E42: 1 | F42: Next | G42: Oct | I42: Not started
A43: 39 | B43: 1b. BNC Exhibition (end Oct) | C43: BNC Exhibition | D43: Promote our attendance on our own social media and mail shots | E43: 1 | F43: Next | G43: Oct | I43: Not started
A44: 40 | B44: 1b. BNC Exhibition (end Oct) | C44: BNC Exhibition | D44: Lead capture on the day – contact details and enquiries | E44: 1 | F44: Next | G44: Event day | I44: Not started
A45: 41 | B45: 1b. BNC Exhibition (end Oct) | C45: BNC Exhibition | D45: Photos and video on the day | E45: 1 | F45: Next | G45: Event day | I45: Not started
A46: 42 | B46: 1b. BNC Exhibition (end Oct) | C46: BNC Exhibition | D46: Follow up every lead within a week | E46: 1 | F46: Next | G46: Early Nov | I46: Not started
A47: 43 | B47: 1c. Venue Sourcing | C47: Venue Sourcing | D47: Brainstorm our point of difference – every caterer wants the venues, why us? (Cat, Jessica, Lois) | E47: 1 | F47: Now | G47: Now | I47: Not started | J47: Whole Collective as one supplier: food, drink, styling, staffing, wellness, Latino
A48: 44 | B48: 1c. Venue Sourcing | C48: Venue Sourcing | D48: Write the point of difference in one line, plus 3 proof points | E48: 1 | F48: Now | G48: Now | I48: Not started
A49: 45 | B49: 1c. Venue Sourcing | C49: Venue Sourcing | D49: Build the target venue list – type, capacity, current caterer, contact | E49: 1 | F49: Now | G49: Now | I49: Not started
A50: 46 | B50: 1c. Venue Sourcing | C50: Venue Sourcing | D50: Pick the top 20 venues to go after first | E50: 1 | F50: Next | G50: Oct | I50: Not started
A51: 47 | B51: 1c. Venue Sourcing | C51: Venue Sourcing | D51: Find out how each venue picks suppliers – preferred supplier lists, tenders, commission | E51: 1 | F51: Next | G51: Oct | I51: Not started
A52: 48 | B52: 1c. Venue Sourcing | C52: Venue Sourcing | D52: Christmas packages for venues | E52: 1 | F52: Now | G52: Now | I52: Not started | J52: Link with PenniBlack Christmas packages
A53: 49 | B53: 1c. Venue Sourcing | C53: Venue Sourcing | D53: Supper club packages | E53: 1 | F53: Next | G53: Oct | I53: Not started
A54: 50 | B54: 1c. Venue Sourcing | C54: Venue Sourcing | D54: Other packages – corporate, launches, wellness days, Latino nights | E54: 1 | F54: Next | G54: Oct–Nov | I54: Not started
A55: 51 | B55: 1c. Venue Sourcing | C55: Venue Sourcing | D55: Venue brochure / supplier pack | E55: 1 | F55: Next | G55: Oct | I55: Not started
A56: 52 | B56: 1c. Venue Sourcing | C56: Venue Sourcing | D56: Case studies to show venues | E56: 1 | F56: Next | G56: Oct–Nov | I56: Not started | J56: Use Free Spirit at Menier as the model
A57: 53 | B57: 1c. Venue Sourcing | C57: Venue Sourcing | D57: Outreach plan – email, call, visit | E57: 1 | F57: Next | G57: Oct | I57: Not started
A58: 54 | B58: 1c. Venue Sourcing | C58: Venue Sourcing | D58: Invite venue managers to a tasting or showcase | E58: 1 | F58: Next | G58: Oct–Nov | I58: Not started
A59: 55 | B59: 1c. Venue Sourcing | C59: Venue Sourcing | D59: Venue pipeline board in Monday – contacted, meeting, trial, on supplier list | E59: 1 | F59: Now | G59: Mon 5 Oct | I59: Not started | J59: Ask Yahya
A60: 56 | B60: 1c. Venue Sourcing | C60: Venue Sourcing | D60: Follow up and get onto preferred supplier lists | E60: 1 | F60: Next | G60: Nov–Dec | I60: Not started
A61: 57 | B61: 2. PenniBlack Catering & Events | C61: Christmas | D61: Christmas campaign to existing followers – social posts | E61: 1 | F61: Now | G61: Oct–Dec | I61: Not started | J61: Big follower base – use it
A62: 58 | B62: 2. PenniBlack Catering & Events | C62: Christmas | D62: Christmas mail shot to past clients and followers | E62: 1 | F62: Next | G62: Oct | I62: Not started
A63: 59 | B63: 2. PenniBlack Catering & Events | C63: Christmas | D63: Christmas packages with 'from £' prices | E63: 1 | F63: Now | G63: Oct | I63: Not started
A64: 60 | B64: 2. PenniBlack Catering & Events | C64: Christmas | D64: Christmas brochure | E64: 1 | F64: Next | G64: Oct | I64: Not started
A65: 61 | B65: 2. PenniBlack Catering & Events | C65: Christmas | D65: Fast follow-up on Christmas enquiries and quotes | E65: 1 | F65: Next | G65: Oct–Dec | I65: Not started | J65: Danelle + Ana
A66: 62 | B66: 2. PenniBlack Catering & Events | C66: Brand activations | D66: Gather photos and case studies from past brand activations | E66: 1 | F66: Next | G66: Oct | I66: Not started
A67: 63 | B67: 2. PenniBlack Catering & Events | C67: Brand activations | D67: Brand activation pitch – 'we bring your brand to life' | E67: 1 | F67: Next | G67: Oct | I67: Not started
A68: 64 | B68: 2. PenniBlack Catering & Events | C68: Brand activations | D68: Target list of companies to pitch | E68: 1 | F68: Next | G68: Oct | I68: Not started
A69: 65 | B69: 2. PenniBlack Catering & Events | C69: Brand activations | D69: Outreach and book meetings with target companies | E69: 1 | F69: Next | G69: Oct–Nov | I69: Not started
A70: 66 | B70: 2. PenniBlack Catering & Events | C70: Harvest Moon | D70: Write up Harvest Moon as the flagship concept example – photos, story, menu | E70: 1 | F70: Next | G70: Oct | I70: Not started
A71: 67 | B71: 2. PenniBlack Catering & Events | C71: Harvest Moon | D71: Develop more concepts in the same style for pitches | E71: 2 | F71: Later | G71: Nov–Jan | I71: Not started
A72: 68 | B72: 3. Free Spirit Wellness | C72: Showcase event | D72: Chase Momoko (Menier Venues) to confirm the date – push hard, nothing can be booked until it's set | E72: 1 | F72: Now | G72: Now | I72: Not started | J72: Hoping for Wed 21 Oct
A73: 69 | B73: 3. Free Spirit Wellness | C73: Showcase event | D73: Confirm which Menier team members are coming and agree the run of show | E73: 1 | F73: Now | G73: Once date set | I73: Not started | J73: Purpose: the Menier team try it and review it
A74: 70 | B74: 3. Free Spirit Wellness | C74: Showcase event | D74: Book workshop hosts – Ayurvedic scrubs, yoga, self-defence | E74: 1 | F74: Now | G74: Once date set | I74: Not started | J74: Waiting on date
A75: 71 | B75: 3. Free Spirit Wellness | C75: Showcase event | D75: Plan the food and menu | E75: 1 | F75: Next | G75: Oct | I75: Not started
A76: 72 | B76: 3. Free Spirit Wellness | C76: Showcase event | D76: Create a luxury concept and styling – every touchpoint high-end | E76: 1 | F76: Next | G76: Oct | I76: Not started | J76: Luxury experience is the brief
A77: 73 | B77: 3. Free Spirit Wellness | C77: Showcase event | D77: Videographer and photographer brief and shot list – film the whole experience | E77: 1 | F77: Next | G77: Oct | I77: Not started
A78: 74 | B78: 3. Free Spirit Wellness | C78: Showcase event | D78: Capture video testimonials and written reviews from the Menier team | E78: 1 | F78: Next | G78: Event day | I78: Not started
A79: 75 | B79: 3. Free Spirit Wellness | C79: After the event | D79: Write the case study | E79: 1 | F79: Next | G79: After event | I79: Not started
A80: 76 | B80: 3. Free Spirit Wellness | C80: After the event | D80: Marketing campaign to venues showing what we can do | E80: 1 | F80: Next | G80: After event | I80: Not started
A81: 77 | B81: 3. Free Spirit Wellness | C81: After the event | D81: Free Spirit brochure / venue pack | E81: 1 | F81: Next | G81: After event | I81: Not started
A82: 78 | B82: 3. Free Spirit Wellness | C82: After the event | D82: Add case study and gallery to website | E82: 2 | F82: Later | G82: Nov | I82: Not started
A83: 79 | B83: 3. Free Spirit Wellness | C83: Research | D83: Research what's trending in the wellness industry | E83: 2 | F83: Later | G83: Nov | I83: Not started
A84: 80 | B84: 4. Pichi | C84: Launch follow-up | D84: Send Momoko (Menier Venues) the full attendee list from the Pichi launch | E84: 1 | F84: Now | G84: Mon 5 Oct | I84: Not started | J84: Promised in Charlotte's email of 1 Oct – Cat
A85: 81 | B85: 4. Pichi | C85: Launch follow-up | D85: Use launch photos and videos for a case study and social posts | E85: 1 | F85: Next | G85: Oct | I85: Not started | J85: Quick win
A86: 82 | B86: 4. Pichi | C86: Vision | D86: Brainstorm sessions with Steph, Raquel and Ana | E86: 2 | F86: Later | G86: Oct–Nov | I86: Not started
A87: 83 | B87: 4. Pichi | C87: Vision | D87: Define the Pichi vision – music, food, energy, Zumba, all of Latino culture | E87: 2 | F87: Later | G87: Nov | I87: Not started
A88: 84 | B88: 4. Pichi | C88: Website | D88: Plan the website structure | E88: 2 | F88: Later | G88: Nov | I88: Not started
A89: 85 | B89: 4. Pichi | C89: Website | D89: Write all website wording | E89: 2 | F89: Later | G89: Nov–Dec | I89: Not started
A90: 86 | B90: 4. Pichi | C90: Website | D90: Build and launch the website | E90: 2 | F90: Later | G90: Dec–Jan | I90: Not started
A91: 87 | B91: 4. Pichi | C91: Marketing | D91: Pichi marketing materials – brochure and social templates | E91: 2 | F91: Later | G91: Nov | I91: Not started
A92: 88 | B92: 4. Pichi | C92: Marketing | D92: Pichi social media pages and content | E92: 2 | F92: Later | G92: Nov | I92: Not started
A93: 89 | B93: 5. Raquel's Staffing & Bar | C93: Marketing plan | D93: Marketing plan built on 'we make people look cool' | E93: 1 | F93: Next | G93: Oct | I93: Not started
A94: 90 | B94: 5. Raquel's Staffing & Bar | C94: Showcase | D94: Photoshoot of the regular team – the great faces and attitude | E94: 1 | F94: Next | G94: Oct | I94: Not started
A95: 91 | B95: 5. Raquel's Staffing & Bar | C95: Showcase | D95: Team profiles and social posts featuring the staff | E95: 1 | F95: Next | G95: Oct–Dec | I95: Not started
A96: 92 | B96: 5. Raquel's Staffing & Bar | C96: Sales | D96: Staffing brochure for venues and agencies | E96: 1 | F96: Next | G96: Oct | I96: Not started
A97: 93 | B97: 5. Raquel's Staffing & Bar | C97: Sales | D97: Target list of venues, agencies and event companies | E97: 1 | F97: Next | G97: Oct | I97: Not started
... A103: 99 | B103: 6. VENN Productions | C103: Sales | D103: VENN brochure | E103: 2 | F103: Later | G103: Dec | I103: Not started
A104: 100 | B104: 7. Be-Zing (Kids + Youth) | C104: Be-Zing Kids | D104: Kids: marketing plan – its own plan, targets and audience (schools) | E104: 1 | F104: Next | G104: Oct | I104: Not started | J104: Separate from Youth
A105: 101 | B105: 7. Be-Zing (Kids + Youth) | C105: Be-Zing Kids | D105: Kids: bring the wellness wheel to life – content explaining each part | E105: 1 | F105: Next | G105: Oct–Nov | I105: Not started
A106: 102 | B106: 7. Be-Zing (Kids + Youth) | C106: Be-Zing Kids | D106: Kids: introduce Be-Zing Kids to schools – intro pack / email | E106: 1 | F106: Next | G106: Oct–Nov | I106: Not started
...
