Workbook

Sheet Invoice Log
A1: JOB DETAILS | K1: QUOTE & INVOICE | V1: PAYMENTS RECEIVED | AE1: WHERE IT STANDS | AI1: REFUND - what actually goes back | AO1: FOR THE COLLECTIVE | AQ1: NOTES
A2: Owner | B2: Our Company | C2: Type | D2: INV Number | E2: Client / Booking Name | F2: Event Start | G2: Event End | H2: Invoice Date | I2: New / Repeat | J2: STATUS | K2: Covers | L2: Quote Total (ex VAT) | M2: Cost per Head | N2: VAT Rate | O2: VAT | P2: Total (inc VAT) | Q2: Deposit Req? | R2: Deposit override | S2: Damage Deposit | T2: INVOICE TOTAL (inc deposit) | U2: 1st Invoice (50% + dep) | V2: Payment 1 | W2: Method | X2: Date | Y2: Payment 2 | Z2: Method | AA2: Date | AB2: Payment 3 | AC2: Method | AD2: Date | AE2: TOTAL PAID | AF2: % Paid | AG2: BALANCE OWED | AH2: Days Overdue | AI2: REFUND DUE | AJ2: Account Name | AK2: Sort Code | AL2: Sort Code | AM2: Refund Method | AN2: Refund Paid Date | AO2: DEPOSIT +/- | AP2: FINAL VALUE (ex VAT) | AQ2: Comments | AR2: Event Ref | AS2: Event Mth | AT2: Yr
A3: Danelle | B3: Penni Black | C3: C | D3: 22004198 | E3: JUST | F3: 46037 | H3: 46028 | I3: N | J3: Complete | K3: 120 | L3: 9809.5 | M3: =IF(OR($K3="",$L3=""),"",$L3/$K3) -> 81.745833 | N3: 0.2 | O3: =IF($L3="","",$L3*IF($N3="",Settings!$J$11,$N3)) -> 1961.9 | P3: =IF($L3="","",$L3+$O3) -> 11771.4 | Q3: Yes | S3: =IF($L3="","",IF($Q3<>"Yes",0,IF($R3<>"",$R3,ROUND($L3*Settings!$J$4,2)))) -> 980.95 | T3: =IF($L3="","",$P3+$S3) -> 12752.35 | U3: =IF($L3="","",ROUND($P3/2,2)+$S3) -> 6866.65 | V3: 9468.29 | W3: CC | X3: 46031 | AE3: =IF($L3="","",SUM($V3,$Y3,$AB3)) -> 9468.29 | AF3: =IF(OR($L3="",$T3=0),"",IF(OR($J3="Complete",$J3="Paid in Full"),1,$AE3/$T3)) -> 1 | AG3: =IF($L3="","",IF(OR($J3="Cancelled",$J3="Complete",$J3="Paid in Full"),0,ROUND($T3-$AE3,2))) -> 0 | AH3: =IF(OR($L3="",$H3="",$AG3<=0),"",MAX(0,TODAY()-($H3+Settings!$J$6))) | AI3: 980.95 | AM3: CC | AN3: 46042 | AO3: =IF(OR($L3="",$S3=0,$AI3=""),0,ROUND($S3-$AI3,2)) -> 0 | AP3: =IF($L3="","",ROUND($L3+$AO3,2)) -> 9809.5 | AR3: =IF($L3="","",IF(ISNUMBER($F3),$F3,IF(ISNUMBER($G3),$G3,""))) -> 46037 | AS3: =IF(OR($L3="",$AR3=""),"",DATE(YEAR($AR3),MONTH($AR3),1)) -> 46023 | AT3: =IF($L3="","",IF($AR3<>"",YEAR($AR3),IF(ISNUMBER($H3),YEAR($H3),""))) -> 2026
A4: Danelle | B4: Penni Black | C4: C | D4: 22004199 | E4: London Review of Books | F4: 46038 | H4: 46030 | I4: N | J4: Complete | K4: 60 | L4: 2135.3 | M4: =IF(OR($K4="",$L4=""),"",$L4/$K4) -> 35.588333 | N4: 0.2 | O4: =IF($L4="","",$L4*IF($N4="",Settings!$J$11,$N4)) -> 427.06 | P4: =IF($L4="","",$L4+$O4) -> 2562.36 | Q4: Yes | S4: =IF($L4="","",IF($Q4<>"Yes",0,IF($R4<>"",$R4,ROUND($L4*Settings!$J$4,2)))) -> 213.53 | T4: =IF($L4="","",$P4+$S4) -> 2775.89 | U4: =IF($L4="","",ROUND($P4/2,2)+$S4) -> 1494.71 | V4: 2775.89 | W4: CC | X4: 46031 | AE4: =IF($L4="","",SUM($V4,$Y4,$AB4)) -> 2775.89 | AF4: =IF(OR($L4="",$T4=0),"",IF(OR($J4="Complete",$J4="Paid in Full"),1,$AE4/$T4)) -> 1 | AG4: =IF($L4="","",IF(OR($J4="Cancelled",$J4="Complete",$J4="Paid in Full"),0,ROUND($T4-$AE4,2))) -> 0 | AH4: =IF(OR($L4="",$H4="",$AG4<=0),"",MAX(0,TODAY()-($H4+Settings!$J$6))) | AI4: 213.53 | AM4: CC | AN4: 46042 | AO4: =IF(OR($L4="",$S4=0,$AI4=""),0,ROUND($S4-$AI4,2)) -> 0 | AP4: =IF($L4="","",ROUND($L4+$AO4,2)) -> 2135.3 | AR4: =IF($L4="","",IF(ISNUMBER($F4),$F4,IF(ISNUMBER($G4),$G4,""))) -> 46038 | AS4: =IF(OR($L4="",$AR4=""),"",DATE(YEAR($AR4),MONTH($AR4),1)) -> 46023 | AT4: =IF($L4="","",IF($AR4<>"",YEAR($AR4),IF(ISNUMBER($H4),YEAR($H4),""))) -> 2026
A5: Danelle | B5: Penni Black | C5: C | D5: 22004200 | E5: Berkeley Homes Capital | F5: 46044 | H5: 46030 | I5: R | J5: Complete | K5: 60 | L5: 2106 | M5: =IF(OR($K5="",$L5=""),"",$L5/$K5) -> 35.1 | N5: 0.2 | O5: =IF($L5="","",$L5*IF($N5="",Settings!$J$11,$N5)) -> 421.2 | P5: =IF($L5="","",$L5+$O5) -> 2527.2 | Q5: No | S5: =IF($L5="","",IF($Q5<>"Yes",0,IF($R5<>"",$R5,ROUND($L5*Settings!$J$4,2)))) -> 0 | T5: =IF($L5="","",$P5+$S5) -> 2527.2 | U5: =IF($L5="","",ROUND($P5/2,2)+$S5) -> 1263.6 | V5: 2527.2 | W5: BACS | Y5: 572.4 | Z5: BACS | AA5: 46075 | AE5: =IF($L5="","",SUM($V5,$Y5,$AB5)) -> 3099.6 | AF5: =IF(OR($L5="",$T5=0),"",IF(OR($J5="Complete",$J5="Paid in Full"),1,$AE5/$T5)) -> 1 | AG5: =IF($L5="","",IF(OR($J5="Cancelled",$J5="Complete",$J5="Paid in Full"),0,ROUND($T5-$AE5,2))) -> 0 | AH5: =IF(OR($L5="",$H5="",$AG5<=0),"",MAX(0,TODAY()-($H5+Settings!$J$6))) | AO5: =IF(OR($L5="",$S5=0,$AI5=""),0,ROUND($S5-$AI5,2)) -> 0 | AP5: =IF($L5="","",ROUND($L5+$AO5,2)) -> 2106 | AR5: =IF($L5="","",IF(ISNUMBER($F5),$F5,IF(ISNUMBER($G5),$G5,""))) -> 46044 | AS5: =IF(OR($L5="",$AR5=""),"",DATE(YEAR($AR5),MONTH($AR5),1)) -> 46023 | AT5: =IF($L5="","",IF($AR5<>"",YEAR($AR5),IF(ISNUMBER($H5),YEAR($H5),""))) -> 2026
A6: Danelle | B6: Penni Black | C6: C | D6: 22004201 | E6: Helaba Landesbank Hessen-Thüringen | F6: 46044 | H6: 46030 | I6: R | J6: Complete | K6: 55 | L6: 6799.5 | M6: =IF(OR($K6="",$L6=""),"",$L6/$K6) -> 123.62727 | N6: 0.2 | O6: =IF($L6="","",$L6*IF($N6="",Settings!$J$11,$N6)) -> 1359.9 | P6: =IF($L6="","",$L6+$O6) -> 8159.4 | Q6: Yes | S6: =IF($L6="","",IF($Q6<>"Yes",0,IF($R6<>"",$R6,ROUND($L6*Settings!$J$4,2)))) -> 679.95 | T6: =IF($L6="","",$P6+$S6) -> 8839.35 | U6: =IF($L6="","",ROUND($P6/2,2)+$S6) -> 4759.65 | AE6: =IF($L6="","",SUM($V6,$Y6,$AB6)) -> 0 | AF6: =IF(OR($L6="",$T6=0),"",IF(OR($J6="Complete",$J6="Paid in Full"),1,$AE6/$T6)) -> 1 | AG6: =IF($L6="","",IF(OR($J6="Cancelled",$J6="Complete",$J6="Paid in Full"),0,ROUND($T6-$AE6,2))) -> 0 | AH6: =IF(OR($L6="",$H6="",$AG6<=0),"",MAX(0,TODAY()-($H6+Settings!$J$6))) | AI6: 679.95 | AJ6: Landesbank Hessen-Thuringen Girozentrale | AK6: 5005 0000 | AL6: 096-2211-009 | AM6: BACS | AN6: 46066 | AO6: =IF(OR($L6="",$S6=0,$AI6=""),0,ROUND($S6-$AI6,2)) -> 0 | AP6: =IF($L6="","",ROUND($L6+$AO6,2)) -> 6799.5 | AR6: =IF($L6="","",IF(ISNUMBER($F6),$F6,IF(ISNUMBER($G6),$G6,""))) -> 46044 | AS6: =IF(OR($L6="",$AR6=""),"",DATE(YEAR($AR6),MONTH($AR6),1)) -> 46023 | AT6: =IF($L6="","",IF($AR6<>"",YEAR($AR6),IF(ISNUMBER($H6),YEAR($H6),""))) -> 2026
A7: Danelle | B7: Penni Black | C7: C | D7: 22004202 | E7: AngloGold - Day 1 | F7: 46069 | H7: 46034 | I7: N | J7: Complete | K7: 20 | L7: 3288.5 | M7: =IF(OR($K7="",$L7=""),"",$L7/$K7) -> 164.425 | N7: 0.2 | O7: =IF($L7="","",$L7*IF($N7="",Settings!$J$11,$N7)) -> 657.7 | P7: =IF($L7="","",$L7+$O7) -> 3946.2 | Q7: Yes | S7: =IF($L7="","",IF($Q7<>"Yes",0,IF($R7<>"",$R7,ROUND($L7*Settings!$J$4,2)))) -> 328.85 | T7: =IF($L7="","",$P7+$S7) -> 4275.05 | U7: =IF($L7="","",ROUND($P7/2,2)+$S7) -> 2301.95 | V7: 1080 | W7: CC | X7: 46037 | Y7: 10599.85 | Z7: BACS | AA7: 46065 | AE7: =IF($L7="","",SUM($V7,$Y7,$AB7)) -> 11679.85 | AF7: =IF(OR($L7="",$T7=0),"",IF(OR($J7="Complete",$J7="Paid in Full"),1,$AE7/$T7)) -> 1 | AG7: =IF($L7="","",IF(OR($J7="Cancelled",$J7="Complete",$J7="Paid in Full"),0,ROUND($T7-$AE7,2))) -> 0 | AH7: =IF(OR($L7="",$H7="",$AG7<=0),"",MAX(0,TODAY()-($H7+Settings!$J$6))) | AI7: 328.85 | AJ7: AngloGold Ashanti PLC | AK7: IBAN: GB48CHAS60924280037769 | AL7: 80037769 | AM7: BACS | AN7: 46089 | AO7: =IF(OR($L7="",$S7=0,$AI7=""),0,ROUND($S7-$AI7,2)) -> 0 | AP7: =IF($L7="","",ROUND($L7+$AO7,2)) -> 3288.5 | AR7: =IF($L7="","",IF(ISNUMBER($F7),$F7,IF(ISNUMBER($G7),$G7,""))) -> 46069 | AS7: =IF(OR($L7="",$AR7=""),"",DATE(YEAR($AR7),MONTH($AR7),1)) -> 46054 | AT7: =IF($L7="","",IF($AR7<>"",YEAR($AR7),IF(ISNUMBER($H7),YEAR($H7),""))) -> 2026
A8: Danelle | B8: Penni Black | C8: C | D8: 22004203 | E8: AngloGold - Day 2 | F8: 46070 | H8: 46034 | I8: N | J8: Complete | K8: 20 | L8: 3302 | M8: =IF(OR($K8="",$L8=""),"",$L8/$K8) -> 165.1 | N8: 0.2 | O8: =IF($L8="","",$L8*IF($N8="",Settings!$J$11,$N8)) -> 660.4 | P8: =IF($L8="","",$L8+$O8) -> 3962.4 | Q8: Yes | S8: =IF($L8="","",IF($Q8<>"Yes",0,IF($R8<>"",$R8,ROUND($L8*Settings!$J$4,2)))) -> 330.2 | T8: =IF($L8="","",$P8+$S8) -> 4292.6 | U8: =IF($L8="","",ROUND($P8/2,2)+$S8) -> 2311.4 | AE8: =IF($L8="","",SUM($V8,$Y8,$AB8)) -> 0 | AF8: =IF(OR($L8="",$T8=0),"",IF(OR($J8="Complete",$J8="Paid in Full"),1,$AE8/$T8)) -> 1 | AG8: =IF($L8="","",IF(OR($J8="Cancelled",$J8="Complete",$J8="Paid in Full"),0,ROUND($T8-$AE8,2))) -> 0 | AH8: =IF(OR($L8="",$H8="",$AG8<=0),"",MAX(0,TODAY()-($H8+Settings!$J$6))) | AI8: 330.2 | AO8: =IF(OR($L8="",$S8=0,$AI8=""),0,ROUND($S8-$AI8,2)) -> 0 | AP8: =IF($L8="","",ROUND($L8+$AO8,2)) -> 3302 | AR8: =IF($L8="","",IF(ISNUMBER($F8),$F8,IF(ISNUMBER($G8),$G8,""))) -> 46070 | AS8: =IF(OR($L8="",$AR8=""),"",DATE(YEAR($AR8),MONTH($AR8),1)) -> 46054 | AT8: =IF($L8="","",IF($AR8<>"",YEAR($AR8),IF(ISNUMBER($H8),YEAR($H8),""))) -> 2026
A9: Danelle | B9: Penni Black | C9: C | D9: 22004204 | E9: AngloGold - Day 3 | F9: 46071 | H9: 46034 | I9: N | J9: Complete | K9: 20 | L9: 2394 | M9: =IF(OR($K9="",$L9=""),"",$L9/$K9) -> 119.7 | N9: 0.2 | O9: =IF($L9="","",$L9*IF($N9="",Settings!$J$11,$N9)) -> 478.8 | P9: =IF($L9="","",$L9+$O9) -> 2872.8 | Q9: Yes | S9: =IF($L9="","",IF($Q9<>"Yes",0,IF($R9<>"",$R9,ROUND($L9*Settings!$J$4,2)))) -> 239.4 | T9: =IF($L9="","",$P9+$S9) -> 3112.2 | U9: =IF($L9="","",ROUND($P9/2,2)+$S9) -> 1675.8 | AE9: =IF($L9="","",SUM($V9,$Y9,$AB9)) -> 0 | AF9: =IF(OR($L9="",$T9=0),"",IF(OR($J9="Complete",$J9="Paid in Full"),1,$AE9/$T9)) -> 1 | AG9: =IF($L9="","",IF(OR($J9="Cancelled",$J9="Complete",$J9="Paid in Full"),0,ROUND($T9-$AE9,2))) -> 0 | AH9: =IF(OR($L9="",$H9="",$AG9<=0),"",MAX(0,TODAY()-($H9+Settings!$J$6))) | AI9: 239.4 | AO9: =IF(OR($L9="",$S9=0,$AI9=""),0,ROUND($S9-$AI9,2)) -> 0 | AP9: =IF($L9="","",ROUND($L9+$AO9,2)) -> 2394 | AR9: =IF($L9="","",IF(ISNUMBER($F9),$F9,IF(ISNUMBER($G9),$G9,""))) -> 46071 | AS9: =IF(OR($L9="",$AR9=""),"",DATE(YEAR($AR9),MONTH($AR9),1)) -> 46054 | AT9: =IF($L9="","",IF($AR9<>"",YEAR($AR9),IF(ISNUMBER($H9),YEAR($H9),""))) -> 2026
A10: Danelle | B10: Penni Black | C10: C | D10: 22004205 | E10: Aesop | F10: 46044 | H10: 46036 | I10: N | J10: Complete | K10: 200 | L10: 7765 | M10: =IF(OR($K10="",$L10=""),"",$L10/$K10) -> 38.825 | N10: 0.2 | O10: =IF($L10="","",$L10*IF($N10="",Settings!$J$11,$N10)) -> 1553 | P10: =IF($L10="","",$L10+$O10) -> 9318 | Q10: Yes | S10: =IF($L10="","",IF($Q10<>"Yes",0,IF($R10<>"",$R10,ROUND($L10*Settings!$J$4,2)))) -> 776.5 | T10: =IF($L10="","",$P10+$S10) -> 10094.5 | U10: =IF($L10="","",ROUND($P10/2,2)+$S10) -> 5435.5 | V10: 10094.5 | W10: CC | X10: 46037 | AE10: =IF($L10="","",SUM($V10,$Y10,$AB10)) -> 10094.5 | AF10: =IF(OR($L10="",$T10=0),"",IF(OR($J10="Complete",$J10="Paid in Full"),1,$AE10/$T10)) -> 1 | AG10: =IF($L10="","",IF(OR($J10="Cancelled",$J10="Complete",$J10="Paid in Full"),0,ROUND($T10-$AE10,2))) -> 0 | AH10: =IF(OR($L10="",$H10="",$AG10<=0),"",MAX(0,TODAY()-($H10+Settings!$J$6))) | AI10: 776.5 | AM10: CC | AN10: 46048 | AO10: =IF(OR($L10="",$S10=0,$AI10=""),0,ROUND($S10-$AI10,2)) -> 0 | AP10: =IF($L10="","",ROUND($L10+$AO10,2)) -> 7765 | AR10: =IF($L10="","",IF(ISNUMBER($F10),$F10,IF(ISNUMBER($G10),$G10,""))) -> 46044 | AS10: =IF(OR($L10="",$AR10=""),"",DATE(YEAR($AR10),MONTH($AR10),1)) -> 46023 | AT10: =IF($L10="","",IF($AR10<>"",YEAR($AR10),IF(ISNUMBER($H10),YEAR($H10),""))) -> 2026
A11: Danelle | B11: Penni Black | C11: C | D11: 22004206 | E11: The Payment Association (Emerging Payments Ventures) | F11: 46241 | H11: 46037 | I11: R | J11: Complete | K11: 45 | L11: 5642.45 | M11: =IF(OR($K11="",$L11=""),"",$L11/$K11) -> 125.38778 | N11: 0.2 | O11: =IF($L11="","",$L11*IF($N11="",Settings!$J$11,$N11)) -> 1128.49 | P11: =IF($L11="","",$L11+$O11) -> 6770.94 | Q11: Yes | S11: =IF($L11="","",IF($Q11<>"Yes",0,IF($R11<>"",$R11,ROUND($L11*Settings!$J$4,2)))) -> 564.25 | T11: =IF($L11="","",$P11+$S11) -> 7335.19 | U11: =IF($L11="","",ROUND($P11/2,2)+$S11) -> 3949.72 | V11: 2996.1 | W11: BACS | X11: 46043 | Y11: 4339.08 | Z11: BACS | AA11: 46241 | AE11: =IF($L11="","",SUM($V11,$Y11,$AB11)) -> 7335.18 | AF11: =IF(OR($L11="",$T11=0),"",IF(OR($J11="Complete",$J11="Paid in Full"),1,$AE11/$T11)) -> 1 | AG11: =IF($L11="","",IF(OR($J11="Cancelled",$J11="Complete",$J11="Paid in Full"),0,ROUND($T11-$AE11,2))) -> 0 | AH11: =IF(OR($L11="",$H11="",$AG11<=0),"",MAX(0,TODAY()-($H11+Settings!$J$6))) | AI11: 564.25 | AM11: BACS | AN11: 46275 | AO11: =IF(OR($L11="",$S11=0,$AI11=""),0,ROUND($S11-$AI11,2)) -> 0 | AP11: =IF($L11="","",ROUND($L11+$AO11,2)) -> 5642.45 | AR11: =IF($L11="","",IF(ISNUMBER($F11),$F11,IF(ISNUMBER($G11),$G11,""))) -> 46241 | AS11: =IF(OR($L11="",$AR11=""),"",DATE(YEAR($AR11),MONTH($AR11),1)) -> 46235 | AT11: =IF($L11="","",IF($AR11<>"",YEAR($AR11),IF(ISNUMBER($H11),YEAR($H11),""))) -> 2026
A12: Danelle | B12: Penni Black | C12: C | D12: 22004207 | E12: George Jensen Limited | F12: 46077 | H12: 46037 | I12: R | J12: Complete | K12: 40 | L12: 2858.6 | M12: =IF(OR($K12="",$L12=""),"",$L12/$K12) -> 71.465 | N12: 0.2 | O12: =IF($L12="","",$L12*IF($N12="",Settings!$J$11,$N12)) -> 571.72 | P12: =IF($L12="","",$L12+$O12) -> 3430.32 | Q12: Yes | S12: =IF($L12="","",IF($Q12<>"Yes",0,IF($R12<>"",$R12,ROUND($L12*Settings!$J$4,2)))) -> 285.86 | T12: =IF($L12="","",$P12+$S12) -> 3716.18 | U12: =IF($L12="","",ROUND($P12/2,2)+$S12) -> 2001.02 | V12: 1605.08 | W12: CC | X12: 46037 | Y12: 1806.89 | Z12: CC | AA12: 46069 | AE12: =IF($L12="","",SUM($V12,$Y12,$AB12)) -> 3411.97 | AF12: =IF(OR($L12="",$T12=0),"",IF(OR($J12="Complete",$J12="Paid in Full"),1,$AE12/$T12)) -> 1 | AG12: =IF($L12="","",IF(OR($J12="Cancelled",$J12="Complete",$J12="Paid in Full"),0,ROUND($T12-$AE12,2))) -> 0 | AH12: =IF(OR($L12="",$H12="",$AG12<=0),"",MAX(0,TODAY()-($H12+Settings!$J$6))) | AI12: 285.86 | AM12: CC | AN12: 46091 | AO12: =IF(OR($L12="",$S12=0,$AI12=""),0,ROUND($S12-$AI12,2)) -> 0 | AP12: =IF($L12="","",ROUND($L12+$AO12,2)) -> 2858.6 | AR12: =IF($L12="","",IF(ISNUMBER($F12),$F12,IF(ISNUMBER($G12),$G12,""))) -> 46077 | AS12: =IF(OR($L12="",$AR12=""),"",DATE(YEAR($AR12),MONTH($AR12),1)) -> 46054 | AT12: =IF($L12="","",IF($AR12<>"",YEAR($AR12),IF(ISNUMBER($H12),YEAR($H12),""))) -> 2026
A13: Danelle | B13: Penni Black | C13: C | D13: 22004208 | E13: SGN - Day 1 | F13: 46050 | H13: 46038 | I13: R | J13: Complete | K13: 27 | L13: 1381.9 | M13: =IF(OR($K13="",$L13=""),"",$L13/$K13) -> 51.181481 | N13: 0.2 | O13: =IF($L13="","",$L13*IF($N13="",Settings!$J$11,$N13)) -> 276.38 | P13: =IF($L13="","",$L13+$O13) -> 1658.28 | Q13: No | S13: =IF($L13="","",IF($Q13<>"Yes",0,IF($R13<>"",$R13,ROUND($L13*Settings!$J$4,2)))) -> 0 | T13: =IF($L13="","",$P13+$S13) -> 1658.28 | U13: =IF($L13="","",ROUND($P13/2,2)+$S13) -> 829.14 | V13: 1658.28 | W13: CC | X13: 46041 | AE13: =IF($L13="","",SUM($V13,$Y13,$AB13)) -> 1658.28 | AF13: =IF(OR($L13="",$T13=0),"",IF(OR($J13="Complete",$J13="Paid in Full"),1,$AE13/$T13)) -> 1 | AG13: =IF($L13="","",IF(OR($J13="Cancelled",$J13="Complete",$J13="Paid in Full"),0,ROUND($T13-$AE13,2))) -> 0 | AH13: =IF(OR($L13="",$H13="",$AG13<=0),"",MAX(0,TODAY()-($H13+Settings!$J$6))) | AO13: =IF(OR($L13="",$S13=0,$AI13=""),0,ROUND($S13-$AI13,2)) -> 0 | AP13: =IF($L13="","",ROUND($L13+$AO13,2)) -> 1381.9 | AR13: =IF($L13="","",IF(ISNUMBER($F13),$F13,IF(ISNUMBER($G13),$G13,""))) -> 46050 | AS13: =IF(OR($L13="",$AR13=""),"",DATE(YEAR($AR13),MONTH($AR13),1)) -> 46023 | AT13: =IF($L13="","",IF($AR13<>"",YEAR($AR13),IF(ISNUMBER($H13),YEAR($H13),""))) -> 2026
A14: Danelle | B14: Penni Black | C14: C | D14: 22004209 | E14: SGN - Day 2 | F14: 46051 | H14: 46038 | I14: R | J14: Complete | K14: 30 | L14: 1478.5 | M14: =IF(OR($K14="",$L14=""),"",$L14/$K14) -> 49.283333 | N14: 0.2 | O14: =IF($L14="","",$L14*IF($N14="",Settings!$J$11,$N14)) -> 295.7 | P14: =IF($L14="","",$L14+$O14) -> 1774.2 | Q14: No | S14: =IF($L14="","",IF($Q14<>"Yes",0,IF($R14<>"",$R14,ROUND($L14*Settings!$J$4,2)))) -> 0 | T14: =IF($L14="","",$P14+$S14) -> 1774.2 | U14: =IF($L14="","",ROUND($P14/2,2)+$S14) -> 887.1 | V14: 1774.2 | W14: CC | X14: 46041 | AE14: =IF($L14="","",SUM($V14,$Y14,$AB14)) -> 1774.2 | AF14: =IF(OR($L14="",$T14=0),"",IF(OR($J14="Complete",$J14="Paid in Full"),1,$AE14/$T14)) -> 1 | AG14: =IF($L14="","",IF(OR($J14="Cancelled",$J14="Complete",$J14="Paid in Full"),0,ROUND($T14-$AE14,2))) -> 0 | AH14: =IF(OR($L14="",$H14="",$AG14<=0),"",MAX(0,TODAY()-($H14+Settings!$J$6))) | AO14: =IF(OR($L14="",$S14=0,$AI14=""),0,ROUND($S14-$AI14,2)) -> 0 | AP14: =IF($L14="","",ROUND($L14+$AO14,2)) -> 1478.5 | AR14: =IF($L14="","",IF(ISNUMBER($F14),$F14,IF(ISNUMBER($G14),$G14,""))) -> 46051 | AS14: =IF(OR($L14="",$AR14=""),"",DATE(YEAR($AR14),MONTH($AR14),1)) -> 46023 | AT14: =IF($L14="","",IF($AR14<>"",YEAR($AR14),IF(ISNUMBER($H14),YEAR($H14),""))) -> 2026
A15: Charlotte | B15: Penni Black | E15: Delegation european union | F15: 46037 | H15: 46039 | I15: R | J15: Complete | K15: 87 | L15: 1827 | M15: =IF(OR($K15="",$L15=""),"",$L15/$K15) -> 21 | N15: 0.2 | O15: =IF($L15="","",$L15*IF($N15="",Settings!$J$11,$N15)) -> 365.4 | P15: =IF($L15="","",$L15+$O15) -> 2192.4 | Q15: No | S15: =IF($L15="","",IF($Q15<>"Yes",0,IF($R15<>"",$R15,ROUND($L15*Settings!$J$4,2)))) -> 0 | T15: =IF($L15="","",$P15+$S15) -> 2192.4 | U15: =IF($L15="","",ROUND($P15/2,2)+$S15) -> 1096.2 | V15: 2192.4 | W15: BACS | X15: 46084 | AE15: =IF($L15="","",SUM($V15,$Y15,$AB15)) -> 2192.4 | AF15: =IF(OR($L15="",$T15=0),"",IF(OR($J15="Complete",$J15="Paid in Full"),1,$AE15/$T15)) -> 1 | AG15: =IF($L15="","",IF(OR($J15="Cancelled",$J15="Complete",$J15="Paid in Full"),0,ROUND($T15-$AE15,2))) -> 0 | AH15: =IF(OR($L15="",$H15="",$AG15<=0),"",MAX(0,TODAY()-($H15+Settings!$J$6))) | AO15: =IF(OR($L15="",$S15=0,$AI15=""),0,ROUND($S15-$AI15,2)) -> 0 | AP15: =IF($L15="","",ROUND($L15+$AO15,2)) -> 1827 | AR15: =IF($L15="","",IF(ISNUMBER($F15),$F15,IF(ISNUMBER($G15),$G15,""))) -> 46037 | AS15: =IF(OR($L15="",$AR15=""),"",DATE(YEAR($AR15),MONTH($AR15),1)) -> 46023 | AT15: =IF($L15="","",IF($AR15<>"",YEAR($AR15),IF(ISNUMBER($H15),YEAR($H15),""))) -> 2026
A16: Danelle | B16: Penni Black | C16: C | D16: 22004210 | E16: Winston & Strawn | F16: 46043 | H16: 46040 | I16: R | J16: Complete | K16: 40 | L16: 1092 | M16: =IF(OR($K16="",$L16=""),"",$L16/$K16) -> 27.3 | N16: 0.2 | O16: =IF($L16="","",$L16*IF($N16="",Settings!$J$11,$N16)) -> 218.4 | P16: =IF($L16="","",$L16+$O16) -> 1310.4 | Q16: No | S16: =IF($L16="","",IF($Q16<>"Yes",0,IF($R16<>"",$R16,ROUND($L16*Settings!$J$4,2)))) -> 0 | T16: =IF($L16="","",$P16+$S16) -> 1310.4 | U16: =IF($L16="","",ROUND($P16/2,2)+$S16) -> 655.2 | V16: 1310.4 | W16: CC | X16: 46041 | AE16: =IF($L16="","",SUM($V16,$Y16,$AB16)) -> 1310.4 | AF16: =IF(OR($L16="",$T16=0),"",IF(OR($J16="Complete",$J16="Paid in Full"),1,$AE16/$T16)) -> 1 | AG16: =IF($L16="","",IF(OR($J16="Cancelled",$J16="Complete",$J16="Paid in Full"),0,ROUND($T16-$AE16,2))) -> 0 | AH16: =IF(OR($L16="",$H16="",$AG16<=0),"",MAX(0,TODAY()-($H16+Settings!$J$6))) | AO16: =IF(OR($L16="",$S16=0,$AI16=""),0,ROUND($S16-$AI16,2)) -> 0 | AP16: =IF($L16="","",ROUND($L16+$AO16,2)) -> 1092 | AR16: =IF($L16="","",IF(ISNUMBER($F16),$F16,IF(ISNUMBER($G16),$G16,""))) -> 46043 | AS16: =IF(OR($L16="",$AR16=""),"",DATE(YEAR($AR16),MONTH($AR16),1)) -> 46023 | AT16: =IF($L16="","",IF($AR16<>"",YEAR($AR16),IF(ISNUMBER($H16),YEAR($H16),""))) -> 2026
A17: Danelle | B17: Penni Black | C17: C | D17: 22004211 | E17: Humanists | F17: 46065 | H17: 46043 | I17: R | J17: Complete | K17: 70 | L17: 3908.43 | M17: =IF(OR($K17="",$L17=""),"",$L17/$K17) -> 55.834714 | N17: 0.2 | O17: =IF($L17="","",$L17*IF($N17="",Settings!$J$11,$N17)) -> 781.686 | P17: =IF($L17="","",$L17+$O17) -> 4690.116 | Q17: Yes | S17: =IF($L17="","",IF($Q17<>"Yes",0,IF($R17<>"",$R17,ROUND($L17*Settings!$J$4,2)))) -> 390.84 | T17: =IF($L17="","",$P17+$S17) -> 5080.956 | U17: =IF($L17="","",ROUND($P17/2,2)+$S17) -> 2735.9 | V17: 5080.96 | W17: BACS | X17: 46062 | AE17: =IF($L17="","",SUM($V17,$Y17,$AB17)) -> 5080.96 | AF17: =IF(OR($L17="",$T17=0),"",IF(OR($J17="Complete",$J17="Paid in Full"),1,$AE17/$T17)) -> 1 | AG17: =IF($L17="","",IF(OR($J17="Cancelled",$J17="Complete",$J17="Paid in Full"),0,ROUND($T17-$AE17,2))) -> 0 | AH17: =IF(OR($L17="",$H17="",$AG17<=0),"",MAX(0,TODAY()-($H17+Settings!$J$6))) | AI17: 390.84 | AJ17: British Humanist Assocation | AK17: 0-9 90 01 | AL17: 65005749 | AM17: BACS | AN17: 46089 | AO17: =IF(OR($L17="",$S17=0,$AI17=""),0,ROUND($S17-$AI17,2)) -> 0 | AP17: =IF($L17="","",ROUND($L17+$AO17,2)) -> 3908.43 | AR17: =IF($L17="","",IF(ISNUMBER($F17),$F17,IF(ISNUMBER($G17),$G17,""))) -> 46065 | AS17: =IF(OR($L17="",$AR17=""),"",DATE(YEAR($AR17),MONTH($AR17),1)) -> 46054 | AT17: =IF($L17="","",IF($AR17<>"",YEAR($AR17),IF(ISNUMBER($H17),YEAR($H17),""))) -> 2026
A18: Danelle | B18: Penni Black | C18: C | D18: 22004212 | E18: Humanists | F18: 46086 | H18: 46043 | I18: R | J18: Complete | K18: 70 | L18: 3908.43 | M18: =IF(OR($K18="",$L18=""),"",$L18/$K18) -> 55.834714 | N18: 0.2 | O18: =IF($L18="","",$L18*IF($N18="",Settings!$J$11,$N18)) -> 781.686 | P18: =IF($L18="","",$L18+$O18) -> 4690.116 | Q18: Yes | S18: =IF($L18="","",IF($Q18<>"Yes",0,IF($R18<>"",$R18,ROUND($L18*Settings!$J$4,2)))) -> 390.84 | T18: =IF($L18="","",$P18+$S18) -> 5080.956 | U18: =IF($L18="","",ROUND($P18/2,2)+$S18) -> 2735.9 | V18: 5080.96 | W18: BACS | X18: 46062 | AE18: =IF($L18="","",SUM($V18,$Y18,$AB18)) -> 5080.96 | AF18: =IF(OR($L18="",$T18=0),"",IF(OR($J18="Complete",$J18="Paid in Full"),1,$AE18/$T18)) -> 1 | AG18: =IF($L18="","",IF(OR($J18="Cancelled",$J18="Complete",$J18="Paid in Full"),0,ROUND($T18-$AE18,2))) -> 0 | AH18: =IF(OR($L18="",$H18="",$AG18<=0),"",MAX(0,TODAY()-($H18+Settings!$J$6))) | AI18: 390.84 | AJ18: British Humanist Assocation | AK18: 0-9 90 01 | AL18: 65005749 | AM18: BACS | AN18: 46092 | AO18: =IF(OR($L18="",$S18=0,$AI18=""),0,ROUND($S18-$AI18,2)) -> 0 | AP18: =IF($L18="","",ROUND($L18+$AO18,2)) -> 3908.43 | AR18: =IF($L18="","",IF(ISNUMBER($F18),$F18,IF(ISNUMBER($G18),$G18,""))) -> 46086 | AS18: =IF(OR($L18="",$AR18=""),"",DATE(YEAR($AR18),MONTH($AR18),1)) -> 46082 | AT18: =IF($L18="","",IF($AR18<>"",YEAR($AR18),IF(ISNUMBER($H18),YEAR($H18),""))) -> 2026
A19: Danelle | B19: Penni Black | C19: C | D19: 22004213 | E19: Arini - DAY 1 | F19: 46048 | H19: 46044 | I19: R | J19: Complete | K19: 35 | L19: 2397.65 | M19: =IF(OR($K19="",$L19=""),"",$L19/$K19) -> 68.504286 | N19: 0.2 | O19: =IF($L19="","",$L19*IF($N19="",Settings!$J$11,$N19)) -> 479.53 | P19: =IF($L19="","",$L19+$O19) -> 2877.18 | Q19: Yes | S19: =IF($L19="","",IF($Q19<>"Yes",0,IF($R19<>"",$R19,ROUND($L19*Settings!$J$4,2)))) -> 239.77 | T19: =IF($L19="","",$P19+$S19) -> 3116.95 | U19: =IF($L19="","",ROUND($P19/2,2)+$S19) -> 1678.36 | V19: 3116.95 | W19: CC | X19: 46044 | AE19: =IF($L19="","",SUM($V19,$Y19,$AB19)) -> 3116.95 | AF19: =IF(OR($L19="",$T19=0),"",IF(OR($J19="Complete",$J19="Paid in Full"),1,$AE19/$T19)) -> 1 | AG19: =IF($L19="","",IF(OR($J19="Cancelled",$J19="Complete",$J19="Paid in Full"),0,ROUND($T19-$AE19,2))) -> 0 | AH19: =IF(OR($L19="",$H19="",$AG19<=0),"",MAX(0,TODAY()-($H19+Settings!$J$6))) | AI19: 239.77 | AM19: CC | AN19: 46057 | AO19: =IF(OR($L19="",$S19=0,$AI19=""),0,ROUND($S19-$AI19,2)) -> 0 | AP19: =IF($L19="","",ROUND($L19+$AO19,2)) -> 2397.65 | AR19: =IF($L19="","",IF(ISNUMBER($F19),$F19,IF(ISNUMBER($G19),$G19,""))) -> 46048 | AS19: =IF(OR($L19="",$AR19=""),"",DATE(YEAR($AR19),MONTH($AR19),1)) -> 46023 | AT19: =IF($L19="","",IF($AR19<>"",YEAR($AR19),IF(ISNUMBER($H19),YEAR($H19),""))) -> 2026
A20: Danelle | B20: Penni Black | C20: C | D20: 22004214 | E20: Arini - DAY 2 | F20: 46051 | H20: 46044 | I20: R | J20: Complete | K20: 25 | L20: 2018.85 | M20: =IF(OR($K20="",$L20=""),"",$L20/$K20) -> 80.754 | N20: 0.2 | O20: =IF($L20="","",$L20*IF($N20="",Settings!$J$11,$N20)) -> 403.77 | P20: =IF($L20="","",$L20+$O20) -> 2422.62 | Q20: Yes | S20: =IF($L20="","",IF($Q20<>"Yes",0,IF($R20<>"",$R20,ROUND($L20*Settings!$J$4,2)))) -> 201.89 | T20: =IF($L20="","",$P20+$S20) -> 2624.51 | U20: =IF($L20="","",ROUND($P20/2,2)+$S20) -> 1413.2 | V20: 2624.52 | W20: CC | X20: 46044 | AE20: =IF($L20="","",SUM($V20,$Y20,$AB20)) -> 2624.52 | AF20: =IF(OR($L20="",$T20=0),"",IF(OR($J20="Complete",$J20="Paid in Full"),1,$AE20/$T20)) -> 1 | AG20: =IF($L20="","",IF(OR($J20="Cancelled",$J20="Complete",$J20="Paid in Full"),0,ROUND($T20-$AE20,2))) -> 0 | AH20: =IF(OR($L20="",$H20="",$AG20<=0),"",MAX(0,TODAY()-($H20+Settings!$J$6))) | AI20: 201.89 | AM20: CC | AO20: =IF(OR($L20="",$S20=0,$AI20=""),0,ROUND($S20-$AI20,2)) -> 0 | AP20: =IF($L20="","",ROUND($L20+$AO20,2)) -> 2018.85 | AR20: =IF($L20="","",IF(ISNUMBER($F20),$F20,IF(ISNUMBER($G20),$G20,""))) -> 46051 | AS20: =IF(OR($L20="",$AR20=""),"",DATE(YEAR($AR20),MONTH($AR20),1)) -> 46023 | AT20: =IF($L20="","",IF($AR20<>"",YEAR($AR20),IF(ISNUMBER($H20),YEAR($H20),""))) -> 2026
A21: Danelle | B21: Penni Black | C21: C | D21: 22004215 | E21: Dixon Wilson | F21: 46093 | H21: 46044 | I21: R | J21: Complete | K21: 40 | L21: 1853.5 | M21: =IF(OR($K21="",$L21=""),"",$L21/$K21) -> 46.3375 | N21: 0.2 | O21: =IF($L21="","",$L21*IF($N21="",Settings!$J$11,$N21)) -> 370.7 | P21: =IF($L21="","",$L21+$O21) -> 2224.2 | Q21: Yes | S21: =IF($L21="","",IF($Q21<>"Yes",0,IF($R21<>"",$R21,ROUND($L21*Settings!$J$4,2)))) -> 185.35 | T21: =IF($L21="","",$P21+$S21) -> 2409.55 | U21: =IF($L21="","",ROUND($P21/2,2)+$S21) -> 1297.45 | V21: 1112.1 | W21: BACS | X21: 46066 | Y21: 1297.45 | Z21: BACS | AA21: 46084 | AE21: =IF($L21="","",SUM($V21,$Y21,$AB21)) -> 2409.55 | AF21: =IF(OR($L21="",$T21=0),"",IF(OR($J21="Complete",$J21="Paid in Full"),1,$AE21/$T21)) -> 1 | AG21: =IF($L21="","",IF(OR($J21="Cancelled",$J21="Complete",$J21="Paid in Full"),0,ROUND($T21-$AE21,2))) -> 0 | AH21: =IF(OR($L21="",$H21="",$AG21<=0),"",MAX(0,TODAY()-($H21+Settings!$J$6))) | AI21: 185.35 | AJ21: Dixon Wilson | AK21: 15-99-00 | AL21: 19332130 | AM21: BACS | AN21: 46095 | AO21: =IF(OR($L21="",$S21=0,$AI21=""),0,ROUND($S21-$AI21,2)) -> 0 | AP21: =IF($L21="","",ROUND($L21+$AO21,2)) -> 1853.5 | AR21: =IF($L21="","",IF(ISNUMBER($F21),$F21,IF(ISNUMBER($G21),$G21,""))) -> 46093 | AS21: =IF(OR($L21="",$AR21=""),"",DATE(YEAR($AR21),MONTH($AR21),1)) -> 46082 | AT21: =IF($L21="","",IF($AR21<>"",YEAR($AR21),IF(ISNUMBER($H21),YEAR($H21),""))) -> 2026
A22: Danelle | B22: Penni Black | C22: C | D22: 22004216 | E22: Mewburn Ellis | F22: 46078 | H22: 46048 | I22: R | J22: Complete | K22: 40 | L22: 3466.6 | M22: =IF(OR($K22="",$L22=""),"",$L22/$K22) -> 86.665 | N22: 0.2 | O22: =IF($L22="","",$L22*IF($N22="",Settings!$J$11,$N22)) -> 693.32 | P22: =IF($L22="","",$L22+$O22) -> 4159.92 | Q22: Yes | S22: =IF($L22="","",IF($Q22<>"Yes",0,IF($R22<>"",$R22,ROUND($L22*Settings!$J$4,2)))) -> 346.66 | T22: =IF($L22="","",$P22+$S22) -> 4506.58 | U22: =IF($L22="","",ROUND($P22/2,2)+$S22) -> 2426.62 | V22: 4506.58 | W22: CC | X22: 46049 | AE22: =IF($L22="","",SUM($V22,$Y22,$AB22)) -> 4506.58 | AF22: =IF(OR($L22="",$T22=0),"",IF(OR($J22="Complete",$J22="Paid in Full"),1,$AE22/$T22)) -> 1 | AG22: =IF($L22="","",IF(OR($J22="Cancelled",$J22="Complete",$J22="Paid in Full"),0,ROUND($T22-$AE22,2))) -> 0 | AH22: =IF(OR($L22="",$H22="",$AG22<=0),"",MAX(0,TODAY()-($H22+Settings!$J$6))) | AI22: 346.66 | AM22: CC | AN22: 46057 | AO22: =IF(OR($L22="",$S22=0,$AI22=""),0,ROUND($S22-$AI22,2)) -> 0 | AP22: =IF($L22="","",ROUND($L22+$AO22,2)) -> 3466.6 | AR22: =IF($L22="","",IF(ISNUMBER($F22),$F22,IF(ISNUMBER($G22),$G22,""))) -> 46078 | AS22: =IF(OR($L22="",$AR22=""),"",DATE(YEAR($AR22),MONTH($AR22),1)) -> 46054 | AT22: =IF($L22="","",IF($AR22<>"",YEAR($AR22),IF(ISNUMBER($H22),YEAR($H22),""))) -> 2026
A23: Danelle | B23: Penni Black | C23: C | D23: 22004217 | E23: Perenco Holdings | F23: 46056 | H23: 46048 | I23: R | J23: Complete | K23: 120 | L23: 7161 | M23: =IF(OR($K23="",$L23=""),"",$L23/$K23) -> 59.675 | N23: 0.2 | O23: =IF($L23="","",$L23*IF($N23="",Settings!$J$11,$N23)) -> 1432.2 | P23: =IF($L23="","",$L23+$O23) -> 8593.2 | Q23: Yes | S23: =IF($L23="","",IF($Q23<>"Yes",0,IF($R23<>"",$R23,ROUND($L23*Settings!$J$4,2)))) -> 716.1 | T23: =IF($L23="","",$P23+$S23) -> 9309.3 | U23: =IF($L23="","",ROUND($P23/2,2)+$S23) -> 5012.7 | V23: 8593.2 | W23: BACS | X23: 46049 | Y23: 62.4 | Z23: CC | AA23: 46058 | AE23: =IF($L23="","",SUM($V23,$Y23,$AB23)) -> 8655.6 | AF23: =IF(OR($L23="",$T23=0),"",IF(OR($J23="Complete",$J23="Paid in Full"),1,$AE23/$T23)) -> 1 | AG23: =IF($L23="","",IF(OR($J23="Cancelled",$J23="Complete",$J23="Paid in Full"),0,ROUND($T23-$AE23,2))) -> 0 | AH23: =IF(OR($L23="",$H23="",$AG23<=0),"",MAX(0,TODAY()-($H23+Settings!$J$6))) | AI23: 716.1 | AO23: =IF(OR($L23="",$S23=0,$AI23=""),0,ROUND($S23-$AI23,2)) -> 0 | AP23: =IF($L23="","",ROUND($L23+$AO23,2)) -> 7161 | AR23: =IF($L23="","",IF(ISNUMBER($F23),$F23,IF(ISNUMBER($G23),$G23,""))) -> 46056 | AS23: =IF(OR($L23="",$AR23=""),"",DATE(YEAR($AR23),MONTH($AR23),1)) -> 46054 | AT23: =IF($L23="","",IF($AR23<>"",YEAR($AR23),IF(ISNUMBER($H23),YEAR($H23),""))) -> 2026
A24: Danelle | B24: Penni Black | C24: C | D24: 22004218 | E24: Emma Daniels | F24: 46061 | H24: 46055 | I24: R | J24: Complete | K24: 15 | L24: 2303.5 | M24: =IF(OR($K24="",$L24=""),"",$L24/$K24) -> 153.56667 | N24: 0.2 | O24: =IF($L24="","",$L24*IF($N24="",Settings!$J$11,$N24)) -> 460.7 | P24: =IF($L24="","",$L24+$O24) -> 2764.2 | Q24: Yes | S24: =IF($L24="","",IF($Q24<>"Yes",0,IF($R24<>"",$R24,ROUND($L24*Settings!$J$4,2)))) -> 230.35 | T24: =IF($L24="","",$P24+$S24) -> 2994.55 | U24: =IF($L24="","",ROUND($P24/2,2)+$S24) -> 1612.45 | AE24: =IF($L24="","",SUM($V24,$Y24,$AB24)) -> 0 | AF24: =IF(OR($L24="",$T24=0),"",IF(OR($J24="Complete",$J24="Paid in Full"),1,$AE24/$T24)) -> 1 | AG24: =IF($L24="","",IF(OR($J24="Cancelled",$J24="Complete",$J24="Paid in Full"),0,ROUND($T24-$AE24,2))) -> 0 | AH24: =IF(OR($L24="",$H24="",$AG24<=0),"",MAX(0,TODAY()-($H24+Settings!$J$6))) | AI24: 230.35 | AO24: =IF(OR($L24="",$S24=0,$AI24=""),0,ROUND($S24-$AI24,2)) -> 0 | AP24: =IF($L24="","",ROUND($L24+$AO24,2)) -> 2303.5 | AR24: =IF($L24="","",IF(ISNUMBER($F24),$F24,IF(ISNUMBER($G24),$G24,""))) -> 46061 | AS24: =IF(OR($L24="",$AR24=""),"",DATE(YEAR($AR24),MONTH($AR24),1)) -> 46054 | AT24: =IF($L24="","",IF($AR24<>"",YEAR($AR24),IF(ISNUMBER($H24),YEAR($H24),""))) -> 2026
A25: Danelle | B25: Penni Black | C25: W | D25: 22004219 | E25: Clara & Naren wedding tasting | F25: 46068 | H25: 46056 | I25: N | J25: Cancelled | K25: 2 | L25: 500 | M25: =IF(OR($K25="",$L25=""),"",$L25/$K25) -> 250 | N25: 0 | O25: =IF($L25="","",$L25*IF($N25="",Settings!$J$11,$N25)) -> 0 | P25: =IF($L25="","",$L25+$O25) -> 500 | Q25: No | S25: =IF($L25="","",IF($Q25<>"Yes",0,IF($R25<>"",$R25,ROUND($L25*Settings!$J$4,2)))) -> 0 | T25: =IF($L25="","",$P25+$S25) -> 500 | U25: =IF($L25="","",ROUND($P25/2,2)+$S25) -> 250 | AE25: =IF($L25="","",SUM($V25,$Y25,$AB25)) -> 0 | AF25: =IF(OR($L25="",$T25=0),"",IF(OR($J25="Complete",$J25="Paid in Full"),1,$AE25/$T25)) -> 0 | AG25: =IF($L25="","",IF(OR($J25="Cancelled",$J25="Complete",$J25="Paid in Full"),0,ROUND($T25-$AE25,2))) -> 0 | AH25: =IF(OR($L25="",$H25="",$AG25<=0),"",MAX(0,TODAY()-($H25+Settings!$J$6))) | AO25: =IF(OR($L25="",$S25=0,$AI25=""),0,ROUND($S25-$AI25,2)) -> 0 | AP25: =IF($L25="","",ROUND($L25+$AO25,2)) -> 500 | AR25: =IF($L25="","",IF(ISNUMBER($F25),$F25,IF(ISNUMBER($G25),$G25,""))) -> 46068 | AS25: =IF(OR($L25="",$AR25=""),"",DATE(YEAR($AR25),MONTH($AR25),1)) -> 46054 | AT25: =IF($L25="","",IF($AR25<>"",YEAR($AR25),IF(ISNUMBER($H25),YEAR($H25),""))) -> 2026
A26: Danelle | B26: Penni Black | C26: P | D26: 22004220 | E26: Alison Brown | F26: 46186 | H26: 46057 | I26: N | J26: Complete | K26: 60 | L26: 5096.5 | M26: =IF(OR($K26="",$L26=""),"",$L26/$K26) -> 84.941667 | N26: 0.2 | O26: =IF($L26="","",$L26*IF($N26="",Settings!$J$11,$N26)) -> 1019.3 | P26: =IF($L26="","",$L26+$O26) -> 6115.8 | Q26: Yes | S26: =IF($L26="","",IF($Q26<>"Yes",0,IF($R26<>"",$R26,ROUND($L26*Settings!$J$4,2)))) -> 509.65 | T26: =IF($L26="","",$P26+$S26) -> 6625.45 | U26: =IF($L26="","",ROUND($P26/2,2)+$S26) -> 3567.55 | V26: 3057.9 | W26: CC | X26: 46057 | Y26: 3168.25 | Z26: CC | AA26: 46175 | AE26: =IF($L26="","",SUM($V26,$Y26,$AB26)) -> 6226.15 | AF26: =IF(OR($L26="",$T26=0),"",IF(OR($J26="Complete",$J26="Paid in Full"),1,$AE26/$T26)) -> 1 | AG26: =IF($L26="","",IF(OR($J26="Cancelled",$J26="Complete",$J26="Paid in Full"),0,ROUND($T26-$AE26,2))) -> 0 | AH26: =IF(OR($L26="",$H26="",$AG26<=0),"",MAX(0,TODAY()-($H26+Settings!$J$6))) | AI26: 509.65 | AM26: CC | AN26: 46198 | AO26: =IF(OR($L26="",$S26=0,$AI26=""),0,ROUND($S26-$AI26,2)) -> 0 | AP26: =IF($L26="","",ROUND($L26+$AO26,2)) -> 5096.5 | AR26: =IF($L26="","",IF(ISNUMBER($F26),$F26,IF(ISNUMBER($G26),$G26,""))) -> 46186 | AS26: =IF(OR($L26="",$AR26=""),"",DATE(YEAR($AR26),MONTH($AR26),1)) -> 46174 | AT26: =IF($L26="","",IF($AR26<>"",YEAR($AR26),IF(ISNUMBER($H26),YEAR($H26),""))) -> 2026
A27: Danelle | B27: Penni Black | C27: C | D27: 22004221 | E27: George Jensen Limited | F27: 46065 | H27: 46058 | I27: R | J27: Complete | K27: 50 | L27: 1408.15 | M27: =IF(OR($K27="",$L27=""),"",$L27/$K27) -> 28.163 | N27: 0.2 | O27: =IF($L27="","",$L27*IF($N27="",Settings!$J$11,$N27)) -> 281.63 | P27: =IF($L27="","",$L27+$O27) -> 1689.78 | Q27: Yes | S27: =IF($L27="","",IF($Q27<>"Yes",0,IF($R27<>"",$R27,ROUND($L27*Settings!$J$4,2)))) -> 140.82 | T27: =IF($L27="","",$P27+$S27) -> 1830.6 | U27: =IF($L27="","",ROUND($P27/2,2)+$S27) -> 985.71 | V27: 1831.05 | W27: CC | X27: 46062 | AE27: =IF($L27="","",SUM($V27,$Y27,$AB27)) -> 1831.05 | AF27: =IF(OR($L27="",$T27=0),"",IF(OR($J27="Complete",$J27="Paid in Full"),1,$AE27/$T27)) -> 1 | AG27: =IF($L27="","",IF(OR($J27="Cancelled",$J27="Complete",$J27="Paid in Full"),0,ROUND($T27-$AE27,2))) -> 0 | AH27: =IF(OR($L27="",$H27="",$AG27<=0),"",MAX(0,TODAY()-($H27+Settings!$J$6))) | AI27: 140.82 | AM27: CC | AN27: 46068 | AO27: =IF(OR($L27="",$S27=0,$AI27=""),0,ROUND($S27-$AI27,2)) -> 0 | AP27: =IF($L27="","",ROUND($L27+$AO27,2)) -> 1408.15 | AR27: =IF($L27="","",IF(ISNUMBER($F27),$F27,IF(ISNUMBER($G27),$G27,""))) -> 46065 | AS27: =IF(OR($L27="",$AR27=""),"",DATE(YEAR($AR27),MONTH($AR27),1)) -> 46054 | AT27: =IF($L27="","",IF($AR27<>"",YEAR($AR27),IF(ISNUMBER($H27),YEAR($H27),""))) -> 2026
A28: Danelle | B28: Penni Black | C28: C | D28: 22004222 | E28: St Williams | F28: 46079 | H28: 46063 | I28: R | J28: Complete | K28: 40 | L28: 1956.4 | M28: =IF(OR($K28="",$L28=""),"",$L28/$K28) -> 48.91 | N28: 0.2 | O28: =IF($L28="","",$L28*IF($N28="",Settings!$J$11,$N28)) -> 391.28 | P28: =IF($L28="","",$L28+$O28) -> 2347.68 | Q28: Yes | S28: =IF($L28="","",IF($Q28<>"Yes",0,IF($R28<>"",$R28,ROUND($L28*Settings!$J$4,2)))) -> 195.64 | T28: =IF($L28="","",$P28+$S28) -> 2543.32 | U28: =IF($L28="","",ROUND($P28/2,2)+$S28) -> 1369.48 | V28: 2543.32 | W28: BACS | X28: 46071 | AE28: =IF($L28="","",SUM($V28,$Y28,$AB28)) -> 2543.32 | AF28: =IF(OR($L28="",$T28=0),"",IF(OR($J28="Complete",$J28="Paid in Full"),1,$AE28/$T28)) -> 1 | AG28: =IF($L28="","",IF(OR($J28="Cancelled",$J28="Complete",$J28="Paid in Full"),0,ROUND($T28-$AE28,2))) -> 0 | AH28: =IF(OR($L28="",$H28="",$AG28<=0),"",MAX(0,TODAY()-($H28+Settings!$J$6))) | AI28: 195.64 | AJ28: StWilliams Homes LLP - KRP | AK28: 20-92-96 | AL28: 205-81658 | AM28: BACS | AN28: 46089 | AO28: =IF(OR($L28="",$S28=0,$AI28=""),0,ROUND($S28-$AI28,2)) -> 0 | AP28: =IF($L28="","",ROUND($L28+$AO28,2)) -> 1956.4 | AR28: =IF($L28="","",IF(ISNUMBER($F28),$F28,IF(ISNUMBER($G28),$G28,""))) -> 46079 | AS28: =IF(OR($L28="",$AR28=""),"",DATE(YEAR($AR28),MONTH($AR28),1)) -> 46054 | AT28: =IF($L28="","",IF($AR28<>"",YEAR($AR28),IF(ISNUMBER($H28),YEAR($H28),""))) -> 2026
A29: Danelle | B29: Penni Black | C29: C | D29: 22004223 | E29: Arnold & Porter | F29: 46071 | H29: 46066 | I29: R | J29: Complete | K29: 70 | L29: 2017 | M29: =IF(OR($K29="",$L29=""),"",$L29/$K29) -> 28.814286 | N29: 0.2 | O29: =IF($L29="","",$L29*IF($N29="",Settings!$J$11,$N29)) -> 403.4 | P29: =IF($L29="","",$L29+$O29) -> 2420.4 | Q29: No | S29: =IF($L29="","",IF($Q29<>"Yes",0,IF($R29<>"",$R29,ROUND($L29*Settings!$J$4,2)))) -> 0 | T29: =IF($L29="","",$P29+$S29) -> 2420.4 | U29: =IF($L29="","",ROUND($P29/2,2)+$S29) -> 1210.2 | V29: 2420.4 | W29: BACS | AE29: =IF($L29="","",SUM($V29,$Y29,$AB29)) -> 2420.4 | AF29: =IF(OR($L29="",$T29=0),"",IF(OR($J29="Complete",$J29="Paid in Full"),1,$AE29/$T29)) -> 1 | AG29: =IF($L29="","",IF(OR($J29="Cancelled",$J29="Complete",$J29="Paid in Full"),0,ROUND($T29-$AE29,2))) -> 0 | AH29: =IF(OR($L29="",$H29="",$AG29<=0),"",MAX(0,TODAY()-($H29+Settings!$J$6))) | AO29: =IF(OR($L29="",$S29=0,$AI29=""),0,ROUND($S29-$AI29,2)) -> 0 | AP29: =IF($L29="","",ROUND($L29+$AO29,2)) -> 2017 | AR29: =IF($L29="","",IF(ISNUMBER($F29),$F29,IF(ISNUMBER($G29),$G29,""))) -> 46071 | AS29: =IF(OR($L29="",$AR29=""),"",DATE(YEAR($AR29),MONTH($AR29),1)) -> 46054 | AT29: =IF($L29="","",IF($AR29<>"",YEAR($AR29),IF(ISNUMBER($H29),YEAR($H29),""))) -> 2026
A30: Danelle | B30: Penni Black | C30: C | D30: 22004224 | E30: Colart International | F30: 46106 | H30: 46075 | I30: R | J30: Complete | K30: 50 | L30: 1377.3 | M30: =IF(OR($K30="",$L30=""),"",$L30/$K30) -> 27.546 | N30: 0.2 | O30: =IF($L30="","",$L30*IF($N30="",Settings!$J$11,$N30)) -> 275.46 | P30: =IF($L30="","",$L30+$O30) -> 1652.76 | Q30: No | S30: =IF($L30="","",IF($Q30<>"Yes",0,IF($R30<>"",$R30,ROUND($L30*Settings!$J$4,2)))) -> 0 | T30: =IF($L30="","",$P30+$S30) -> 1652.76 | U30: =IF($L30="","",ROUND($P30/2,2)+$S30) -> 826.38 | V30: 1652.76 | W30: BACS | X30: 46079 | AE30: =IF($L30="","",SUM($V30,$Y30,$AB30)) -> 1652.76 | AF30: =IF(OR($L30="",$T30=0),"",IF(OR($J30="Complete",$J30="Paid in Full"),1,$AE30/$T30)) -> 1 | AG30: =IF($L30="","",IF(OR($J30="Cancelled",$J30="Complete",$J30="Paid in Full"),0,ROUND($T30-$AE30,2))) -> 0 | AH30: =IF(OR($L30="",$H30="",$AG30<=0),"",MAX(0,TODAY()-($H30+Settings!$J$6))) | AO30: =IF(OR($L30="",$S30=0,$AI30=""),0,ROUND($S30-$AI30,2)) -> 0 | AP30: =IF($L30="","",ROUND($L30+$AO30,2)) -> 1377.3 | AR30: =IF($L30="","",IF(ISNUMBER($F30),$F30,IF(ISNUMBER($G30),$G30,""))) -> 46106 | AS30: =IF(OR($L30="",$AR30=""),"",DATE(YEAR($AR30),MONTH($AR30),1)) -> 46082 | AT30: =IF($L30="","",IF($AR30<>"",YEAR($AR30),IF(ISNUMBER($H30),YEAR($H30),""))) -> 2026
A31: Danelle | B31: Penni Black | C31: C | D31: 22004225 | E31: Zenith Bank Ltd - Day 1 & 2 | H31: 46075 | I31: R | J31: Complete | K31: 37 | L31: 4135.6 | M31: =IF(OR($K31="",$L31=""),"",$L31/$K31) -> 111.77297 | N31: 0.2 | O31: =IF($L31="","",$L31*IF($N31="",Settings!$J$11,$N31)) -> 827.12 | P31: =IF($L31="","",$L31+$O31) -> 4962.72 | Q31: Yes | S31: =IF($L31="","",IF($Q31<>"Yes",0,IF($R31<>"",$R31,ROUND($L31*Settings!$J$4,2)))) -> 413.56 | T31: =IF($L31="","",$P31+$S31) -> 5376.28 | U31: =IF($L31="","",ROUND($P31/2,2)+$S31) -> 2894.92 | V31: 5376.28 | W31: BACS | X31: 46080 | AE31: =IF($L31="","",SUM($V31,$Y31,$AB31)) -> 5376.28 | AF31: =IF(OR($L31="",$T31=0),"",IF(OR($J31="Complete",$J31="Paid in Full"),1,$AE31/$T31)) -> 1 | AG31: =IF($L31="","",IF(OR($J31="Cancelled",$J31="Complete",$J31="Paid in Full"),0,ROUND($T31-$AE31,2))) -> 0 | AH31: =IF(OR($L31="",$H31="",$AG31<=0),"",MAX(0,TODAY()-($H31+Settings!$J$6))) | AI31: 413.56 | AJ31: Zenith Bank UK Ltd | AK31: 40-02-50 | AL31: 81253972 | AM31: BACS | AN31: 46095 | AO31: =IF(OR($L31="",$S31=0,$AI31=""),0,ROUND($S31-$AI31,2)) -> 0 | AP31: =IF($L31="","",ROUND($L31+$AO31,2)) -> 4135.6 | AQ31: Event dates: 12 & 13th March. | AR31: =IF($L31="","",IF(ISNUMBER($F31),$F31,IF(ISNUMBER($G31),$G31,""))) | AS31: =IF(OR($L31="",$AR31=""),"",DATE(YEAR($AR31),MONTH($AR31),1)) | AT31: =IF($L31="","",IF($AR31<>"",YEAR($AR31),IF(ISNUMBER($H31),YEAR($H31),""))) -> 2026
A32: Danelle | B32: Penni Black | C32: C | D32: 22004226 | E32: Perenco Holdings | F32: 46093 | H32: 46075 | I32: R | J32: Complete | K32: 13 | L32: 847 | M32: =IF(OR($K32="",$L32=""),"",$L32/$K32) -> 65.153846 | N32: 0.2 | O32: =IF($L32="","",$L32*IF($N32="",Settings!$J$11,$N32)) -> 169.4 | P32: =IF($L32="","",$L32+$O32) -> 1016.4 | Q32: No | S32: =IF($L32="","",IF($Q32<>"Yes",0,IF($R32<>"",$R32,ROUND($L32*Settings!$J$4,2)))) -> 0 | T32: =IF($L32="","",$P32+$S32) -> 1016.4 | U32: =IF($L32="","",ROUND($P32/2,2)+$S32) -> 508.2 | AE32: =IF($L32="","",SUM($V32,$Y32,$AB32)) -> 0 | AF32: =IF(OR($L32="",$T32=0),"",IF(OR($J32="Complete",$J32="Paid in Full"),1,$AE32/$T32)) -> 1 | AG32: =IF($L32="","",IF(OR($J32="Cancelled",$J32="Complete",$J32="Paid in Full"),0,ROUND($T32-$AE32,2))) -> 0 | AH32: =IF(OR($L32="",$H32="",$AG32<=0),"",MAX(0,TODAY()-($H32+Settings!$J$6))) | AO32: =IF(OR($L32="",$S32=0,$AI32=""),0,ROUND($S32-$AI32,2)) -> 0 | AP32: =IF($L32="","",ROUND($L32+$AO32,2)) -> 847 | AR32: =IF($L32="","",IF(ISNUMBER($F32),$F32,IF(ISNUMBER($G32),$G32,""))) -> 46093 | AS32: =IF(OR($L32="",$AR32=""),"",DATE(YEAR($AR32),MONTH($AR32),1)) -> 46082 | AT32: =IF($L32="","",IF($AR32<>"",YEAR($AR32),IF(ISNUMBER($H32),YEAR($H32),""))) -> 2026
A33: Danelle | B33: Penni Black | C33: C | D33: 22004227 | E33: Cognizant | F33: 46085 | H33: 46077 | I33: R | J33: Complete | K33: 100 | L33: 7390.4 | M33: =IF(OR($K33="",$L33=""),"",$L33/$K33) -> 73.904 | N33: 0.2 | O33: =IF($L33="","",$L33*IF($N33="",Settings!$J$11,$N33)) -> 1478.08 | P33: =IF($L33="","",$L33+$O33) -> 8868.48 | Q33: Yes | S33: =IF($L33="","",IF($Q33<>"Yes",0,IF($R33<>"",$R33,ROUND($L33*Settings!$J$4,2)))) -> 739.04 | T33: =IF($L33="","",$P33+$S33) -> 9607.52 | U33: =IF($L33="","",ROUND($P33/2,2)+$S33) -> 5173.28 | V33: 6709.68 | W33: CC | X33: 46079 | Y33: 2897.84 | Z33: CC | AA33: 46079 | AE33: =IF($L33="","",SUM($V33,$Y33,$AB33)) -> 9607.52 | AF33: =IF(OR($L33="",$T33=0),"",IF(OR($J33="Complete",$J33="Paid in Full"),1,$AE33/$T33)) -> 1 | AG33: =IF($L33="","",IF(OR($J33="Cancelled",$J33="Complete",$J33="Paid in Full"),0,ROUND($T33-$AE33,2))) -> 0 | AH33: =IF(OR($L33="",$H33="",$AG33<=0),"",MAX(0,TODAY()-($H33+Settings!$J$6))) | AI33: 739.04 | AM33: CC | AN33: 46089 | AO33: =IF(OR($L33="",$S33=0,$AI33=""),0,ROUND($S33-$AI33,2)) -> 0 | AP33: =IF($L33="","",ROUND($L33+$AO33,2)) -> 7390.4 | AR33: =IF($L33="","",IF(ISNUMBER($F33),$F33,IF(ISNUMBER($G33),$G33,""))) -> 46085 | AS33: =IF(OR($L33="",$AR33=""),"",DATE(YEAR($AR33),MONTH($AR33),1)) -> 46082 | AT33: =IF($L33="","",IF($AR33<>"",YEAR($AR33),IF(ISNUMBER($H33),YEAR($H33),""))) -> 2026
A34: Danelle | B34: Penni Black | C34: C | D34: 22004228 | E34: House of Decant | F34: 46084 | H34: 46077 | I34: N | J34: Complete | K34: 25 | L34: 514 | M34: =IF(OR($K34="",$L34=""),"",$L34/$K34) -> 20.56 | N34: 0.2 | O34: =IF($L34="","",$L34*IF($N34="",Settings!$J$11,$N34)) -> 102.8 | P34: =IF($L34="","",$L34+$O34) -> 616.8 | Q34: No | S34: =IF($L34="","",IF($Q34<>"Yes",0,IF($R34<>"",$R34,ROUND($L34*Settings!$J$4,2)))) -> 0 | T34: =IF($L34="","",$P34+$S34) -> 616.8 | U34: =IF($L34="","",ROUND($P34/2,2)+$S34) -> 308.4 | AE34: =IF($L34="","",SUM($V34,$Y34,$AB34)) -> 0 | AF34: =IF(OR($L34="",$T34=0),"",IF(OR($J34="Complete",$J34="Paid in Full"),1,$AE34/$T34)) -> 1 | AG34: =IF($L34="","",IF(OR($J34="Cancelled",$J34="Complete",$J34="Paid in Full"),0,ROUND($T34-$AE34,2))) -> 0 | AH34: =IF(OR($L34="",$H34="",$AG34<=0),"",MAX(0,TODAY()-($H34+Settings!$J$6))) | AO34: =IF(OR($L34="",$S34=0,$AI34=""),0,ROUND($S34-$AI34,2)) -> 0 | AP34: =IF($L34="","",ROUND($L34+$AO34,2)) -> 514 | AR34: =IF($L34="","",IF(ISNUMBER($F34),$F34,IF(ISNUMBER($G34),$G34,""))) -> 46084 | AS34: =IF(OR($L34="",$AR34=""),"",DATE(YEAR($AR34),MONTH($AR34),1)) -> 46082 | AT34: =IF($L34="","",IF($AR34<>"",YEAR($AR34),IF(ISNUMBER($H34),YEAR($H34),""))) -> 2026
A35: Danelle | B35: Penni Black | C35: C | D35: 22004229 | E35: Conway Hall | F35: 46084 | H35: 46077 | I35: R | J35: Complete | K35: 60 | L35: 176 | M35: =IF(OR($K35="",$L35=""),"",$L35/$K35) -> 2.9333333 | N35: 0.2 | O35: =IF($L35="","",$L35*IF($N35="",Settings!$J$11,$N35)) -> 35.2 | P35: =IF($L35="","",$L35+$O35) -> 211.2 | Q35: No | S35: =IF($L35="","",IF($Q35<>"Yes",0,IF($R35<>"",$R35,ROUND($L35*Settings!$J$4,2)))) -> 0 | T35: =IF($L35="","",$P35+$S35) -> 211.2 | U35: =IF($L35="","",ROUND($P35/2,2)+$S35) -> 105.6 | V35: 211.2 | W35: CC | X35: 46080 | AE35: =IF($L35="","",SUM($V35,$Y35,$AB35)) -> 211.2 | AF35: =IF(OR($L35="",$T35=0),"",IF(OR($J35="Complete",$J35="Paid in Full"),1,$AE35/$T35)) -> 1 | AG35: =IF($L35="","",IF(OR($J35="Cancelled",$J35="Complete",$J35="Paid in Full"),0,ROUND($T35-$AE35,2))) -> 0 | AH35: =IF(OR($L35="",$H35="",$AG35<=0),"",MAX(0,TODAY()-($H35+Settings!$J$6))) | AO35: =IF(OR($L35="",$S35=0,$AI35=""),0,ROUND($S35-$AI35,2)) -> 0 | AP35: =IF($L35="","",ROUND($L35+$AO35,2)) -> 176 | AR35: =IF($L35="","",IF(ISNUMBER($F35),$F35,IF(ISNUMBER($G35),$G35,""))) -> 46084 | AS35: =IF(OR($L35="",$AR35=""),"",DATE(YEAR($AR35),MONTH($AR35),1)) -> 46082 | AT35: =IF($L35="","",IF($AR35<>"",YEAR($AR35),IF(ISNUMBER($H35),YEAR($H35),""))) -> 2026
A36: Danelle | B36: Penni Black | C36: C | D36: 22004230 | E36: Health Sciences University | F36: 46098 | H36: 46080 | I36: N | J36: Complete | K36: 100 | L36: 5061.25 | M36: =IF(OR($K36="",$L36=""),"",$L36/$K36) -> 50.6125 | N36: 0.2 | O36: =IF($L36="","",$L36*IF($N36="",Settings!$J$11,$N36)) -> 1012.25 | P36: =IF($L36="","",$L36+$O36) -> 6073.5 | Q36: Yes | S36: =IF($L36="","",IF($Q36<>"Yes",0,IF($R36<>"",$R36,ROUND($L36*Settings!$J$4,2)))) -> 506.13 | T36: =IF($L36="","",$P36+$S36) -> 6579.63 | U36: =IF($L36="","",ROUND($P36/2,2)+$S36) -> 3542.88 | V36: 6579.62 | W36: BACS | X36: 46089 | AE36: =IF($L36="","",SUM($V36,$Y36,$AB36)) -> 6579.62 | AF36: =IF(OR($L36="",$T36=0),"",IF(OR($J36="Complete",$J36="Paid in Full"),1,$AE36/$T36)) -> 1 | AG36: =IF($L36="","",IF(OR($J36="Cancelled",$J36="Complete",$J36="Paid in Full"),0,ROUND($T36-$AE36,2))) -> 0 | AH36: =IF(OR($L36="",$H36="",$AG36<=0),"",MAX(0,TODAY()-($H36+Settings!$J$6))) | AI36: 506.13 | AJ36: Health Sciences University | AK36: 51073796 | AL36: 40-46-19 | AM36: BACS | AN36: 46125 | AO36: =IF(OR($L36="",$S36=0,$AI36=""),0,ROUND($S36-$AI36,2)) -> 0 | AP36: =IF($L36="","",ROUND($L36+$AO36,2)) -> 5061.25 | AQ36: REF: “P/L PENN06 DEP RFND” | AR36: =IF($L36="","",IF(ISNUMBER($F36),$F36,IF(ISNUMBER($G36),$G36,""))) -> 46098 | AS36: =IF(OR($L36="",$AR36=""),"",DATE(YEAR($AR36),MONTH($AR36),1)) -> 46082 | AT36: =IF($L36="","",IF($AR36<>"",YEAR($AR36),IF(ISNUMBER($H36),YEAR($H36),""))) -> 2026
A37: Charlotte | B37: Penni Black | C37: C | D37: 22004231 | E37: Delegation european union | F37: 46079 | H37: 46079 | I37: R | J37: Complete | K37: 70 | L37: 1470 | M37: =IF(OR($K37="",$L37=""),"",$L37/$K37) -> 21 | N37: 0.2 | O37: =IF($L37="","",$L37*IF($N37="",Settings!$J$11,$N37)) -> 294 | P37: =IF($L37="","",$L37+$O37) -> 1764 | Q37: No | S37: =IF($L37="","",IF($Q37<>"Yes",0,IF($R37<>"",$R37,ROUND($L37*Settings!$J$4,2)))) -> 0 | T37: =IF($L37="","",$P37+$S37) -> 1764 | U37: =IF($L37="","",ROUND($P37/2,2)+$S37) -> 882 | V37: 1764 | W37: BACS | X37: 46125 | AE37: =IF($L37="","",SUM($V37,$Y37,$AB37)) -> 1764 | AF37: =IF(OR($L37="",$T37=0),"",IF(OR($J37="Complete",$J37="Paid in Full"),1,$AE37/$T37)) -> 1 | AG37: =IF($L37="","",IF(OR($J37="Cancelled",$J37="Complete",$J37="Paid in Full"),0,ROUND($T37-$AE37,2))) -> 0 | AH37: =IF(OR($L37="",$H37="",$AG37<=0),"",MAX(0,TODAY()-($H37+Settings!$J$6))) | AO37: =IF(OR($L37="",$S37=0,$AI37=""),0,ROUND($S37-$AI37,2)) -> 0 | AP37: =IF($L37="","",ROUND($L37+$AO37,2)) -> 1470 | AR37: =IF($L37="","",IF(ISNUMBER($F37),$F37,IF(ISNUMBER($G37),$G37,""))) -> 46079 | AS37: =IF(OR($L37="",$AR37=""),"",DATE(YEAR($AR37),MONTH($AR37),1)) -> 46054 | AT37: =IF($L37="","",IF($AR37<>"",YEAR($AR37),IF(ISNUMBER($H37),YEAR($H37),""))) -> 2026
A38: Danelle | B38: Penni Black | C38: C | D38: 22004232 | E38: MediaPlus UK | F38: 46086 | H38: 46082 | I38: N | J38: Complete | K38: 50 | L38: 910 | M38: =IF(OR($K38="",$L38=""),"",$L38/$K38) -> 18.2 | N38: 0.2 | O38: =IF($L38="","",$L38*IF($N38="",Settings!$J$11,$N38)) -> 182 | P38: =IF($L38="","",$L38+$O38) -> 1092 | Q38: No | S38: =IF($L38="","",IF($Q38<>"Yes",0,IF($R38<>"",$R38,ROUND($L38*Settings!$J$4,2)))) -> 0 | T38: =IF($L38="","",$P38+$S38) -> 1092 | U38: =IF($L38="","",ROUND($P38/2,2)+$S38) -> 546 | V38: 1092 | W38: BACS | X38: 46084 | AE38: =IF($L38="","",SUM($V38,$Y38,$AB38)) -> 1092 | AF38: =IF(OR($L38="",$T38=0),"",IF(OR($J38="Complete",$J38="Paid in Full"),1,$AE38/$T38)) -> 1 | AG38: =IF($L38="","",IF(OR($J38="Cancelled",$J38="Complete",$J38="Paid in Full"),0,ROUND($T38-$AE38,2))) -> 0 | AH38: =IF(OR($L38="",$H38="",$AG38<=0),"",MAX(0,TODAY()-($H38+Settings!$J$6))) | AO38: =IF(OR($L38="",$S38=0,$AI38=""),0,ROUND($S38-$AI38,2)) -> 0 | AP38: =IF($L38="","",ROUND($L38+$AO38,2)) -> 910 | AR38: =IF($L38="","",IF(ISNUMBER($F38),$F38,IF(ISNUMBER($G38),$G38,""))) -> 46086 | AS38: =IF(OR($L38="",$AR38=""),"",DATE(YEAR($AR38),MONTH($AR38),1)) -> 46082 | AT38: =IF($L38="","",IF($AR38<>"",YEAR($AR38),IF(ISNUMBER($H38),YEAR($H38),""))) -> 2026
A39: Charlotte | B39: Penni Black | C39: C | D39: 22004233 | E39: Steve Bosley Herne Hill | F39: 46081 | H39: 46083 | I39: R | J39: Complete | K39: 130 | L39: 1430 | M39: =IF(OR($K39="",$L39=""),"",$L39/$K39) -> 11 | N39: 0 | O39: =IF($L39="","",$L39*IF($N39="",Settings!$J$11,$N39)) -> 0 | P39: =IF($L39="","",$L39+$O39) -> 1430 | Q39: No | S39: =IF($L39="","",IF($Q39<>"Yes",0,IF($R39<>"",$R39,ROUND($L39*Settings!$J$4,2)))) -> 0 | T39: =IF($L39="","",$P39+$S39) -> 1430 | U39: =IF($L39="","",ROUND($P39/2,2)+$S39) -> 715 | AE39: =IF($L39="","",SUM($V39,$Y39,$AB39)) -> 0 | AF39: =IF(OR($L39="",$T39=0),"",IF(OR($J39="Complete",$J39="Paid in Full"),1,$AE39/$T39)) -> 1 | AG39: =IF($L39="","",IF(OR($J39="Cancelled",$J39="Complete",$J39="Paid in Full"),0,ROUND($T39-$AE39,2))) -> 0 | AH39: =IF(OR($L39="",$H39="",$AG39<=0),"",MAX(0,TODAY()-($H39+Settings!$J$6))) | AO39: =IF(OR($L39="",$S39=0,$AI39=""),0,ROUND($S39-$AI39,2)) -> 0 | AP39: =IF($L39="","",ROUND($L39+$AO39,2)) -> 1430 | AR39: =IF($L39="","",IF(ISNUMBER($F39),$F39,IF(ISNUMBER($G39),$G39,""))) -> 46081 | AS39: =IF(OR($L39="",$AR39=""),"",DATE(YEAR($AR39),MONTH($AR39),1)) -> 46054 | AT39: =IF($L39="","",IF($AR39<>"",YEAR($AR39),IF(ISNUMBER($H39),YEAR($H39),""))) -> 2026
A40: Danelle | B40: Penni Black | C40: C | D40: 22004234 | E40: SGN - Day 1 | F40: 46106 | H40: 46084 | I40: R | J40: Complete | K40: 30 | L40: 1465 | M40: =IF(OR($K40="",$L40=""),"",$L40/$K40) -> 48.833333 | N40: 0.2 | O40: =IF($L40="","",$L40*IF($N40="",Settings!$J$11,$N40)) -> 293 | P40: =IF($L40="","",$L40+$O40) -> 1758 | Q40: No | S40: =IF($L40="","",IF($Q40<>"Yes",0,IF($R40<>"",$R40,ROUND($L40*Settings!$J$4,2)))) -> 0 | T40: =IF($L40="","",$P40+$S40) -> 1758 | U40: =IF($L40="","",ROUND($P40/2,2)+$S40) -> 879 | V40: 1758 | W40: CC | X40: 46087 | AE40: =IF($L40="","",SUM($V40,$Y40,$AB40)) -> 1758 | AF40: =IF(OR($L40="",$T40=0),"",IF(OR($J40="Complete",$J40="Paid in Full"),1,$AE40/$T40)) -> 1 | AG40: =IF($L40="","",IF(OR($J40="Cancelled",$J40="Complete",$J40="Paid in Full"),0,ROUND($T40-$AE40,2))) -> 0 | AH40: =IF(OR($L40="",$H40="",$AG40<=0),"",MAX(0,TODAY()-($H40+Settings!$J$6))) | AO40: =IF(OR($L40="",$S40=0,$AI40=""),0,ROUND($S40-$AI40,2)) -> 0 | AP40: =IF($L40="","",ROUND($L40+$AO40,2)) -> 1465 | AR40: =IF($L40="","",IF(ISNUMBER($F40),$F40,IF(ISNUMBER($G40),$G40,""))) -> 46106 | AS40: =IF(OR($L40="",$AR40=""),"",DATE(YEAR($AR40),MONTH($AR40),1)) -> 46082 | AT40: =IF($L40="","",IF($AR40<>"",YEAR($AR40),IF(ISNUMBER($H40),YEAR($H40),""))) -> 2026
A41: Danelle | B41: Penni Black | C41: C | D41: 22004235 | E41: SGN - Day 2 | F41: 46107 | H41: 46084 | I41: R | J41: Complete | K41: 30 | L41: 1478.5 | M41: =IF(OR($K41="",$L41=""),"",$L41/$K41) -> 49.283333 | N41: 0.2 | O41: =IF($L41="","",$L41*IF($N41="",Settings!$J$11,$N41)) -> 295.7 | P41: =IF($L41="","",$L41+$O41) -> 1774.2 | Q41: No | S41: =IF($L41="","",IF($Q41<>"Yes",0,IF($R41<>"",$R41,ROUND($L41*Settings!$J$4,2)))) -> 0 | T41: =IF($L41="","",$P41+$S41) -> 1774.2 | U41: =IF($L41="","",ROUND($P41/2,2)+$S41) -> 887.1 | V41: 1774.2 | W41: CC | X41: 46087 | AE41: =IF($L41="","",SUM($V41,$Y41,$AB41)) -> 1774.2 | AF41: =IF(OR($L41="",$T41=0),"",IF(OR($J41="Complete",$J41="Paid in Full"),1,$AE41/$T41)) -> 1 | AG41: =IF($L41="","",IF(OR($J41="Cancelled",$J41="Complete",$J41="Paid in Full"),0,ROUND($T41-$AE41,2))) -> 0 | AH41: =IF(OR($L41="",$H41="",$AG41<=0),"",MAX(0,TODAY()-($H41+Settings!$J$6))) | AO41: =IF(OR($L41="",$S41=0,$AI41=""),0,ROUND($S41-$AI41,2)) -> 0 | AP41: =IF($L41="","",ROUND($L41+$AO41,2)) -> 1478.5 | AR41: =IF($L41="","",IF(ISNUMBER($F41),$F41,IF(ISNUMBER($G41),$G41,""))) -> 46107 | AS41: =IF(OR($L41="",$AR41=""),"",DATE(YEAR($AR41),MONTH($AR41),1)) -> 46082 | AT41: =IF($L41="","",IF($AR41<>"",YEAR($AR41),IF(ISNUMBER($H41),YEAR($H41),""))) -> 2026
A42: Danelle | B42: Penni Black | C42: C | D42: 22004236 | E42: House of Decant | F42: 46091 | H42: 46086 | I42: R | J42: Complete | K42: 35 | L42: 731 | M42: =IF(OR($K42="",$L42=""),"",$L42/$K42) -> 20.885714 | N42: 0.2 | O42: =IF($L42="","",$L42*IF($N42="",Settings!$J$11,$N42)) -> 146.2 | P42: =IF($L42="","",$L42+$O42) -> 877.2 | Q42: No | S42: =IF($L42="","",IF($Q42<>"Yes",0,IF($R42<>"",$R42,ROUND($L42*Settings!$J$4,2)))) -> 0 | T42: =IF($L42="","",$P42+$S42) -> 877.2 | U42: =IF($L42="","",ROUND($P42/2,2)+$S42) -> 438.6 | V42: 877.2 | W42: BACS | X42: 46090 | AE42: =IF($L42="","",SUM($V42,$Y42,$AB42)) -> 877.2 | AF42: =IF(OR($L42="",$T42=0),"",IF(OR($J42="Complete",$J42="Paid in Full"),1,$AE42/$T42)) -> 1 | AG42: =IF($L42="","",IF(OR($J42="Cancelled",$J42="Complete",$J42="Paid in Full"),0,ROUND($T42-$AE42,2))) -> 0 | AH42: =IF(OR($L42="",$H42="",$AG42<=0),"",MAX(0,TODAY()-($H42+Settings!$J$6))) | AO42: =IF(OR($L42="",$S42=0,$AI42=""),0,ROUND($S42-$AI42,2)) -> 0 | AP42: =IF($L42="","",ROUND($L42+$AO42,2)) -> 731 | AR42: =IF($L42="","",IF(ISNUMBER($F42),$F42,IF(ISNUMBER($G42),$G42,""))) -> 46091 | AS42: =IF(OR($L42="",$AR42=""),"",DATE(YEAR($AR42),MONTH($AR42),1)) -> 46082 | AT42: =IF($L42="","",IF($AR42<>"",YEAR($AR42),IF(ISNUMBER($H42),YEAR($H42),""))) -> 2026
A43: Danelle | B43: Penni Black | C43: C | D43: 22004237 | E43: House of Decant | F43: 46092 | H43: 46090 | I43: R | J43: Complete | K43: 35 | L43: 731 | M43: =IF(OR($K43="",$L43=""),"",$L43/$K43) -> 20.885714 | N43: 0.2 | O43: =IF($L43="","",$L43*IF($N43="",Settings!$J$11,$N43)) -> 146.2 | P43: =IF($L43="","",$L43+$O43) -> 877.2 | Q43: No | S43: =IF($L43="","",IF($Q43<>"Yes",0,IF($R43<>"",$R43,ROUND($L43*Settings!$J$4,2)))) -> 0 | T43: =IF($L43="","",$P43+$S43) -> 877.2 | U43: =IF($L43="","",ROUND($P43/2,2)+$S43) -> 438.6 | V43: 877.2 | W43: BACS | X43: 46090 | AE43: =IF($L43="","",SUM($V43,$Y43,$AB43)) -> 877.2 | AF43: =IF(OR($L43="",$T43=0),"",IF(OR($J43="Complete",$J43="Paid in Full"),1,$AE43/$T43)) -> 1 | AG43: =IF($L43="","",IF(OR($J43="Cancelled",$J43="Complete",$J43="Paid in Full"),0,ROUND($T43-$AE43,2))) -> 0 | AH43: =IF(OR($L43="",$H43="",$AG43<=0),"",MAX(0,TODAY()-($H43+Settings!$J$6))) | AO43: =IF(OR($L43="",$S43=0,$AI43=""),0,ROUND($S43-$AI43,2)) -> 0 | AP43: =IF($L43="","",ROUND($L43+$AO43,2)) -> 731 | AR43: =IF($L43="","",IF(ISNUMBER($F43),$F43,IF(ISNUMBER($G43),$G43,""))) -> 46092 | AS43: =IF(OR($L43="",$AR43=""),"",DATE(YEAR($AR43),MONTH($AR43),1)) -> 46082 | AT43: =IF($L43="","",IF($AR43<>"",YEAR($AR43),IF(ISNUMBER($H43),YEAR($H43),""))) -> 2026
A44: Danelle | B44: Penni Black | C44: C | D44: 22004238 | E44: Bryony Spottiswoode | F44: 46103 | H44: 46091 | I44: N | J44: Complete | K44: 43 | L44: 2608 | M44: =IF(OR($K44="",$L44=""),"",$L44/$K44) -> 60.651163 | N44: 0.2 | O44: =IF($L44="","",$L44*IF($N44="",Settings!$J$11,$N44)) -> 521.6 | P44: =IF($L44="","",$L44+$O44) -> 3129.6 | Q44: No | S44: =IF($L44="","",IF($Q44<>"Yes",0,IF($R44<>"",$R44,ROUND($L44*Settings!$J$4,2)))) -> 0 | T44: =IF($L44="","",$P44+$S44) -> 3129.6 | U44: =IF($L44="","",ROUND($P44/2,2)+$S44) -> 1564.8 | V44: 3390.4 | W44: CC | X44: 46306 | AE44: =IF($L44="","",SUM($V44,$Y44,$AB44)) -> 3390.4 | AF44: =IF(OR($L44="",$T44=0),"",IF(OR($J44="Complete",$J44="Paid in Full"),1,$AE44/$T44)) -> 1 | AG44: =IF($L44="","",IF(OR($J44="Cancelled",$J44="Complete",$J44="Paid in Full"),0,ROUND($T44-$AE44,2))) -> 0 | AH44: =IF(OR($L44="",$H44="",$AG44<=0),"",MAX(0,TODAY()-($H44+Settings!$J$6))) | AM44: CC | AN44: 46106 | AO44: =IF(OR($L44="",$S44=0,$AI44=""),0,ROUND($S44-$AI44,2)) -> 0 | AP44: =IF($L44="","",ROUND($L44+$AO44,2)) -> 2608 | AR44: =IF($L44="","",IF(ISNUMBER($F44),$F44,IF(ISNUMBER($G44),$G44,""))) -> 46103 | AS44: =IF(OR($L44="",$AR44=""),"",DATE(YEAR($AR44),MONTH($AR44),1)) -> 46082 | AT44: =IF($L44="","",IF($AR44<>"",YEAR($AR44),IF(ISNUMBER($H44),YEAR($H44),""))) -> 2026
A45: Danelle | B45: Penni Black | C45: C | D45: 22004239 | E45: Katten | F45: 46100 | H45: 46093 | I45: R | J45: Complete | K45: 43 | L45: 1185.25 | M45: =IF(OR($K45="",$L45=""),"",$L45/$K45) -> 27.563953 | N45: 0.2 | O45: =IF($L45="","",$L45*IF($N45="",Settings!$J$11,$N45)) -> 237.05 | P45: =IF($L45="","",$L45+$O45) -> 1422.3 | Q45: No | S45: =IF($L45="","",IF($Q45<>"Yes",0,IF($R45<>"",$R45,ROUND($L45*Settings!$J$4,2)))) -> 0 | T45: =IF($L45="","",$P45+$S45) -> 1422.3 | U45: =IF($L45="","",ROUND($P45/2,2)+$S45) -> 711.15 | V45: 1540.82 | W45: CC | X45: 46093 | AE45: =IF($L45="","",SUM($V45,$Y45,$AB45)) -> 1540.82 | AF45: =IF(OR($L45="",$T45=0),"",IF(OR($J45="Complete",$J45="Paid in Full"),1,$AE45/$T45)) -> 1 | AG45: =IF($L45="","",IF(OR($J45="Cancelled",$J45="Complete",$J45="Paid in Full"),0,ROUND($T45-$AE45,2))) -> 0 | AH45: =IF(OR($L45="",$H45="",$AG45<=0),"",MAX(0,TODAY()-($H45+Settings!$J$6))) | AM45: CC | AN45: 46103 | AO45: =IF(OR($L45="",$S45=0,$AI45=""),0,ROUND($S45-$AI45,2)) -> 0 | AP45: =IF($L45="","",ROUND($L45+$AO45,2)) -> 1185.25 | AR45: =IF($L45="","",IF(ISNUMBER($F45),$F45,IF(ISNUMBER($G45),$G45,""))) -> 46100 | AS45: =IF(OR($L45="",$AR45=""),"",DATE(YEAR($AR45),MONTH($AR45),1)) -> 46082 | AT45: =IF($L45="","",IF($AR45<>"",YEAR($AR45),IF(ISNUMBER($H45),YEAR($H45),""))) -> 2026
A46: Danelle | B46: Penni Black | C46: C | D46: 22004240 | E46: House of Decant | F46: 46100 | H46: 46093 | I46: R | J46: Complete | K46: 25 | L46: 545 | M46: =IF(OR($K46="",$L46=""),"",$L46/$K46) -> 21.8 | N46: 0.2 | O46: =IF($L46="","",$L46*IF($N46="",Settings!$J$11,$N46)) -> 109 | P46: =IF($L46="","",$L46+$O46) -> 654 | Q46: No | S46: =IF($L46="","",IF($Q46<>"Yes",0,IF($R46<>"",$R46,ROUND($L46*Settings!$J$4,2)))) -> 0 | T46: =IF($L46="","",$P46+$S46) -> 654 | U46: =IF($L46="","",ROUND($P46/2,2)+$S46) -> 327 | V46: 654 | W46: BACS | X46: 46103 | AE46: =IF($L46="","",SUM($V46,$Y46,$AB46)) -> 654 | AF46: =IF(OR($L46="",$T46=0),"",IF(OR($J46="Complete",$J46="Paid in Full"),1,$AE46/$T46)) -> 1 | AG46: =IF($L46="","",IF(OR($J46="Cancelled",$J46="Complete",$J46="Paid in Full"),0,ROUND($T46-$AE46,2))) -> 0 | AH46: =IF(OR($L46="",$H46="",$AG46<=0),"",MAX(0,TODAY()-($H46+Settings!$J$6))) | AO46: =IF(OR($L46="",$S46=0,$AI46=""),0,ROUND($S46-$AI46,2)) -> 0 | AP46: =IF($L46="","",ROUND($L46+$AO46,2)) -> 545 | AR46: =IF($L46="","",IF(ISNUMBER($F46),$F46,IF(ISNUMBER($G46),$G46,""))) -> 46100 | AS46: =IF(OR($L46="",$AR46=""),"",DATE(YEAR($AR46),MONTH($AR46),1)) -> 46082 | AT46: =IF($L46="","",IF($AR46<>"",YEAR($AR46),IF(ISNUMBER($H46),YEAR($H46),""))) -> 2026
A47: Danelle | B47: Penni Black | C47: C | D47: 22004241 | E47: House of Decant | F47: 46106 | H47: 46093 | I47: R | J47: Complete | K47: 40 | L47: 576 | M47: =IF(OR($K47="",$L47=""),"",$L47/$K47) -> 14.4 | N47: 0.2 | O47: =IF($L47="","",$L47*IF($N47="",Settings!$J$11,$N47)) -> 115.2 | P47: =IF($L47="","",$L47+$O47) -> 691.2 | Q47: No | S47: =IF($L47="","",IF($Q47<>"Yes",0,IF($R47<>"",$R47,ROUND($L47*Settings!$J$4,2)))) -> 0 | T47: =IF($L47="","",$P47+$S47) -> 691.2 | U47: =IF($L47="","",ROUND($P47/2,2)+$S47) -> 345.6 | V47: 691.2 | W47: BACS | X47: 46103 | AE47: =IF($L47="","",SUM($V47,$Y47,$AB47)) -> 691.2 | AF47: =IF(OR($L47="",$T47=0),"",IF(OR($J47="Complete",$J47="Paid in Full"),1,$AE47/$T47)) -> 1 | AG47: =IF($L47="","",IF(OR($J47="Cancelled",$J47="Complete",$J47="Paid in Full"),0,ROUND($T47-$AE47,2))) -> 0 | AH47: =IF(OR($L47="",$H47="",$AG47<=0),"",MAX(0,TODAY()-($H47+Settings!$J$6))) | AO47: =IF(OR($L47="",$S47=0,$AI47=""),0,ROUND($S47-$AI47,2)) -> 0 | AP47: =IF($L47="","",ROUND($L47+$AO47,2)) -> 576 | AR47: =IF($L47="","",IF(ISNUMBER($F47),$F47,IF(ISNUMBER($G47),$G47,""))) -> 46106 | AS47: =IF(OR($L47="",$AR47=""),"",DATE(YEAR($AR47),MONTH($AR47),1)) -> 46082 | AT47: =IF($L47="","",IF($AR47<>"",YEAR($AR47),IF(ISNUMBER($H47),YEAR($H47),""))) -> 2026
A48: Danelle | B48: Penni Black | C48: C | D48: 22004242 | E48: Fred Ofori-Atta | F48: 46122 | H48: 46094 | I48: N | J48: Complete | K48: 16 | L48: 1362.6 | M48: =IF(OR($K48="",$L48=""),"",$L48/$K48) -> 85.1625 | N48: 0.2 | O48: =IF($L48="","",$L48*IF($N48="",Settings!$J$11,$N48)) -> 272.52 | P48: =IF($L48="","",$L48+$O48) -> 1635.12 | Q48: No | S48: =IF($L48="","",IF($Q48<>"Yes",0,IF($R48<>"",$R48,ROUND($L48*Settings!$J$4,2)))) -> 0 | T48: =IF($L48="","",$P48+$S48) -> 1635.12 | U48: =IF($L48="","",ROUND($P48/2,2)+$S48) -> 817.56 | AE48: =IF($L48="","",SUM($V48,$Y48,$AB48)) -> 0 | AF48: =IF(OR($L48="",$T48=0),"",IF(OR($J48="Complete",$J48="Paid in Full"),1,$AE48/$T48)) -> 1 | AG48: =IF($L48="","",IF(OR($J48="Cancelled",$J48="Complete",$J48="Paid in Full"),0,ROUND($T48-$AE48,2))) -> 0 | AH48: =IF(OR($L48="",$H48="",$AG48<=0),"",MAX(0,TODAY()-($H48+Settings!$J$6))) | AJ48: Fredua Ofori-Atta | AK48: 56-00-46 | AL48: 38550989 | AM48: BACS | AN48: 46138 | AO48: =IF(OR($L48="",$S48=0,$AI48=""),0,ROUND($S48-$AI48,2)) -> 0 | AP48: =IF($L48="","",ROUND($L48+$AO48,2)) -> 1362.6 | AR48: =IF($L48="","",IF(ISNUMBER($F48),$F48,IF(ISNUMBER($G48),$G48,""))) -> 46122 | AS48: =IF(OR($L48="",$AR48=""),"",DATE(YEAR($AR48),MONTH($AR48),1)) -> 46113 | AT48: =IF($L48="","",IF($AR48<>"",YEAR($AR48),IF(ISNUMBER($H48),YEAR($H48),""))) -> 2026
A49: Danelle | B49: Penni Black | C49: C | D49: 22004243 | E49: CBRE | F49: 46106 | H49: 46094 | I49: N | J49: Complete | K49: 50 | L49: 1378.5 | M49: =IF(OR($K49="",$L49=""),"",$L49/$K49) -> 27.57 | N49: 0.2 | O49: =IF($L49="","",$L49*IF($N49="",Settings!$J$11,$N49)) -> 275.7 | P49: =IF($L49="","",$L49+$O49) -> 1654.2 | Q49: No | S49: =IF($L49="","",IF($Q49<>"Yes",0,IF($R49<>"",$R49,ROUND($L49*Settings!$J$4,2)))) -> 0 | T49: =IF($L49="","",$P49+$S49) -> 1654.2 | U49: =IF($L49="","",ROUND($P49/2,2)+$S49) -> 827.1 | AE49: =IF($L49="","",SUM($V49,$Y49,$AB49)) -> 0 | AF49: =IF(OR($L49="",$T49=0),"",IF(OR($J49="Complete",$J49="Paid in Full"),1,$AE49/$T49)) -> 1 | AG49: =IF($L49="","",IF(OR($J49="Cancelled",$J49="Complete",$J49="Paid in Full"),0,ROUND($T49-$AE49,2))) -> 0 | AH49: =IF(OR($L49="",$H49="",$AG49<=0),"",MAX(0,TODAY()-($H49+Settings!$J$6))) | AO49: =IF(OR($L49="",$S49=0,$AI49=""),0,ROUND($S49-$AI49,2)) -> 0 | AP49: =IF($L49="","",ROUND($L49+$AO49,2)) -> 1378.5 | AR49: =IF($L49="","",IF(ISNUMBER($F49),$F49,IF(ISNUMBER($G49),$G49,""))) -> 46106 | AS49: =IF(OR($L49="",$AR49=""),"",DATE(YEAR($AR49),MONTH($AR49),1)) -> 46082 | AT49: =IF($L49="","",IF($AR49<>"",YEAR($AR49),IF(ISNUMBER($H49),YEAR($H49),""))) -> 2026
A50: Charlotte | B50: Penni Black | C50: C | D50: 22004244 | E50: Canada House - Shawnigan Lake School | F50: 46105 | H50: 46099 | I50: R | J50: Complete | K50: 80 | L50: 3599 | M50: =IF(OR($K50="",$L50=""),"",$L50/$K50) -> 44.9875 | N50: 0.2 | O50: =IF($L50="","",$L50*IF($N50="",Settings!$J$11,$N50)) -> 719.8 | P50: =IF($L50="","",$L50+$O50) -> 4318.8 | Q50: No | S50: =IF($L50="","",IF($Q50<>"Yes",0,IF($R50<>"",$R50,ROUND($L50*Settings!$J$4,2)))) -> 0 | T50: =IF($L50="","",$P50+$S50) -> 4318.8 | U50: =IF($L50="","",ROUND($P50/2,2)+$S50) -> 2159.4 | V50: 4318.8 | W50: CC | X50: 46100 | AE50: =IF($L50="","",SUM($V50,$Y50,$AB50)) -> 4318.8 | AF50: =IF(OR($L50="",$T50=0),"",IF(OR($J50="Complete",$J50="Paid in Full"),1,$AE50/$T50)) -> 1 | AG50: =IF($L50="","",IF(OR($J50="Cancelled",$J50="Complete",$J50="Paid in Full"),0,ROUND($T50-$AE50,2))) -> 0 | AH50: =IF(OR($L50="",$H50="",$AG50<=0),"",MAX(0,TODAY()-($H50+Settings!$J$6))) | AN50: 46106 | AO50: =IF(OR($L50="",$S50=0,$AI50=""),0,ROUND($S50-$AI50,2)) -> 0 | AP50: =IF($L50="","",ROUND($L50+$AO50,2)) -> 3599 | AR50: =IF($L50="","",IF(ISNUMBER($F50),$F50,IF(ISNUMBER($G50),$G50,""))) -> 46105 | AS50: =IF(OR($L50="",$AR50=""),"",DATE(YEAR($AR50),MONTH($AR50),1)) -> 46082 | AT50: =IF($L50="","",IF($AR50<>"",YEAR($AR50),IF(ISNUMBER($H50),YEAR($H50),""))) -> 2026
A51: Charlotte | B51: Penni Black | C51: C | D51: 22004245 | E51: Nick Noise | F51: 46106 | H51: 46100 | I51: N | J51: Complete | K51: 40 | L51: 880 | M51: =IF(OR($K51="",$L51=""),"",$L51/$K51) -> 22 | N51: 0.2 | O51: =IF($L51="","",$L51*IF($N51="",Settings!$J$11,$N51)) -> 176 | P51: =IF($L51="","",$L51+$O51) -> 1056 | Q51: No | S51: =IF($L51="","",IF($Q51<>"Yes",0,IF($R51<>"",$R51,ROUND($L51*Settings!$J$4,2)))) -> 0 | T51: =IF($L51="","",$P51+$S51) -> 1056 | U51: =IF($L51="","",ROUND($P51/2,2)+$S51) -> 528 | AE51: =IF($L51="","",SUM($V51,$Y51,$AB51)) -> 0 | AF51: =IF(OR($L51="",$T51=0),"",IF(OR($J51="Complete",$J51="Paid in Full"),1,$AE51/$T51)) -> 1 | AG51: =IF($L51="","",IF(OR($J51="Cancelled",$J51="Complete",$J51="Paid in Full"),0,ROUND($T51-$AE51,2))) -> 0 | AH51: =IF(OR($L51="",$H51="",$AG51<=0),"",MAX(0,TODAY()-($H51+Settings!$J$6))) | AO51: =IF(OR($L51="",$S51=0,$AI51=""),0,ROUND($S51-$AI51,2)) -> 0 | AP51: =IF($L51="","",ROUND($L51+$AO51,2)) -> 880 | AR51: =IF($L51="","",IF(ISNUMBER($F51),$F51,IF(ISNUMBER($G51),$G51,""))) -> 46106 | AS51: =IF(OR($L51="",$AR51=""),"",DATE(YEAR($AR51),MONTH($AR51),1)) -> 46082 | AT51: =IF($L51="","",IF($AR51<>"",YEAR($AR51),IF(ISNUMBER($H51),YEAR($H51),""))) -> 2026
A52: Charlotte | B52: Penni Black | C52: C | D52: 22004246 | E52: Alethea Tabor | F52: 46119 | H52: 46101 | I52: N | J52: Complete | K52: 40 | L52: 4046.2 | M52: =IF(OR($K52="",$L52=""),"",$L52/$K52) -> 101.155 | N52: 0.2 | O52: =IF($L52="","",$L52*IF($N52="",Settings!$J$11,$N52)) -> 809.24 | P52: =IF($L52="","",$L52+$O52) -> 4855.44 | Q52: Yes | S52: =IF($L52="","",IF($Q52<>"Yes",0,IF($R52<>"",$R52,ROUND($L52*Settings!$J$4,2)))) -> 404.62 | T52: =IF($L52="","",$P52+$S52) -> 5260.06 | U52: =IF($L52="","",ROUND($P52/2,2)+$S52) -> 2832.34 | V52: 5255.44 | W52: BACS | X52: 46112 | AE52: =IF($L52="","",SUM($V52,$Y52,$AB52)) -> 5255.44 | AF52: =IF(OR($L52="",$T52=0),"",IF(OR($J52="Complete",$J52="Paid in Full"),1,$AE52/$T52)) -> 1 | AG52: =IF($L52="","",IF(OR($J52="Cancelled",$J52="Complete",$J52="Paid in Full"),0,ROUND($T52-$AE52,2))) -> 0 | AH52: =IF(OR($L52="",$H52="",$AG52<=0),"",MAX(0,TODAY()-($H52+Settings!$J$6))) | AI52: 404.62 | AJ52: Miss A B Tabor | AK52: 56-00-31 | AL52: 69607451 | AM52: BACS | AN52: 46138 | AO52: =IF(OR($L52="",$S52=0,$AI52=""),0,ROUND($S52-$AI52,2)) -> 0 | AP52: =IF($L52="","",ROUND($L52+$AO52,2)) -> 4046.2 | AR52: =IF($L52="","",IF(ISNUMBER($F52),$F52,IF(ISNUMBER($G52),$G52,""))) -> 46119 | AS52: =IF(OR($L52="",$AR52=""),"",DATE(YEAR($AR52),MONTH($AR52),1)) -> 46113 | AT52: =IF($L52="","",IF($AR52<>"",YEAR($AR52),IF(ISNUMBER($H52),YEAR($H52),""))) -> 2026
A53: Danelle | B53: Penni Black | C53: C | D53: 22004247 | E53: ScotiaBank | F53: 46120 | H53: 46103 | I53: N | J53: Complete | K53: 60 | L53: 10683 | M53: =IF(OR($K53="",$L53=""),"",$L53/$K53) -> 178.05 | N53: 0.2 | O53: =IF($L53="","",$L53*IF($N53="",Settings!$J$11,$N53)) -> 2136.6 | P53: =IF($L53="","",$L53+$O53) -> 12819.6 | Q53: No | S53: =IF($L53="","",IF($Q53<>"Yes",0,IF($R53<>"",$R53,ROUND($L53*Settings!$J$4,2)))) -> 0 | T53: =IF($L53="","",$P53+$S53) -> 12819.6 | U53: =IF($L53="","",ROUND($P53/2,2)+$S53) -> 6409.8 | V53: 13887.9 | W53: CC | X53: 46106 | AE53: =IF($L53="","",SUM($V53,$Y53,$AB53)) -> 13887.9 | AF53: =IF(OR($L53="",$T53=0),"",IF(OR($J53="Complete",$J53="Paid in Full"),1,$AE53/$T53)) -> 1 | AG53: =IF($L53="","",IF(OR($J53="Cancelled",$J53="Complete",$J53="Paid in Full"),0,ROUND($T53-$AE53,2))) -> 0 | AH53: =IF(OR($L53="",$H53="",$AG53<=0),"",MAX(0,TODAY()-($H53+Settings!$J$6))) | AM53: CC | AN53: 46126 | AO53: =IF(OR($L53="",$S53=0,$AI53=""),0,ROUND($S53-$AI53,2)) -> 0 | AP53: =IF($L53="","",ROUND($L53+$AO53,2)) -> 10683 | AR53: =IF($L53="","",IF(ISNUMBER($F53),$F53,IF(ISNUMBER($G53),$G53,""))) -> 46120 | AS53: =IF(OR($L53="",$AR53=""),"",DATE(YEAR($AR53),MONTH($AR53),1)) -> 46113 | AT53: =IF($L53="","",IF($AR53<>"",YEAR($AR53),IF(ISNUMBER($H53),YEAR($H53),""))) -> 2026
A54: Danelle | B54: Penni Black | C54: C | D54: 22004248 | E54: House of Decant | F54: 46106 | H54: 46105 | I54: R | J54: Complete | K54: 40 | L54: 124 | M54: =IF(OR($K54="",$L54=""),"",$L54/$K54) -> 3.1 | N54: 0.2 | O54: =IF($L54="","",$L54*IF($N54="",Settings!$J$11,$N54)) -> 24.8 | P54: =IF($L54="","",$L54+$O54) -> 148.8 | Q54: No | S54: =IF($L54="","",IF($Q54<>"Yes",0,IF($R54<>"",$R54,ROUND($L54*Settings!$J$4,2)))) -> 0 | T54: =IF($L54="","",$P54+$S54) -> 148.8 | U54: =IF($L54="","",ROUND($P54/2,2)+$S54) -> 74.4 | AE54: =IF($L54="","",SUM($V54,$Y54,$AB54)) -> 0 | AF54: =IF(OR($L54="",$T54=0),"",IF(OR($J54="Complete",$J54="Paid in Full"),1,$AE54/$T54)) -> 1 | AG54: =IF($L54="","",IF(OR($J54="Cancelled",$J54="Complete",$J54="Paid in Full"),0,ROUND($T54-$AE54,2))) -> 0 | AH54: =IF(OR($L54="",$H54="",$AG54<=0),"",MAX(0,TODAY()-($H54+Settings!$J$6))) | AO54: =IF(OR($L54="",$S54=0,$AI54=""),0,ROUND($S54-$AI54,2)) -> 0 | AP54: =IF($L54="","",ROUND($L54+$AO54,2)) -> 124 | AR54: =IF($L54="","",IF(ISNUMBER($F54),$F54,IF(ISNUMBER($G54),$G54,""))) -> 46106 | AS54: =IF(OR($L54="",$AR54=""),"",DATE(YEAR($AR54),MONTH($AR54),1)) -> 46082 | AT54: =IF($L54="","",IF($AR54<>"",YEAR($AR54),IF(ISNUMBER($H54),YEAR($H54),""))) -> 2026
A55: Charlotte | B55: Penni Black | C55: C | D55: 22004249 | E55: Canada House | F55: 46105 | H55: 46105 | I55: R | J55: Complete | L55: 3414 | M55: =IF(OR($K55="",$L55=""),"",$L55/$K55) | N55: 0.2 | O55: =IF($L55="","",$L55*IF($N55="",Settings!$J$11,$N55)) -> 682.8 | P55: =IF($L55="","",$L55+$O55) -> 4096.8 | Q55: No | S55: =IF($L55="","",IF($Q55<>"Yes",0,IF($R55<>"",$R55,ROUND($L55*Settings!$J$4,2)))) -> 0 | T55: =IF($L55="","",$P55+$S55) -> 4096.8 | U55: =IF($L55="","",ROUND($P55/2,2)+$S55) -> 2048.4 | V55: 4096.8 | W55: BACS | X55: 46112 | AE55: =IF($L55="","",SUM($V55,$Y55,$AB55)) -> 4096.8 | AF55: =IF(OR($L55="",$T55=0),"",IF(OR($J55="Complete",$J55="Paid in Full"),1,$AE55/$T55)) -> 1 | AG55: =IF($L55="","",IF(OR($J55="Cancelled",$J55="Complete",$J55="Paid in Full"),0,ROUND($T55-$AE55,2))) -> 0 | AH55: =IF(OR($L55="",$H55="",$AG55<=0),"",MAX(0,TODAY()-($H55+Settings!$J$6))) | AO55: =IF(OR($L55="",$S55=0,$AI55=""),0,ROUND($S55-$AI55,2)) -> 0 | AP55: =IF($L55="","",ROUND($L55+$AO55,2)) -> 3414 | AR55: =IF($L55="","",IF(ISNUMBER($F55),$F55,IF(ISNUMBER($G55),$G55,""))) -> 46105 | AS55: =IF(OR($L55="",$AR55=""),"",DATE(YEAR($AR55),MONTH($AR55),1)) -> 46082 | AT55: =IF($L55="","",IF($AR55<>"",YEAR($AR55),IF(ISNUMBER($H55),YEAR($H55),""))) -> 2026
A56: Danelle | B56: Penni Black | C56: C | D56: 22004250 | E56: High Commission of Canada | F56: 46113 | H56: 46106 | I56: R | J56: Complete | K56: 22 | L56: 2045.65 | M56: =IF(OR($K56="",$L56=""),"",$L56/$K56) -> 92.984091 | N56: 0.2 | O56: =IF($L56="","",$L56*IF($N56="",Settings!$J$11,$N56)) -> 409.13 | P56: =IF($L56="","",$L56+$O56) -> 2454.78 | Q56: No | S56: =IF($L56="","",IF($Q56<>"Yes",0,IF($R56<>"",$R56,ROUND($L56*Settings!$J$4,2)))) -> 0 | T56: =IF($L56="","",$P56+$S56) -> 2454.78 | U56: =IF($L56="","",ROUND($P56/2,2)+$S56) -> 1227.39 | V56: 2454.78 | W56: BACS | X56: 46119 | AE56: =IF($L56="","",SUM($V56,$Y56,$AB56)) -> 2454.78 | AF56: =IF(OR($L56="",$T56=0),"",IF(OR($J56="Complete",$J56="Paid in Full"),1,$AE56/$T56)) -> 1 | AG56: =IF($L56="","",IF(OR($J56="Cancelled",$J56="Complete",$J56="Paid in Full"),0,ROUND($T56-$AE56,2))) -> 0 | AH56: =IF(OR($L56="",$H56="",$AG56<=0),"",MAX(0,TODAY()-($H56+Settings!$J$6))) | AJ56: Canadian High Commission | AK56: 20-67-59 | AL56: 50824313 | AM56: BACS | AN56: 46138 | AO56: =IF(OR($L56="",$S56=0,$AI56=""),0,ROUND($S56-$AI56,2)) -> 0 | AP56: =IF($L56="","",ROUND($L56+$AO56,2)) -> 2045.65 | AQ56: REF; IFFEd DINNER 1.4.26 | AR56: =IF($L56="","",IF(ISNUMBER($F56),$F56,IF(ISNUMBER($G56),$G56,""))) -> 46113 | AS56: =IF(OR($L56="",$AR56=""),"",DATE(YEAR($AR56),MONTH($AR56),1)) -> 46113 | AT56: =IF($L56="","",IF($AR56<>"",YEAR($AR56),IF(ISNUMBER($H56),YEAR($H56),""))) -> 2026
A57: Danelle | B57: Penni Black | C57: C | D57: 22004251 | E57: House of Decant | F57: 46114 | H57: 46106 | I57: R | J57: Complete | K57: 80 | L57: 1072 | M57: =IF(OR($K57="",$L57=""),"",$L57/$K57) -> 13.4 | N57: 0.2 | O57: =IF($L57="","",$L57*IF($N57="",Settings!$J$11,$N57)) -> 214.4 | P57: =IF($L57="","",$L57+$O57) -> 1286.4 | Q57: No | S57: =IF($L57="","",IF($Q57<>"Yes",0,IF($R57<>"",$R57,ROUND($L57*Settings!$J$4,2)))) -> 0 | T57: =IF($L57="","",$P57+$S57) -> 1286.4 | U57: =IF($L57="","",ROUND($P57/2,2)+$S57) -> 643.2 | V57: 1286.4 | W57: BACS | X57: 46125 | AE57: =IF($L57="","",SUM($V57,$Y57,$AB57)) -> 1286.4 | AF57: =IF(OR($L57="",$T57=0),"",IF(OR($J57="Complete",$J57="Paid in Full"),1,$AE57/$T57)) -> 1 | AG57: =IF($L57="","",IF(OR($J57="Cancelled",$J57="Complete",$J57="Paid in Full"),0,ROUND($T57-$AE57,2))) -> 0 | AH57: =IF(OR($L57="",$H57="",$AG57<=0),"",MAX(0,TODAY()-($H57+Settings!$J$6))) | AO57: =IF(OR($L57="",$S57=0,$AI57=""),0,ROUND($S57-$AI57,2)) -> 0 | AP57: =IF($L57="","",ROUND($L57+$AO57,2)) -> 1072 | AR57: =IF($L57="","",IF(ISNUMBER($F57),$F57,IF(ISNUMBER($G57),$G57,""))) -> 46114 | AS57: =IF(OR($L57="",$AR57=""),"",DATE(YEAR($AR57),MONTH($AR57),1)) -> 46113 | AT57: =IF($L57="","",IF($AR57<>"",YEAR($AR57),IF(ISNUMBER($H57),YEAR($H57),""))) -> 2026
A58: Charlotte | B58: Penni Black | C58: C | D58: 22004252 | E58: Delegation european union - Cyprus HC | F58: 46128 | H58: 46112 | I58: R | J58: Complete | L58: 1106 | M58: =IF(OR($K58="",$L58=""),"",$L58/$K58) | N58: 0.2 | O58: =IF($L58="","",$L58*IF($N58="",Settings!$J$11,$N58)) -> 221.2 | P58: =IF($L58="","",$L58+$O58) -> 1327.2 | Q58: No | S58: =IF($L58="","",IF($Q58<>"Yes",0,IF($R58<>"",$R58,ROUND($L58*Settings!$J$4,2)))) -> 0 | T58: =IF($L58="","",$P58+$S58) -> 1327.2 | U58: =IF($L58="","",ROUND($P58/2,2)+$S58) -> 663.6 | V58: 1372.2 | W58: BACS | X58: 46114 | AE58: =IF($L58="","",SUM($V58,$Y58,$AB58)) -> 1372.2 | AF58: =IF(OR($L58="",$T58=0),"",IF(OR($J58="Complete",$J58="Paid in Full"),1,$AE58/$T58)) -> 1 | AG58: =IF($L58="","",IF(OR($J58="Cancelled",$J58="Complete",$J58="Paid in Full"),0,ROUND($T58-$AE58,2))) -> 0 | AH58: =IF(OR($L58="",$H58="",$AG58<=0),"",MAX(0,TODAY()-($H58+Settings!$J$6))) | AO58: =IF(OR($L58="",$S58=0,$AI58=""),0,ROUND($S58-$AI58,2)) -> 0 | AP58: =IF($L58="","",ROUND($L58+$AO58,2)) -> 1106 | AR58: =IF($L58="","",IF(ISNUMBER($F58),$F58,IF(ISNUMBER($G58),$G58,""))) -> 46128 | AS58: =IF(OR($L58="",$AR58=""),"",DATE(YEAR($AR58),MONTH($AR58),1)) -> 46113 | AT58: =IF($L58="","",IF($AR58<>"",YEAR($AR58),IF(ISNUMBER($H58),YEAR($H58),""))) -> 2026
A59: Charlotte | B59: Penni Black | C59: C | D59: 22004253 | E59: Berkeley | F59: 46134 | H59: 46112 | I59: R | J59: Complete | L59: 1548 | M59: =IF(OR($K59="",$L59=""),"",$L59/$K59) | N59: 0.2 | O59: =IF($L59="","",$L59*IF($N59="",Settings!$J$11,$N59)) -> 309.6 | P59: =IF($L59="","",$L59+$O59) -> 1857.6 | Q59: Yes | S59: =IF($L59="","",IF($Q59<>"Yes",0,IF($R59<>"",$R59,ROUND($L59*Settings!$J$4,2)))) -> 154.8 | T59: =IF($L59="","",$P59+$S59) -> 2012.4 | U59: =IF($L59="","",ROUND($P59/2,2)+$S59) -> 1083.6 | V59: 1857.6 | W59: BACS | X59: 46121 | AE59: =IF($L59="","",SUM($V59,$Y59,$AB59)) -> 1857.6 | AF59: =IF(OR($L59="",$T59=0),"",IF(OR($J59="Complete",$J59="Paid in Full"),1,$AE59/$T59)) -> 1 | AG59: =IF($L59="","",IF(OR($J59="Cancelled",$J59="Complete",$J59="Paid in Full"),0,ROUND($T59-$AE59,2))) -> 0 | AH59: =IF(OR($L59="",$H59="",$AG59<=0),"",MAX(0,TODAY()-($H59+Settings!$J$6))) | AI59: 154.8 | AO59: =IF(OR($L59="",$S59=0,$AI59=""),0,ROUND($S59-$AI59,2)) -> 0 | AP59: =IF($L59="","",ROUND($L59+$AO59,2)) -> 1548 | AR59: =IF($L59="","",IF(ISNUMBER($F59),$F59,IF(ISNUMBER($G59),$G59,""))) -> 46134 | AS59: =IF(OR($L59="",$AR59=""),"",DATE(YEAR($AR59),MONTH($AR59),1)) -> 46113 | AT59: =IF($L59="","",IF($AR59<>"",YEAR($AR59),IF(ISNUMBER($H59),YEAR($H59),""))) -> 2026
A60: Danelle | B60: Penni Black | C60: C | D60: 22004254 | E60: House of Decant | H60: 46119 | I60: R | J60: Complete | K60: 65 | L60: 1105.5 | M60: =IF(OR($K60="",$L60=""),"",$L60/$K60) -> 17.007692 | N60: 0.2 | O60: =IF($L60="","",$L60*IF($N60="",Settings!$J$11,$N60)) -> 221.1 | P60: =IF($L60="","",$L60+$O60) -> 1326.6 | Q60: No | S60: =IF($L60="","",IF($Q60<>"Yes",0,IF($R60<>"",$R60,ROUND($L60*Settings!$J$4,2)))) -> 0 | T60: =IF($L60="","",$P60+$S60) -> 1326.6 | U60: =IF($L60="","",ROUND($P60/2,2)+$S60) -> 663.3 | V60: 1326.6 | W60: BACS | X60: 46125 | AE60: =IF($L60="","",SUM($V60,$Y60,$AB60)) -> 1326.6 | AF60: =IF(OR($L60="",$T60=0),"",IF(OR($J60="Complete",$J60="Paid in Full"),1,$AE60/$T60)) -> 1 | AG60: =IF($L60="","",IF(OR($J60="Cancelled",$J60="Complete",$J60="Paid in Full"),0,ROUND($T60-$AE60,2))) -> 0 | AH60: =IF(OR($L60="",$H60="",$AG60<=0),"",MAX(0,TODAY()-($H60+Settings!$J$6))) | AO60: =IF(OR($L60="",$S60=0,$AI60=""),0,ROUND($S60-$AI60,2)) -> 0 | AP60: =IF($L60="","",ROUND($L60+$AO60,2)) -> 1105.5 | AQ60: Event dates: 14&15 April 2026. | AR60: =IF($L60="","",IF(ISNUMBER($F60),$F60,IF(ISNUMBER($G60),$G60,""))) | AS60: =IF(OR($L60="",$AR60=""),"",DATE(YEAR($AR60),MONTH($AR60),1)) | AT60: =IF($L60="","",IF($AR60<>"",YEAR($AR60),IF(ISNUMBER($H60),YEAR($H60),""))) -> 2026
A61: Danelle | B61: Penni Black | C61: C | D61: 22004255 | E61: Mewburn Ellis | F61: 46148 | H61: 46119 | I61: R | J61: Complete | K61: 40 | L61: 1934.1 | M61: =IF(OR($K61="",$L61=""),"",$L61/$K61) -> 48.3525 | N61: 0.2 | O61: =IF($L61="","",$L61*IF($N61="",Settings!$J$11,$N61)) -> 386.82 | P61: =IF($L61="","",$L61+$O61) -> 2320.92 | Q61: No | S61: =IF($L61="","",IF($Q61<>"Yes",0,IF($R61<>"",$R61,ROUND($L61*Settings!$J$4,2)))) -> 0 | T61: =IF($L61="","",$P61+$S61) -> 2320.92 | U61: =IF($L61="","",ROUND($P61/2,2)+$S61) -> 1160.46 | V61: 2514.33 | W61: BACS | X61: 46126 | AE61: =IF($L61="","",SUM($V61,$Y61,$AB61)) -> 2514.33 | AF61: =IF(OR($L61="",$T61=0),"",IF(OR($J61="Complete",$J61="Paid in Full"),1,$AE61/$T61)) -> 1 | AG61: =IF($L61="","",IF(OR($J61="Cancelled",$J61="Complete",$J61="Paid in Full"),0,ROUND($T61-$AE61,2))) -> 0 | AH61: =IF(OR($L61="",$H61="",$AG61<=0),"",MAX(0,TODAY()-($H61+Settings!$J$6))) | AJ61: Mewburn Ellis LLP | AK61: 20-13-42 | AL61: 23238083 | AM61: BACS | AN61: 46177 | AO61: =IF(OR($L61="",$S61=0,$AI61=""),0,ROUND($S61-$AI61,2)) -> 0 | AP61: =IF($L61="","",ROUND($L61+$AO61,2)) -> 1934.1 | AR61: =IF($L61="","",IF(ISNUMBER($F61),$F61,IF(ISNUMBER($G61),$G61,""))) -> 46148 | AS61: =IF(OR($L61="",$AR61=""),"",DATE(YEAR($AR61),MONTH($AR61),1)) -> 46143 | AT61: =IF($L61="","",IF($AR61<>"",YEAR($AR61),IF(ISNUMBER($H61),YEAR($H61),""))) -> 2026
A62: Danelle | B62: Penni Black | C62: C | D62: 22004256 | E62: The Event Book - Voltwise | F62: 46140 | H62: 46121 | I62: N | J62: Cancelled | K62: 33 | L62: 3179.15 | M62: =IF(OR($K62="",$L62=""),"",$L62/$K62) -> 96.337879 | N62: 0.2 | O62: =IF($L62="","",$L62*IF($N62="",Settings!$J$11,$N62)) -> 635.83 | P62: =IF($L62="","",$L62+$O62) -> 3814.98 | Q62: No | S62: =IF($L62="","",IF($Q62<>"Yes",0,IF($R62<>"",$R62,ROUND($L62*Settings!$J$4,2)))) -> 0 | T62: =IF($L62="","",$P62+$S62) -> 3814.98 | U62: =IF($L62="","",ROUND($P62/2,2)+$S62) -> 1907.49 | AE62: =IF($L62="","",SUM($V62,$Y62,$AB62)) -> 0 | AF62: =IF(OR($L62="",$T62=0),"",IF(OR($J62="Complete",$J62="Paid in Full"),1,$AE62/$T62)) -> 0 | AG62: =IF($L62="","",IF(OR($J62="Cancelled",$J62="Complete",$J62="Paid in Full"),0,ROUND($T62-$AE62,2))) -> 0 | AH62: =IF(OR($L62="",$H62="",$AG62<=0),"",MAX(0,TODAY()-($H62+Settings!$J$6))) | AO62: =IF(OR($L62="",$S62=0,$AI62=""),0,ROUND($S62-$AI62,2)) -> 0 | AP62: =IF($L62="","",ROUND($L62+$AO62,2)) -> 3179.15 | AR62: =IF($L62="","",IF(ISNUMBER($F62),$F62,IF(ISNUMBER($G62),$G62,""))) -> 46140 | AS62: =IF(OR($L62="",$AR62=""),"",DATE(YEAR($AR62),MONTH($AR62),1)) -> 46113 | AT62: =IF($L62="","",IF($AR62<>"",YEAR($AR62),IF(ISNUMBER($H62),YEAR($H62),""))) -> 2026
A63: Danelle | B63: Penni Black | C63: C | D63: 22004257 | E63: Canada-UK Chamber of Commerce | F63: 46140 | H63: 46121 | I63: R | J63: Complete | K63: 30 | L63: 1825.65 | M63: =IF(OR($K63="",$L63=""),"",$L63/$K63) -> 60.855 | N63: 0.2 | O63: =IF($L63="","",$L63*IF($N63="",Settings!$J$11,$N63)) -> 365.13 | P63: =IF($L63="","",$L63+$O63) -> 2190.78 | Q63: Yes | S63: =IF($L63="","",IF($Q63<>"Yes",0,IF($R63<>"",$R63,ROUND($L63*Settings!$J$4,2)))) -> 182.57 | T63: =IF($L63="","",$P63+$S63) -> 2373.35 | U63: =IF($L63="","",ROUND($P63/2,2)+$S63) -> 1277.96 | V63: 2373.35 | W63: BACS | X63: 46136 | AE63: =IF($L63="","",SUM($V63,$Y63,$AB63)) -> 2373.35 | AF63: =IF(OR($L63="",$T63=0),"",IF(OR($J63="Complete",$J63="Paid in Full"),1,$AE63/$T63)) -> 1 | AG63: =IF($L63="","",IF(OR($J63="Cancelled",$J63="Complete",$J63="Paid in Full"),0,ROUND($T63-$AE63,2))) -> 0 | AH63: =IF(OR($L63="",$H63="",$AG63<=0),"",MAX(0,TODAY()-($H63+Settings!$J$6))) | AI63: 182.57 | AJ63: Canada-UK Chamber of Commerce | AK63: 29364 | AL63: 18260492 | AM63: BACS | AN63: 46168 | AO63: =IF(OR($L63="",$S63=0,$AI63=""),0,ROUND($S63-$AI63,2)) -> 0 | AP63: =IF($L63="","",ROUND($L63+$AO63,2)) -> 1825.65 | AR63: =IF($L63="","",IF(ISNUMBER($F63),$F63,IF(ISNUMBER($G63),$G63,""))) -> 46140 | AS63: =IF(OR($L63="",$AR63=""),"",DATE(YEAR($AR63),MONTH($AR63),1)) -> 46113 | AT63: =IF($L63="","",IF($AR63<>"",YEAR($AR63),IF(ISNUMBER($H63),YEAR($H63),""))) -> 2026
A64: Danelle | B64: Penni Black | C64: P | D64: 22004258 | E64: David & Nigel | F64: 46192 | H64: 46127 | I64: R | J64: Complete | K64: 32 | L64: 4713.25 | M64: =IF(OR($K64="",$L64=""),"",$L64/$K64) -> 147.28906 | N64: 0.2 | O64: =IF($L64="","",$L64*IF($N64="",Settings!$J$11,$N64)) -> 942.65 | P64: =IF($L64="","",$L64+$O64) -> 5655.9 | Q64: Yes | S64: =IF($L64="","",IF($Q64<>"Yes",0,IF($R64<>"",$R64,ROUND($L64*Settings!$J$4,2)))) -> 471.33 | T64: =IF($L64="","",$P64+$S64) -> 6127.23 | U64: =IF($L64="","",ROUND($P64/2,2)+$S64) -> 3299.28 | V64: 2827.94 | W64: CC | X64: 46127 | Y64: 3495.97 | Z64: CC | AE64: =IF($L64="","",SUM($V64,$Y64,$AB64)) -> 6323.91 | AF64: =IF(OR($L64="",$T64=0),"",IF(OR($J64="Complete",$J64="Paid in Full"),1,$AE64/$T64)) -> 1 | AG64: =IF($L64="","",IF(OR($J64="Cancelled",$J64="Complete",$J64="Paid in Full"),0,ROUND($T64-$AE64,2))) -> 0 | AH64: =IF(OR($L64="",$H64="",$AG64<=0),"",MAX(0,TODAY()-($H64+Settings!$J$6))) | AI64: 471.33 | AM64: CC | AN64: 46204 | AO64: =IF(OR($L64="",$S64=0,$AI64=""),0,ROUND($S64-$AI64,2)) -> 0 | AP64: =IF($L64="","",ROUND($L64+$AO64,2)) -> 4713.25 | AR64: =IF($L64="","",IF(ISNUMBER($F64),$F64,IF(ISNUMBER($G64),$G64,""))) -> 46192 | AS64: =IF(OR($L64="",$AR64=""),"",DATE(YEAR($AR64),MONTH($AR64),1)) -> 46174 | AT64: =IF($L64="","",IF($AR64<>"",YEAR($AR64),IF(ISNUMBER($H64),YEAR($H64),""))) -> 2026
A65: Danelle | B65: Penni Black | C65: P | D65: 22004260 | E65: Diane Hay | F65: 46172 | H65: 46127 | I65: R | J65: Complete | K65: 50 | L65: 4478.5 | M65: =IF(OR($K65="",$L65=""),"",$L65/$K65) -> 89.57 | N65: 0.2 | O65: =IF($L65="","",$L65*IF($N65="",Settings!$J$11,$N65)) -> 895.7 | P65: =IF($L65="","",$L65+$O65) -> 5374.2 | Q65: Yes | S65: =IF($L65="","",IF($Q65<>"Yes",0,IF($R65<>"",$R65,ROUND($L65*Settings!$J$4,2)))) -> 447.85 | T65: =IF($L65="","",$P65+$S65) -> 5822.05 | U65: =IF($L65="","",ROUND($P65/2,2)+$S65) -> 3134.95 | V65: 2687.1 | W65: CC | X65: 46136 | Y65: 2597.98 | AE65: =IF($L65="","",SUM($V65,$Y65,$AB65)) -> 5285.08 | AF65: =IF(OR($L65="",$T65=0),"",IF(OR($J65="Complete",$J65="Paid in Full"),1,$AE65/$T65)) -> 1 | AG65: =IF($L65="","",IF(OR($J65="Cancelled",$J65="Complete",$J65="Paid in Full"),0,ROUND($T65-$AE65,2))) -> 0 | AH65: =IF(OR($L65="",$H65="",$AG65<=0),"",MAX(0,TODAY()-($H65+Settings!$J$6))) | AI65: 447.85 | AM65: CC | AN65: 46174 | AO65: =IF(OR($L65="",$S65=0,$AI65=""),0,ROUND($S65-$AI65,2)) -> 0 | AP65: =IF($L65="","",ROUND($L65+$AO65,2)) -> 4478.5 | AR65: =IF($L65="","",IF(ISNUMBER($F65),$F65,IF(ISNUMBER($G65),$G65,""))) -> 46172 | AS65: =IF(OR($L65="",$AR65=""),"",DATE(YEAR($AR65),MONTH($AR65),1)) -> 46143 | AT65: =IF($L65="","",IF($AR65<>"",YEAR($AR65),IF(ISNUMBER($H65),YEAR($H65),""))) -> 2026
A66: Danelle | B66: Penni Black | C66: C | D66: 22004261 | E66: Zenith Bank Ltd - Day 7 & 8 | H66: 46132 | I66: R | J66: Complete | K66: 32 | L66: 3877.6 | M66: =IF(OR($K66="",$L66=""),"",$L66/$K66) -> 121.175 | N66: 0.2 | O66: =IF($L66="","",$L66*IF($N66="",Settings!$J$11,$N66)) -> 775.52 | P66: =IF($L66="","",$L66+$O66) -> 4653.12 | Q66: Yes | S66: =IF($L66="","",IF($Q66<>"Yes",0,IF($R66<>"",$R66,ROUND($L66*Settings!$J$4,2)))) -> 387.76 | T66: =IF($L66="","",$P66+$S66) -> 5040.88 | U66: =IF($L66="","",ROUND($P66/2,2)+$S66) -> 2714.32 | V66: 5040.88 | W66: BACS | X66: 46140 | AE66: =IF($L66="","",SUM($V66,$Y66,$AB66)) -> 5040.88 | AF66: =IF(OR($L66="",$T66=0),"",IF(OR($J66="Complete",$J66="Paid in Full"),1,$AE66/$T66)) -> 1 | AG66: =IF($L66="","",IF(OR($J66="Cancelled",$J66="Complete",$J66="Paid in Full"),0,ROUND($T66-$AE66,2))) -> 0 | AH66: =IF(OR($L66="",$H66="",$AG66<=0),"",MAX(0,TODAY()-($H66+Settings!$J$6))) | AI66: 387.76 | AJ66: Zenith Bank UK Ltd | AK66: 40-02-50 | AL66: 81253972 | AM66: BACS | AN66: 46168 | AO66: =IF(OR($L66="",$S66=0,$AI66=""),0,ROUND($S66-$AI66,2)) -> 0 | AP66: =IF($L66="","",ROUND($L66+$AO66,2)) -> 3877.6 | AQ66: Event dates: 7 & 8 May. | AR66: =IF($L66="","",IF(ISNUMBER($F66),$F66,IF(ISNUMBER($G66),$G66,""))) | AS66: =IF(OR($L66="",$AR66=""),"",DATE(YEAR($AR66),MONTH($AR66),1)) | AT66: =IF($L66="","",IF($AR66<>"",YEAR($AR66),IF(ISNUMBER($H66),YEAR($H66),""))) -> 2026
A67: Danelle | B67: Penni Black | C67: C | D67: 22004262 | E67: Griffin University | F67: 46160 | H67: 46134 | I67: N | J67: Complete | K67: 50 | L67: 3131.4 | M67: =IF(OR($K67="",$L67=""),"",$L67/$K67) -> 62.628 | N67: 0.2 | O67: =IF($L67="","",$L67*IF($N67="",Settings!$J$11,$N67)) -> 626.28 | P67: =IF($L67="","",$L67+$O67) -> 3757.68 | Q67: Yes | S67: =IF($L67="","",IF($Q67<>"Yes",0,IF($R67<>"",$R67,ROUND($L67*Settings!$J$4,2)))) -> 313.14 | T67: =IF($L67="","",$P67+$S67) -> 4070.82 | U67: =IF($L67="","",ROUND($P67/2,2)+$S67) -> 2191.98 | V67: 4070.82 | W67: CC | X67: 46147 | AE67: =IF($L67="","",SUM($V67,$Y67,$AB67)) -> 4070.82 | AF67: =IF(OR($L67="",$T67=0),"",IF(OR($J67="Complete",$J67="Paid in Full"),1,$AE67/$T67)) -> 1 | AG67: =IF($L67="","",IF(OR($J67="Cancelled",$J67="Complete",$J67="Paid in Full"),0,ROUND($T67-$AE67,2))) -> 0 | AH67: =IF(OR($L67="",$H67="",$AG67<=0),"",MAX(0,TODAY()-($H67+Settings!$J$6))) | AI67: 313.14 | AM67: CC | AN67: 46161 | AO67: =IF(OR($L67="",$S67=0,$AI67=""),0,ROUND($S67-$AI67,2)) -> 0 | AP67: =IF($L67="","",ROUND($L67+$AO67,2)) -> 3131.4 | AR67: =IF($L67="","",IF(ISNUMBER($F67),$F67,IF(ISNUMBER($G67),$G67,""))) -> 46160 | AS67: =IF(OR($L67="",$AR67=""),"",DATE(YEAR($AR67),MONTH($AR67),1)) -> 46143 | AT67: =IF($L67="","",IF($AR67<>"",YEAR($AR67),IF(ISNUMBER($H67),YEAR($H67),""))) -> 2026
A68: Danelle | B68: Penni Black | C68: P | D68: 22004263 | E68: Sarah Gower | F68: 46179 | H68: 46135 | I68: N | J68: Complete | K68: 30 | L68: 1189.5 | M68: =IF(OR($K68="",$L68=""),"",$L68/$K68) -> 39.65 | N68: 0.2 | O68: =IF($L68="","",$L68*IF($N68="",Settings!$J$11,$N68)) -> 237.9 | P68: =IF($L68="","",$L68+$O68) -> 1427.4 | Q68: No | S68: =IF($L68="","",IF($Q68<>"Yes",0,IF($R68<>"",$R68,ROUND($L68*Settings!$J$4,2)))) -> 0 | T68: =IF($L68="","",$P68+$S68) -> 1427.4 | U68: =IF($L68="","",ROUND($P68/2,2)+$S68) -> 713.7 | V68: 1427.4 | W68: BACS | X68: 46162 | AE68: =IF($L68="","",SUM($V68,$Y68,$AB68)) -> 1427.4 | AF68: =IF(OR($L68="",$T68=0),"",IF(OR($J68="Complete",$J68="Paid in Full"),1,$AE68/$T68)) -> 1 | AG68: =IF($L68="","",IF(OR($J68="Cancelled",$J68="Complete",$J68="Paid in Full"),0,ROUND($T68-$AE68,2))) -> 0 | AH68: =IF(OR($L68="",$H68="",$AG68<=0),"",MAX(0,TODAY()-($H68+Settings!$J$6))) | AO68: =IF(OR($L68="",$S68=0,$AI68=""),0,ROUND($S68-$AI68,2)) -> 0 | AP68: =IF($L68="","",ROUND($L68+$AO68,2)) -> 1189.5 | AR68: =IF($L68="","",IF(ISNUMBER($F68),$F68,IF(ISNUMBER($G68),$G68,""))) -> 46179 | AS68: =IF(OR($L68="",$AR68=""),"",DATE(YEAR($AR68),MONTH($AR68),1)) -> 46174 | AT68: =IF($L68="","",IF($AR68<>"",YEAR($AR68),IF(ISNUMBER($H68),YEAR($H68),""))) -> 2026
A69: Danelle | B69: Penni Black | C69: C | D69: 22004264 | E69: Orbit Design Studio Ltd | F69: 46148 | H69: 46141 | I69: N | J69: Complete | K69: 30 | L69: 2237.5 | M69: =IF(OR($K69="",$L69=""),"",$L69/$K69) -> 74.583333 | N69: 0.2 | O69: =IF($L69="","",$L69*IF($N69="",Settings!$J$11,$N69)) -> 447.5 | P69: =IF($L69="","",$L69+$O69) -> 2685 | Q69: Yes | S69: =IF($L69="","",IF($Q69<>"Yes",0,IF($R69<>"",$R69,ROUND($L69*Settings!$J$4,2)))) -> 223.75 | T69: =IF($L69="","",$P69+$S69) -> 2908.75 | U69: =IF($L69="","",ROUND($P69/2,2)+$S69) -> 1566.25 | V69: 2908.75 | W69: CC | X69: 46132 | AE69: =IF($L69="","",SUM($V69,$Y69,$AB69)) -> 2908.75 | AF69: =IF(OR($L69="",$T69=0),"",IF(OR($J69="Complete",$J69="Paid in Full"),1,$AE69/$T69)) -> 1 | AG69: =IF($L69="","",IF(OR($J69="Cancelled",$J69="Complete",$J69="Paid in Full"),0,ROUND($T69-$AE69,2))) -> 0 | AH69: =IF(OR($L69="",$H69="",$AG69<=0),"",MAX(0,TODAY()-($H69+Settings!$J$6))) | AI69: 223.75 | AM69: CC | AN69: 46161 | AO69: =IF(OR($L69="",$S69=0,$AI69=""),0,ROUND($S69-$AI69,2)) -> 0 | AP69: =IF($L69="","",ROUND($L69+$AO69,2)) -> 2237.5 | AR69: =IF($L69="","",IF(ISNUMBER($F69),$F69,IF(ISNUMBER($G69),$G69,""))) -> 46148 | AS69: =IF(OR($L69="",$AR69=""),"",DATE(YEAR($AR69),MONTH($AR69),1)) -> 46143 | AT69: =IF($L69="","",IF($AR69<>"",YEAR($AR69),IF(ISNUMBER($H69),YEAR($H69),""))) -> 2026
A70: Danelle | B70: Penni Black | C70: C | D70: 22004265 | E70: Phaidon International | F70: 46183 | H70: 46141 | I70: N | J70: Complete | K70: 55 | L70: 2187.25 | M70: =IF(OR($K70="",$L70=""),"",$L70/$K70) -> 39.768182 | N70: 0.2 | O70: =IF($L70="","",$L70*IF($N70="",Settings!$J$11,$N70)) -> 437.45 | P70: =IF($L70="","",$L70+$O70) -> 2624.7 | Q70: Yes | S70: =IF($L70="","",IF($Q70<>"Yes",0,IF($R70<>"",$R70,ROUND($L70*Settings!$J$4,2)))) -> 218.73 | T70: =IF($L70="","",$P70+$S70) -> 2843.43 | U70: =IF($L70="","",ROUND($P70/2,2)+$S70) -> 1531.08 | V70: 2843.42 | W70: CC | X70: 46156 | AE70: =IF($L70="","",SUM($V70,$Y70,$AB70)) -> 2843.42 | AF70: =IF(OR($L70="",$T70=0),"",IF(OR($J70="Complete",$J70="Paid in Full"),1,$AE70/$T70)) -> 1 | AG70: =IF($L70="","",IF(OR($J70="Cancelled",$J70="Complete",$J70="Paid in Full"),0,ROUND($T70-$AE70,2))) -> 0 | AH70: =IF(OR($L70="",$H70="",$AG70<=0),"",MAX(0,TODAY()-($H70+Settings!$J$6))) | AI70: 218.73 | AM70: CC | AN70: 46202 | AO70: =IF(OR($L70="",$S70=0,$AI70=""),0,ROUND($S70-$AI70,2)) -> 0 | AP70: =IF($L70="","",ROUND($L70+$AO70,2)) -> 2187.25 | AR70: =IF($L70="","",IF(ISNUMBER($F70),$F70,IF(ISNUMBER($G70),$G70,""))) -> 46183 | AS70: =IF(OR($L70="",$AR70=""),"",DATE(YEAR($AR70),MONTH($AR70),1)) -> 46174 | AT70: =IF($L70="","",IF($AR70<>"",YEAR($AR70),IF(ISNUMBER($H70),YEAR($H70),""))) -> 2026
A71: Danelle | B71: Penni Black | C71: C | D71: 22004266 | E71: Canada House | F71: 46177 | H71: 46141 | I71: R | J71: Complete | K71: 30 | L71: 1934 | M71: =IF(OR($K71="",$L71=""),"",$L71/$K71) -> 64.466667 | N71: 0.2 | O71: =IF($L71="","",$L71*IF($N71="",Settings!$J$11,$N71)) -> 386.8 | P71: =IF($L71="","",$L71+$O71) -> 2320.8 | Q71: Yes | S71: =IF($L71="","",IF($Q71<>"Yes",0,IF($R71<>"",$R71,ROUND($L71*Settings!$J$4,2)))) -> 193.4 | T71: =IF($L71="","",$P71+$S71) -> 2514.2 | U71: =IF($L71="","",ROUND($P71/2,2)+$S71) -> 1353.8 | V71: 2358.2 | W71: BACS | X71: 46174 | AE71: =IF($L71="","",SUM($V71,$Y71,$AB71)) -> 2358.2 | AF71: =IF(OR($L71="",$T71=0),"",IF(OR($J71="Complete",$J71="Paid in Full"),1,$AE71/$T71)) -> 1 | AG71: =IF($L71="","",IF(OR($J71="Cancelled",$J71="Complete",$J71="Paid in Full"),0,ROUND($T71-$AE71,2))) -> 0 | AH71: =IF(OR($L71="",$H71="",$AG71<=0),"",MAX(0,TODAY()-($H71+Settings!$J$6))) | AI71: 193.4 | AJ71: Canada-UK Chamber of Commerce | AK71: 29364 | AL71: 18260492 | AM71: BACS | AN71: 46180 | AO71: =IF(OR($L71="",$S71=0,$AI71=""),0,ROUND($S71-$AI71,2)) -> 0 | AP71: =IF($L71="","",ROUND($L71+$AO71,2)) -> 1934 | AR71: =IF($L71="","",IF(ISNUMBER($F71),$F71,IF(ISNUMBER($G71),$G71,""))) -> 46177 | AS71: =IF(OR($L71="",$AR71=""),"",DATE(YEAR($AR71),MONTH($AR71),1)) -> 46174 | AT71: =IF($L71="","",IF($AR71<>"",YEAR($AR71),IF(ISNUMBER($H71),YEAR($H71),""))) -> 2026
A72: Danelle | B72: Penni Black | C72: C | D72: 22004267 | E72: Chew Events | F72: 46191 | H72: 46142 | I72: N | J72: Complete | K72: 200 | L72: 54536.5 | M72: =IF(OR($K72="",$L72=""),"",$L72/$K72) -> 272.6825 | N72: 0.2 | O72: =IF($L72="","",$L72*IF($N72="",Settings!$J$11,$N72)) -> 10907.3 | P72: =IF($L72="","",$L72+$O72) -> 65443.8 | Q72: Yes | S72: =IF($L72="","",IF($Q72<>"Yes",0,IF($R72<>"",$R72,ROUND($L72*Settings!$J$4,2)))) -> 5453.65 | T72: =IF($L72="","",$P72+$S72) -> 70897.45 | U72: =IF($L72="","",ROUND($P72/2,2)+$S72) -> 38175.55 | V72: 32721.84 | W72: CC | X72: 46194 | Y72: 38175.48 | Z72: CC | AA72: 46183 | AE72: =IF($L72="","",SUM($V72,$Y72,$AB72)) -> 70897.32 | AF72: =IF(OR($L72="",$T72=0),"",IF(OR($J72="Complete",$J72="Paid in Full"),1,$AE72/$T72)) -> 1 | AG72: =IF($L72="","",IF(OR($J72="Cancelled",$J72="Complete",$J72="Paid in Full"),0,ROUND($T72-$AE72,2))) -> 0 | AH72: =IF(OR($L72="",$H72="",$AG72<=0),"",MAX(0,TODAY()-($H72+Settings!$J$6))) | AI72: 5453.65 | AO72: =IF(OR($L72="",$S72=0,$AI72=""),0,ROUND($S72-$AI72,2)) -> 0 | AP72: =IF($L72="","",ROUND($L72+$AO72,2)) -> 54536.5 | AR72: =IF($L72="","",IF(ISNUMBER($F72),$F72,IF(ISNUMBER($G72),$G72,""))) -> 46191 | AS72: =IF(OR($L72="",$AR72=""),"",DATE(YEAR($AR72),MONTH($AR72),1)) -> 46174 | AT72: =IF($L72="","",IF($AR72<>"",YEAR($AR72),IF(ISNUMBER($H72),YEAR($H72),""))) -> 2026
A73: Danelle | B73: Penni Black | C73: C | D73: 22004268 | E73: Salt Productions | F73: 46176 | H73: 46142 | I73: N | J73: Complete | K73: 12 | M73: =IF(OR($K73="",$L73=""),"",$L73/$K73) | N73: 0.2 | O73: =IF($L73="","",$L73*IF($N73="",Settings!$J$11,$N73)) | P73: =IF($L73="","",$L73+$O73) | Q73: Yes | S73: =IF($L73="","",IF($Q73<>"Yes",0,IF($R73<>"",$R73,ROUND($L73*Settings!$J$4,2)))) | T73: =IF($L73="","",$P73+$S73) | U73: =IF($L73="","",ROUND($P73/2,2)+$S73) | AE73: =IF($L73="","",SUM($V73,$Y73,$AB73)) | AF73: =IF(OR($L73="",$T73=0),"",IF(OR($J73="Complete",$J73="Paid in Full"),1,$AE73/$T73)) | AG73: =IF($L73="","",IF(OR($J73="Cancelled",$J73="Complete",$J73="Paid in Full"),0,ROUND($T73-$AE73,2))) | AH73: =IF(OR($L73="",$H73="",$AG73<=0),"",MAX(0,TODAY()-($H73+Settings!$J$6))) | AO73: =IF(OR($L73="",$S73=0,$AI73=""),0,ROUND($S73-$AI73,2)) -> 0 | AP73: =IF($L73="","",ROUND($L73+$AO73,2)) | AR73: =IF($L73="","",IF(ISNUMBER($F73),$F73,IF(ISNUMBER($G73),$G73,""))) | AS73: =IF(OR($L73="",$AR73=""),"",DATE(YEAR($AR73),MONTH($AR73),1)) | AT73: =IF($L73="","",IF($AR73<>"",YEAR($AR73),IF(ISNUMBER($H73),YEAR($H73),"")))
A74: Danelle | B74: Penni Black | C74: C | D74: 22004269 | E74: Salt Productions | F74: 46177 | H74: 46142 | I74: N | J74: Complete | K74: 150 | L74: 7568 | M74: =IF(OR($K74="",$L74=""),"",$L74/$K74) -> 50.453333 | N74: 0.2 | O74: =IF($L74="","",$L74*IF($N74="",Settings!$J$11,$N74)) -> 1513.6 | P74: =IF($L74="","",$L74+$O74) -> 9081.6 | Q74: Yes | S74: =IF($L74="","",IF($Q74<>"Yes",0,IF($R74<>"",$R74,ROUND($L74*Settings!$J$4,2)))) -> 756.8 | T74: =IF($L74="","",$P74+$S74) -> 9838.4 | U74: =IF($L74="","",ROUND($P74/2,2)+$S74) -> 5297.6 | V74: 9081.6 | W74: CC | X74: 46161 | Y74: 14564.75 | Z74: CC | AA74: 46169 | AB74: 4470.6 | AC74: CC | AD74: 46175 | AE74: =IF($L74="","",SUM($V74,$Y74,$AB74)) -> 28116.95 | AF74: =IF(OR($L74="",$T74=0),"",IF(OR($J74="Complete",$J74="Paid in Full"),1,$AE74/$T74)) -> 1 | AG74: =IF($L74="","",IF(OR($J74="Cancelled",$J74="Complete",$J74="Paid in Full"),0,ROUND($T74-$AE74,2))) -> 0 | AH74: =IF(OR($L74="",$H74="",$AG74<=0),"",MAX(0,TODAY()-($H74+Settings!$J$6))) | AI74: 756.8 | AM74: CC | AN74: 46183 | AO74: =IF(OR($L74="",$S74=0,$AI74=""),0,ROUND($S74-$AI74,2)) -> 0 | AP74: =IF($L74="","",ROUND($L74+$AO74,2)) -> 7568 | AR74: =IF($L74="","",IF(ISNUMBER($F74),$F74,IF(ISNUMBER($G74),$G74,""))) -> 46177 | AS74: =IF(OR($L74="",$AR74=""),"",DATE(YEAR($AR74),MONTH($AR74),1)) -> 46174 | AT74: =IF($L74="","",IF($AR74<>"",YEAR($AR74),IF(ISNUMBER($H74),YEAR($H74),""))) -> 2026
A75: Danelle | B75: Penni Black | C75: C | D75: 22004270 | E75: House of Decant | F75: 46154 | H75: 46148 | I75: R | J75: Complete | K75: 30 | L75: 638 | M75: =IF(OR($K75="",$L75=""),"",$L75/$K75) -> 21.266667 | N75: 0.2 | O75: =IF($L75="","",$L75*IF($N75="",Settings!$J$11,$N75)) -> 127.6 | P75: =IF($L75="","",$L75+$O75) -> 765.6 | Q75: No | S75: =IF($L75="","",IF($Q75<>"Yes",0,IF($R75<>"",$R75,ROUND($L75*Settings!$J$4,2)))) -> 0 | T75: =IF($L75="","",$P75+$S75) -> 765.6 | U75: =IF($L75="","",ROUND($P75/2,2)+$S75) -> 382.8 | AE75: =IF($L75="","",SUM($V75,$Y75,$AB75)) -> 0 | AF75: =IF(OR($L75="",$T75=0),"",IF(OR($J75="Complete",$J75="Paid in Full"),1,$AE75/$T75)) -> 1 | AG75: =IF($L75="","",IF(OR($J75="Cancelled",$J75="Complete",$J75="Paid in Full"),0,ROUND($T75-$AE75,2))) -> 0 | AH75: =IF(OR($L75="",$H75="",$AG75<=0),"",MAX(0,TODAY()-($H75+Settings!$J$6))) | AO75: =IF(OR($L75="",$S75=0,$AI75=""),0,ROUND($S75-$AI75,2)) -> 0 | AP75: =IF($L75="","",ROUND($L75+$AO75,2)) -> 638 | AR75: =IF($L75="","",IF(ISNUMBER($F75),$F75,IF(ISNUMBER($G75),$G75,""))) -> 46154 | AS75: =IF(OR($L75="",$AR75=""),"",DATE(YEAR($AR75),MONTH($AR75),1)) -> 46143 | AT75: =IF($L75="","",IF($AR75<>"",YEAR($AR75),IF(ISNUMBER($H75),YEAR($H75),""))) -> 2026
A76: Danelle | B76: Penni Black | C76: C | D76: 22004271 | E76: House of Decant | F76: 46156 | H76: 46148 | I76: R | J76: Complete | K76: 20 | L76: 452 | M76: =IF(OR($K76="",$L76=""),"",$L76/$K76) -> 22.6 | N76: 0.2 | O76: =IF($L76="","",$L76*IF($N76="",Settings!$J$11,$N76)) -> 90.4 | P76: =IF($L76="","",$L76+$O76) -> 542.4 | Q76: No | S76: =IF($L76="","",IF($Q76<>"Yes",0,IF($R76<>"",$R76,ROUND($L76*Settings!$J$4,2)))) -> 0 | T76: =IF($L76="","",$P76+$S76) -> 542.4 | U76: =IF($L76="","",ROUND($P76/2,2)+$S76) -> 271.2 | AE76: =IF($L76="","",SUM($V76,$Y76,$AB76)) -> 0 | AF76: =IF(OR($L76="",$T76=0),"",IF(OR($J76="Complete",$J76="Paid in Full"),1,$AE76/$T76)) -> 1 | AG76: =IF($L76="","",IF(OR($J76="Cancelled",$J76="Complete",$J76="Paid in Full"),0,ROUND($T76-$AE76,2))) -> 0 | AH76: =IF(OR($L76="",$H76="",$AG76<=0),"",MAX(0,TODAY()-($H76+Settings!$J$6))) | AO76: =IF(OR($L76="",$S76=0,$AI76=""),0,ROUND($S76-$AI76,2)) -> 0 | AP76: =IF($L76="","",ROUND($L76+$AO76,2)) -> 452 | AR76: =IF($L76="","",IF(ISNUMBER($F76),$F76,IF(ISNUMBER($G76),$G76,""))) -> 46156 | AS76: =IF(OR($L76="",$AR76=""),"",DATE(YEAR($AR76),MONTH($AR76),1)) -> 46143 | AT76: =IF($L76="","",IF($AR76<>"",YEAR($AR76),IF(ISNUMBER($H76),YEAR($H76),""))) -> 2026
A77: Danelle | B77: Penni Black | C77: C | D77: 22004272 | E77: Cognizant | F77: 46154 | H77: 46149 | I77: R | J77: Complete | K77: 20 | L77: 2594 | M77: =IF(OR($K77="",$L77=""),"",$L77/$K77) -> 129.7 | N77: 0.2 | O77: =IF($L77="","",$L77*IF($N77="",Settings!$J$11,$N77)) -> 518.8 | P77: =IF($L77="","",$L77+$O77) -> 3112.8 | Q77: No | S77: =IF($L77="","",IF($Q77<>"Yes",0,IF($R77<>"",$R77,ROUND($L77*Settings!$J$4,2)))) -> 0 | T77: =IF($L77="","",$P77+$S77) -> 3112.8 | U77: =IF($L77="","",ROUND($P77/2,2)+$S77) -> 1556.4 | V77: 2594 | W77: CC | X77: 46150 | AE77: =IF($L77="","",SUM($V77,$Y77,$AB77)) -> 2594 | AF77: =IF(OR($L77="",$T77=0),"",IF(OR($J77="Complete",$J77="Paid in Full"),1,$AE77/$T77)) -> 1 | AG77: =IF($L77="","",IF(OR($J77="Cancelled",$J77="Complete",$J77="Paid in Full"),0,ROUND($T77-$AE77,2))) -> 0 | AH77: =IF(OR($L77="",$H77="",$AG77<=0),"",MAX(0,TODAY()-($H77+Settings!$J$6))) | AO77: =IF(OR($L77="",$S77=0,$AI77=""),0,ROUND($S77-$AI77,2)) -> 0 | AP77: =IF($L77="","",ROUND($L77+$AO77,2)) -> 2594 | AR77: =IF($L77="","",IF(ISNUMBER($F77),$F77,IF(ISNUMBER($G77),$G77,""))) -> 46154 | AS77: =IF(OR($L77="",$AR77=""),"",DATE(YEAR($AR77),MONTH($AR77),1)) -> 46143 | AT77: =IF($L77="","",IF($AR77<>"",YEAR($AR77),IF(ISNUMBER($H77),YEAR($H77),""))) -> 2026
A78: Danelle | B78: Penni Black | C78: C | D78: 22004273 | E78: Orbit Design Studio Ltd | H78: 46149 | I78: R | J78: Complete | K78: 75 | L78: 6483 | M78: =IF(OR($K78="",$L78=""),"",$L78/$K78) -> 86.44 | N78: 0.2 | O78: =IF($L78="","",$L78*IF($N78="",Settings!$J$11,$N78)) -> 1296.6 | P78: =IF($L78="","",$L78+$O78) -> 7779.6 | Q78: Yes | S78: =IF($L78="","",IF($Q78<>"Yes",0,IF($R78<>"",$R78,ROUND($L78*Settings!$J$4,2)))) -> 648.3 | T78: =IF($L78="","",$P78+$S78) -> 8427.9 | U78: =IF($L78="","",ROUND($P78/2,2)+$S78) -> 4538.1 | V78: 11469.6 | W78: CC | X78: 46150 | AE78: =IF($L78="","",SUM($V78,$Y78,$AB78)) -> 11469.6 | AF78: =IF(OR($L78="",$T78=0),"",IF(OR($J78="Complete",$J78="Paid in Full"),1,$AE78/$T78)) -> 1 | AG78: =IF($L78="","",IF(OR($J78="Cancelled",$J78="Complete",$J78="Paid in Full"),0,ROUND($T78-$AE78,2))) -> 0 | AH78: =IF(OR($L78="",$H78="",$AG78<=0),"",MAX(0,TODAY()-($H78+Settings!$J$6))) | AI78: 648.3 | AM78: CC | AN78: 46161 | AO78: =IF(OR($L78="",$S78=0,$AI78=""),0,ROUND($S78-$AI78,2)) -> 0 | AP78: =IF($L78="","",ROUND($L78+$AO78,2)) -> 6483 | AQ78: Event dates: 12-14 May. | AR78: =IF($L78="","",IF(ISNUMBER($F78),$F78,IF(ISNUMBER($G78),$G78,""))) | AS78: =IF(OR($L78="",$AR78=""),"",DATE(YEAR($AR78),MONTH($AR78),1)) | AT78: =IF($L78="","",IF($AR78<>"",YEAR($AR78),IF(ISNUMBER($H78),YEAR($H78),""))) -> 2026
A79: Danelle | B79: Penni Black | C79: C | D79: 22004274 | E79: Tabayer | F79: 45798 | H79: 46157 | I79: N | J79: Complete | K79: 30 | L79: 836 | M79: =IF(OR($K79="",$L79=""),"",$L79/$K79) -> 27.866667 | N79: 0.2 | O79: =IF($L79="","",$L79*IF($N79="",Settings!$J$11,$N79)) -> 167.2 | P79: =IF($L79="","",$L79+$O79) -> 1003.2 | Q79: Yes | S79: =IF($L79="","",IF($Q79<>"Yes",0,IF($R79<>"",$R79,ROUND($L79*Settings!$J$4,2)))) -> 83.6 | T79: =IF($L79="","",$P79+$S79) -> 1086.8 | U79: =IF($L79="","",ROUND($P79/2,2)+$S79) -> 585.2 | V79: 1086.8 | W79: CC | X79: 46158 | AE79: =IF($L79="","",SUM($V79,$Y79,$AB79)) -> 1086.8 | AF79: =IF(OR($L79="",$T79=0),"",IF(OR($J79="Complete",$J79="Paid in Full"),1,$AE79/$T79)) -> 1 | AG79: =IF($L79="","",IF(OR($J79="Cancelled",$J79="Complete",$J79="Paid in Full"),0,ROUND($T79-$AE79,2))) -> 0 | AH79: =IF(OR($L79="",$H79="",$AG79<=0),"",MAX(0,TODAY()-($H79+Settings!$J$6))) | AI79: 83.6 | AO79: =IF(OR($L79="",$S79=0,$AI79=""),0,ROUND($S79-$AI79,2)) -> 0 | AP79: =IF($L79="","",ROUND($L79+$AO79,2)) -> 836 | AR79: =IF($L79="","",IF(ISNUMBER($F79),$F79,IF(ISNUMBER($G79),$G79,""))) -> 45798 | AS79: =IF(OR($L79="",$AR79=""),"",DATE(YEAR($AR79),MONTH($AR79),1)) -> 45778 | AT79: =IF($L79="","",IF($AR79<>"",YEAR($AR79),IF(ISNUMBER($H79),YEAR($H79),""))) -> 2025
A80: Danelle | B80: Penni Black | C80: C | D80: 22004275 | E80: Mewburn Ellis | F80: 46211 | H80: 46160 | I80: R | J80: Complete | K80: 30 | L80: 2081.8 | M80: =IF(OR($K80="",$L80=""),"",$L80/$K80) -> 69.393333 | N80: 0.2 | O80: =IF($L80="","",$L80*IF($N80="",Settings!$J$11,$N80)) -> 416.36 | P80: =IF($L80="","",$L80+$O80) -> 2498.16 | Q80: Yes | S80: =IF($L80="","",IF($Q80<>"Yes",0,IF($R80<>"",$R80,ROUND($L80*Settings!$J$4,2)))) -> 208.18 | T80: =IF($L80="","",$P80+$S80) -> 2706.34 | U80: =IF($L80="","",ROUND($P80/2,2)+$S80) -> 1457.26 | V80: 2590.25 | W80: CC | X80: 46205 | AE80: =IF($L80="","",SUM($V80,$Y80,$AB80)) -> 2590.25 | AF80: =IF(OR($L80="",$T80=0),"",IF(OR($J80="Complete",$J80="Paid in Full"),1,$AE80/$T80)) -> 1 | AG80: =IF($L80="","",IF(OR($J80="Cancelled",$J80="Complete",$J80="Paid in Full"),0,ROUND($T80-$AE80,2))) -> 0 | AH80: =IF(OR($L80="",$H80="",$AG80<=0),"",MAX(0,TODAY()-($H80+Settings!$J$6))) | AI80: 208.18 | AM80: CC | AN80: 46219 | AO80: =IF(OR($L80="",$S80=0,$AI80=""),0,ROUND($S80-$AI80,2)) -> 0 | AP80: =IF($L80="","",ROUND($L80+$AO80,2)) -> 2081.8 | AR80: =IF($L80="","",IF(ISNUMBER($F80),$F80,IF(ISNUMBER($G80),$G80,""))) -> 46211 | AS80: =IF(OR($L80="",$AR80=""),"",DATE(YEAR($AR80),MONTH($AR80),1)) -> 46204 | AT80: =IF($L80="","",IF($AR80<>"",YEAR($AR80),IF(ISNUMBER($H80),YEAR($H80),""))) -> 2026
A81: Danelle | B81: Penni Black | C81: P | D81: 22004276 | E81: David & Nigel | F81: 46221 | H81: 46160 | I81: R | J81: Complete | K81: 18 | L81: 5112.3 | M81: =IF(OR($K81="",$L81=""),"",$L81/$K81) -> 284.01667 | N81: 0.2 | O81: =IF($L81="","",$L81*IF($N81="",Settings!$J$11,$N81)) -> 1022.46 | P81: =IF($L81="","",$L81+$O81) -> 6134.76 | Q81: Yes | S81: =IF($L81="","",IF($Q81<>"Yes",0,IF($R81<>"",$R81,ROUND($L81*Settings!$J$4,2)))) -> 511.23 | T81: =IF($L81="","",$P81+$S81) -> 6645.99 | U81: =IF($L81="","",ROUND($P81/2,2)+$S81) -> 3578.61 | V81: 2416.16 | W81: CC | X81: 46163 | Y81: 4299.83 | Z81: CC | AA81: 46212 | AE81: =IF($L81="","",SUM($V81,$Y81,$AB81)) -> 6715.99 | AF81: =IF(OR($L81="",$T81=0),"",IF(OR($J81="Complete",$J81="Paid in Full"),1,$AE81/$T81)) -> 1 | AG81: =IF($L81="","",IF(OR($J81="Cancelled",$J81="Complete",$J81="Paid in Full"),0,ROUND($T81-$AE81,2))) -> 0 | AH81: =IF(OR($L81="",$H81="",$AG81<=0),"",MAX(0,TODAY()-($H81+Settings!$J$6))) | AI81: 511.23 | AM81: CC | AN81: 46225 | AO81: =IF(OR($L81="",$S81=0,$AI81=""),0,ROUND($S81-$AI81,2)) -> 0 | AP81: =IF($L81="","",ROUND($L81+$AO81,2)) -> 5112.3 | AR81: =IF($L81="","",IF(ISNUMBER($F81),$F81,IF(ISNUMBER($G81),$G81,""))) -> 46221 | AS81: =IF(OR($L81="",$AR81=""),"",DATE(YEAR($AR81),MONTH($AR81),1)) -> 46204 | AT81: =IF($L81="","",IF($AR81<>"",YEAR($AR81),IF(ISNUMBER($H81),YEAR($H81),""))) -> 2026
A82: Danelle | B82: Penni Black | C82: C | D82: 22004277 | E82: Helaba Landesbank Hessen-Thüringen | F82: 46191 | H82: 46162 | I82: R | J82: Complete | K82: 80 | L82: 4987 | M82: =IF(OR($K82="",$L82=""),"",$L82/$K82) -> 62.3375 | N82: 0.2 | O82: =IF($L82="","",$L82*IF($N82="",Settings!$J$11,$N82)) -> 997.4 | P82: =IF($L82="","",$L82+$O82) -> 5984.4 | Q82: Yes | S82: =IF($L82="","",IF($Q82<>"Yes",0,IF($R82<>"",$R82,ROUND($L82*Settings!$J$4,2)))) -> 498.7 | T82: =IF($L82="","",$P82+$S82) -> 6483.1 | U82: =IF($L82="","",ROUND($P82/2,2)+$S82) -> 3490.9 | V82: 5984.4 | W82: BACS | X82: 46185 | Y82: 150 | Z82: CC | AA82: 46181 | AE82: =IF($L82="","",SUM($V82,$Y82,$AB82)) -> 6134.4 | AF82: =IF(OR($L82="",$T82=0),"",IF(OR($J82="Complete",$J82="Paid in Full"),1,$AE82/$T82)) -> 1 | AG82: =IF($L82="","",IF(OR($J82="Cancelled",$J82="Complete",$J82="Paid in Full"),0,ROUND($T82-$AE82,2))) -> 0 | AH82: =IF(OR($L82="",$H82="",$AG82<=0),"",MAX(0,TODAY()-($H82+Settings!$J$6))) | AI82: 498.7 | AM82: CC | AN82: 46198 | AO82: =IF(OR($L82="",$S82=0,$AI82=""),0,ROUND($S82-$AI82,2)) -> 0 | AP82: =IF($L82="","",ROUND($L82+$AO82,2)) -> 4987 | AR82: =IF($L82="","",IF(ISNUMBER($F82),$F82,IF(ISNUMBER($G82),$G82,""))) -> 46191 | AS82: =IF(OR($L82="",$AR82=""),"",DATE(YEAR($AR82),MONTH($AR82),1)) -> 46174 | AT82: =IF($L82="","",IF($AR82<>"",YEAR($AR82),IF(ISNUMBER($H82),YEAR($H82),""))) -> 2026
A83: Danelle | B83: Penni Black | C83: C | D83: 22004278 | E83: WSGR | F83: 46205 | H83: 46162 | I83: R | J83: Complete | K83: 275 | L83: 33957.2 | M83: =IF(OR($K83="",$L83=""),"",$L83/$K83) -> 123.48073 | N83: 0.2 | O83: =IF($L83="","",$L83*IF($N83="",Settings!$J$11,$N83)) -> 6791.44 | P83: =IF($L83="","",$L83+$O83) -> 40748.64 | Q83: Yes | S83: =IF($L83="","",IF($Q83<>"Yes",0,IF($R83<>"",$R83,ROUND($L83*Settings!$J$4,2)))) -> 3395.72 | T83: =IF($L83="","",$P83+$S83) -> 44144.36 | U83: =IF($L83="","",ROUND($P83/2,2)+$S83) -> 23770.04 | V83: 20374.32 | W83: CC | X83: 46176 | Y83: 26363.93 | Z83: CC | AA83: 46203 | AE83: =IF($L83="","",SUM($V83,$Y83,$AB83)) -> 46738.25 | AF83: =IF(OR($L83="",$T83=0),"",IF(OR($J83="Complete",$J83="Paid in Full"),1,$AE83/$T83)) -> 1 | AG83: =IF($L83="","",IF(OR($J83="Cancelled",$J83="Complete",$J83="Paid in Full"),0,ROUND($T83-$AE83,2))) -> 0 | AH83: =IF(OR($L83="",$H83="",$AG83<=0),"",MAX(0,TODAY()-($H83+Settings!$J$6))) | AI83: 3395.72 | AM83: CC | AN83: 46209 | AO83: =IF(OR($L83="",$S83=0,$AI83=""),0,ROUND($S83-$AI83,2)) -> 0 | AP83: =IF($L83="","",ROUND($L83+$AO83,2)) -> 33957.2 | AR83: =IF($L83="","",IF(ISNUMBER($F83),$F83,IF(ISNUMBER($G83),$G83,""))) -> 46205 | AS83: =IF(OR($L83="",$AR83=""),"",DATE(YEAR($AR83),MONTH($AR83),1)) -> 46204 | AT83: =IF($L83="","",IF($AR83<>"",YEAR($AR83),IF(ISNUMBER($H83),YEAR($H83),""))) -> 2026
A84: Danelle | B84: Penni Black | C84: C | D84: 22004279 | E84: TGB | F84: 46177 | I84: N | J84: Complete | K84: 50 | L84: 4773.5 | M84: =IF(OR($K84="",$L84=""),"",$L84/$K84) -> 95.47 | N84: 0.2 | O84: =IF($L84="","",$L84*IF($N84="",Settings!$J$11,$N84)) -> 954.7 | P84: =IF($L84="","",$L84+$O84) -> 5728.2 | Q84: Yes | S84: =IF($L84="","",IF($Q84<>"Yes",0,IF($R84<>"",$R84,ROUND($L84*Settings!$J$4,2)))) -> 477.35 | T84: =IF($L84="","",$P84+$S84) -> 6205.55 | U84: =IF($L84="","",ROUND($P84/2,2)+$S84) -> 3341.45 | V84: 6205.55 | W84: CC | X84: 46174 | AE84: =IF($L84="","",SUM($V84,$Y84,$AB84)) -> 6205.55 | AF84: =IF(OR($L84="",$T84=0),"",IF(OR($J84="Complete",$J84="Paid in Full"),1,$AE84/$T84)) -> 1 | AG84: =IF($L84="","",IF(OR($J84="Cancelled",$J84="Complete",$J84="Paid in Full"),0,ROUND($T84-$AE84,2))) -> 0 | AH84: =IF(OR($L84="",$H84="",$AG84<=0),"",MAX(0,TODAY()-($H84+Settings!$J$6))) | AI84: 477.35 | AM84: CC | AN84: 46198 | AO84: =IF(OR($L84="",$S84=0,$AI84=""),0,ROUND($S84-$AI84,2)) -> 0 | AP84: =IF($L84="","",ROUND($L84+$AO84,2)) -> 4773.5 | AR84: =IF($L84="","",IF(ISNUMBER($F84),$F84,IF(ISNUMBER($G84),$G84,""))) -> 46177 | AS84: =IF(OR($L84="",$AR84=""),"",DATE(YEAR($AR84),MONTH($AR84),1)) -> 46174 | AT84: =IF($L84="","",IF($AR84<>"",YEAR($AR84),IF(ISNUMBER($H84),YEAR($H84),""))) -> 2026
A85: Danelle | B85: Penni Black | C85: C | D85: 22004280 | E85: MaryWard House | F85: 46182 | H85: 374889 | I85: N | J85: Complete | K85: 30 | L85: 805.5 | M85: =IF(OR($K85="",$L85=""),"",$L85/$K85) -> 26.85 | N85: 0.2 | O85: =IF($L85="","",$L85*IF($N85="",Settings!$J$11,$N85)) -> 161.1 | P85: =IF($L85="","",$L85+$O85) -> 966.6 | Q85: No | S85: =IF($L85="","",IF($Q85<>"Yes",0,IF($R85<>"",$R85,ROUND($L85*Settings!$J$4,2)))) -> 0 | T85: =IF($L85="","",$P85+$S85) -> 966.6 | U85: =IF($L85="","",ROUND($P85/2,2)+$S85) -> 483.3 | V85: 966.6 | W85: CC | X85: 46174 | AE85: =IF($L85="","",SUM($V85,$Y85,$AB85)) -> 966.6 | AF85: =IF(OR($L85="",$T85=0),"",IF(OR($J85="Complete",$J85="Paid in Full"),1,$AE85/$T85)) -> 1 | AG85: =IF($L85="","",IF(OR($J85="Cancelled",$J85="Complete",$J85="Paid in Full"),0,ROUND($T85-$AE85,2))) -> 0 | AH85: =IF(OR($L85="",$H85="",$AG85<=0),"",MAX(0,TODAY()-($H85+Settings!$J$6))) | AO85: =IF(OR($L85="",$S85=0,$AI85=""),0,ROUND($S85-$AI85,2)) -> 0 | AP85: =IF($L85="","",ROUND($L85+$AO85,2)) -> 805.5 | AR85: =IF($L85="","",IF(ISNUMBER($F85),$F85,IF(ISNUMBER($G85),$G85,""))) -> 46182 | AS85: =IF(OR($L85="",$AR85=""),"",DATE(YEAR($AR85),MONTH($AR85),1)) -> 46174 | AT85: =IF($L85="","",IF($AR85<>"",YEAR($AR85),IF(ISNUMBER($H85),YEAR($H85),""))) -> 2026
A86: Danelle | B86: Penni Black | C86: C | D86: 22004281 | E86: House of Decant - June | H86: 46174 | I86: R | J86: Complete | K86: 90 | L86: 1920.5 | M86: =IF(OR($K86="",$L86=""),"",$L86/$K86) -> 21.338889 | N86: 0.2 | O86: =IF($L86="","",$L86*IF($N86="",Settings!$J$11,$N86)) -> 384.1 | P86: =IF($L86="","",$L86+$O86) -> 2304.6 | Q86: No | S86: =IF($L86="","",IF($Q86<>"Yes",0,IF($R86<>"",$R86,ROUND($L86*Settings!$J$4,2)))) -> 0 | T86: =IF($L86="","",$P86+$S86) -> 2304.6 | U86: =IF($L86="","",ROUND($P86/2,2)+$S86) -> 1152.3 | V86: 2304.6 | W86: BACS | X86: 46234 | AE86: =IF($L86="","",SUM($V86,$Y86,$AB86)) -> 2304.6 | AF86: =IF(OR($L86="",$T86=0),"",IF(OR($J86="Complete",$J86="Paid in Full"),1,$AE86/$T86)) -> 1 | AG86: =IF($L86="","",IF(OR($J86="Cancelled",$J86="Complete",$J86="Paid in Full"),0,ROUND($T86-$AE86,2))) -> 0 | AH86: =IF(OR($L86="",$H86="",$AG86<=0),"",MAX(0,TODAY()-($H86+Settings!$J$6))) | AO86: =IF(OR($L86="",$S86=0,$AI86=""),0,ROUND($S86-$AI86,2)) -> 0 | AP86: =IF($L86="","",ROUND($L86+$AO86,2)) -> 1920.5 | AQ86: Event dates: June. | AR86: =IF($L86="","",IF(ISNUMBER($F86),$F86,IF(ISNUMBER($G86),$G86,""))) | AS86: =IF(OR($L86="",$AR86=""),"",DATE(YEAR($AR86),MONTH($AR86),1)) | AT86: =IF($L86="","",IF($AR86<>"",YEAR($AR86),IF(ISNUMBER($H86),YEAR($H86),""))) -> 2026
A87: Danelle | B87: Penni Black | C87: P | D87: 22004282 | E87: Peter Pearson | F87: 46184 | H87: 46175 | I87: N | J87: Complete | K87: 65 | L87: 3736.5 | M87: =IF(OR($K87="",$L87=""),"",$L87/$K87) -> 57.484615 | N87: 0.2 | O87: =IF($L87="","",$L87*IF($N87="",Settings!$J$11,$N87)) -> 747.3 | P87: =IF($L87="","",$L87+$O87) -> 4483.8 | Q87: Yes | S87: =IF($L87="","",IF($Q87<>"Yes",0,IF($R87<>"",$R87,ROUND($L87*Settings!$J$4,2)))) -> 373.65 | T87: =IF($L87="","",$P87+$S87) -> 4857.45 | U87: =IF($L87="","",ROUND($P87/2,2)+$S87) -> 2615.55 | V87: 4816.92 | W87: CC | X87: 46177 | AE87: =IF($L87="","",SUM($V87,$Y87,$AB87)) -> 4816.92 | AF87: =IF(OR($L87="",$T87=0),"",IF(OR($J87="Complete",$J87="Paid in Full"),1,$AE87/$T87)) -> 1 | AG87: =IF($L87="","",IF(OR($J87="Cancelled",$J87="Complete",$J87="Paid in Full"),0,ROUND($T87-$AE87,2))) -> 0 | AH87: =IF(OR($L87="",$H87="",$AG87<=0),"",MAX(0,TODAY()-($H87+Settings!$J$6))) | AI87: 373.65 | AM87: CC | AN87: 46198 | AO87: =IF(OR($L87="",$S87=0,$AI87=""),0,ROUND($S87-$AI87,2)) -> 0 | AP87: =IF($L87="","",ROUND($L87+$AO87,2)) -> 3736.5 | AR87: =IF($L87="","",IF(ISNUMBER($F87),$F87,IF(ISNUMBER($G87),$G87,""))) -> 46184 | AS87: =IF(OR($L87="",$AR87=""),"",DATE(YEAR($AR87),MONTH($AR87),1)) -> 46174 | AT87: =IF($L87="","",IF($AR87<>"",YEAR($AR87),IF(ISNUMBER($H87),YEAR($H87),""))) -> 2026
A88: Danelle | B88: Penni Black | C88: C | D88: 22004283 | E88: Pontoon | F88: 46191 | H88: 46177 | I88: N | J88: Complete | K88: 60 | M88: =IF(OR($K88="",$L88=""),"",$L88/$K88) | N88: 0.2 | O88: =IF($L88="","",$L88*IF($N88="",Settings!$J$11,$N88)) | P88: =IF($L88="","",$L88+$O88) | Q88: Yes | S88: =IF($L88="","",IF($Q88<>"Yes",0,IF($R88<>"",$R88,ROUND($L88*Settings!$J$4,2)))) | T88: =IF($L88="","",$P88+$S88) | U88: =IF($L88="","",ROUND($P88/2,2)+$S88) | V88: 6164.6 | W88: CC | X88: 46181 | AE88: =IF($L88="","",SUM($V88,$Y88,$AB88)) | AF88: =IF(OR($L88="",$T88=0),"",IF(OR($J88="Complete",$J88="Paid in Full"),1,$AE88/$T88)) | AG88: =IF($L88="","",IF(OR($J88="Cancelled",$J88="Complete",$J88="Paid in Full"),0,ROUND($T88-$AE88,2))) | AH88: =IF(OR($L88="",$H88="",$AG88<=0),"",MAX(0,TODAY()-($H88+Settings!$J$6))) | AM88: CC | AO88: =IF(OR($L88="",$S88=0,$AI88=""),0,ROUND($S88-$AI88,2)) -> 0 | AP88: =IF($L88="","",ROUND($L88+$AO88,2)) | AR88: =IF($L88="","",IF(ISNUMBER($F88),$F88,IF(ISNUMBER($G88),$G88,""))) | AS88: =IF(OR($L88="",$AR88=""),"",DATE(YEAR($AR88),MONTH($AR88),1)) | AT88: =IF($L88="","",IF($AR88<>"",YEAR($AR88),IF(ISNUMBER($H88),YEAR($H88),"")))
A89: Danelle | B89: Penni Black | C89: C | D89: 22004284 | E89: Small Business Britain | F89: 46189 | H89: 46178 | I89: N | J89: Complete | K89: 100 | L89: 7214.5 | M89: =IF(OR($K89="",$L89=""),"",$L89/$K89) -> 72.145 | N89: 0.2 | O89: =IF($L89="","",$L89*IF($N89="",Settings!$J$11,$N89)) -> 1442.9 | P89: =IF($L89="","",$L89+$O89) -> 8657.4 | Q89: Yes | S89: =IF($L89="","",IF($Q89<>"Yes",0,IF($R89<>"",$R89,ROUND($L89*Settings!$J$4,2)))) -> 721.45 | T89: =IF($L89="","",$P89+$S89) -> 9378.85 | U89: =IF($L89="","",ROUND($P89/2,2)+$S89) -> 5050.15 | V89: 6966.05 | W89: CC | X89: 46183 | Y89: 2120.03 | Z89: CC | AE89: =IF($L89="","",SUM($V89,$Y89,$AB89)) -> 9086.08 | AF89: =IF(OR($L89="",$T89=0),"",IF(OR($J89="Complete",$J89="Paid in Full"),1,$AE89/$T89)) -> 1 | AG89: =IF($L89="","",IF(OR($J89="Cancelled",$J89="Complete",$J89="Paid in Full"),0,ROUND($T89-$AE89,2))) -> 0 | AH89: =IF(OR($L89="",$H89="",$AG89<=0),"",MAX(0,TODAY()-($H89+Settings!$J$6))) | AI89: 721.45 | AM89: CC | AN89: 46198 | AO89: =IF(OR($L89="",$S89=0,$AI89=""),0,ROUND($S89-$AI89,2)) -> 0 | AP89: =IF($L89="","",ROUND($L89+$AO89,2)) -> 7214.5 | AR89: =IF($L89="","",IF(ISNUMBER($F89),$F89,IF(ISNUMBER($G89),$G89,""))) -> 46189 | AS89: =IF(OR($L89="",$AR89=""),"",DATE(YEAR($AR89),MONTH($AR89),1)) -> 46174 | AT89: =IF($L89="","",IF($AR89<>"",YEAR($AR89),IF(ISNUMBER($H89),YEAR($H89),""))) -> 2026
A90: Danelle | B90: Penni Black | C90: C | D90: 22004285 | E90: Trading Technology | F90: 46191 | H90: 46180 | I90: R | J90: Complete | K90: 80 | L90: 11415.1 | M90: =IF(OR($K90="",$L90=""),"",$L90/$K90) -> 142.68875 | N90: 0.2 | O90: =IF($L90="","",$L90*IF($N90="",Settings!$J$11,$N90)) -> 2283.02 | P90: =IF($L90="","",$L90+$O90) -> 13698.12 | Q90: Yes | S90: =IF($L90="","",IF($Q90<>"Yes",0,IF($R90<>"",$R90,ROUND($L90*Settings!$J$4,2)))) -> 1141.51 | T90: =IF($L90="","",$P90+$S90) -> 14839.63 | U90: =IF($L90="","",ROUND($P90/2,2)+$S90) -> 7990.57 | V90: 6000 | W90: CC | X90: 46181 | Y90: 8839.63 | Z90: CC | AA90: 46184 | AE90: =IF($L90="","",SUM($V90,$Y90,$AB90)) -> 14839.63 | AF90: =IF(OR($L90="",$T90=0),"",IF(OR($J90="Complete",$J90="Paid in Full"),1,$AE90/$T90)) -> 1 | AG90: =IF($L90="","",IF(OR($J90="Cancelled",$J90="Complete",$J90="Paid in Full"),0,ROUND($T90-$AE90,2))) -> 0 | AH90: =IF(OR($L90="",$H90="",$AG90<=0),"",MAX(0,TODAY()-($H90+Settings!$J$6))) | AI90: 1141.51 | AM90: CC | AN90: 46202 | AO90: =IF(OR($L90="",$S90=0,$AI90=""),0,ROUND($S90-$AI90,2)) -> 0 | AP90: =IF($L90="","",ROUND($L90+$AO90,2)) -> 11415.1 | AR90: =IF($L90="","",IF(ISNUMBER($F90),$F90,IF(ISNUMBER($G90),$G90,""))) -> 46191 | AS90: =IF(OR($L90="",$AR90=""),"",DATE(YEAR($AR90),MONTH($AR90),1)) -> 46174 | AT90: =IF($L90="","",IF($AR90<>"",YEAR($AR90),IF(ISNUMBER($H90),YEAR($H90),""))) -> 2026
A91: Danelle | B91: Penni Black | C91: C | D91: 22004286 | E91: Perenco Holdings | F91: 46192 | H91: 46182 | I91: R | J91: Complete | K91: 17 | L91: 723.6 | M91: =IF(OR($K91="",$L91=""),"",$L91/$K91) -> 42.564706 | N91: 0.2 | O91: =IF($L91="","",$L91*IF($N91="",Settings!$J$11,$N91)) -> 144.72 | P91: =IF($L91="","",$L91+$O91) -> 868.32 | Q91: No | S91: =IF($L91="","",IF($Q91<>"Yes",0,IF($R91<>"",$R91,ROUND($L91*Settings!$J$4,2)))) -> 0 | T91: =IF($L91="","",$P91+$S91) -> 868.32 | U91: =IF($L91="","",ROUND($P91/2,2)+$S91) -> 434.16 | AE91: =IF($L91="","",SUM($V91,$Y91,$AB91)) -> 0 | AF91: =IF(OR($L91="",$T91=0),"",IF(OR($J91="Complete",$J91="Paid in Full"),1,$AE91/$T91)) -> 1 | AG91: =IF($L91="","",IF(OR($J91="Cancelled",$J91="Complete",$J91="Paid in Full"),0,ROUND($T91-$AE91,2))) -> 0 | AH91: =IF(OR($L91="",$H91="",$AG91<=0),"",MAX(0,TODAY()-($H91+Settings!$J$6))) | AO91: =IF(OR($L91="",$S91=0,$AI91=""),0,ROUND($S91-$AI91,2)) -> 0 | AP91: =IF($L91="","",ROUND($L91+$AO91,2)) -> 723.6 | AR91: =IF($L91="","",IF(ISNUMBER($F91),$F91,IF(ISNUMBER($G91),$G91,""))) -> 46192 | AS91: =IF(OR($L91="",$AR91=""),"",DATE(YEAR($AR91),MONTH($AR91),1)) -> 46174 | AT91: =IF($L91="","",IF($AR91<>"",YEAR($AR91),IF(ISNUMBER($H91),YEAR($H91),""))) -> 2026
A92: Danelle | B92: Penni Black | C92: C | D92: 22004287 | E92: Perenco Holdings | F92: 46191 | H92: 46182 | I92: R | J92: Complete | K92: 20 | L92: 745.7 | M92: =IF(OR($K92="",$L92=""),"",$L92/$K92) -> 37.285 | N92: 0.2 | O92: =IF($L92="","",$L92*IF($N92="",Settings!$J$11,$N92)) -> 149.14 | P92: =IF($L92="","",$L92+$O92) -> 894.84 | Q92: No | S92: =IF($L92="","",IF($Q92<>"Yes",0,IF($R92<>"",$R92,ROUND($L92*Settings!$J$4,2)))) -> 0 | T92: =IF($L92="","",$P92+$S92) -> 894.84 | U92: =IF($L92="","",ROUND($P92/2,2)+$S92) -> 447.42 | X92: 46188 | AE92: =IF($L92="","",SUM($V92,$Y92,$AB92)) -> 0 | AF92: =IF(OR($L92="",$T92=0),"",IF(OR($J92="Complete",$J92="Paid in Full"),1,$AE92/$T92)) -> 1 | AG92: =IF($L92="","",IF(OR($J92="Cancelled",$J92="Complete",$J92="Paid in Full"),0,ROUND($T92-$AE92,2))) -> 0 | AH92: =IF(OR($L92="",$H92="",$AG92<=0),"",MAX(0,TODAY()-($H92+Settings!$J$6))) | AO92: =IF(OR($L92="",$S92=0,$AI92=""),0,ROUND($S92-$AI92,2)) -> 0 | AP92: =IF($L92="","",ROUND($L92+$AO92,2)) -> 745.7 | AR92: =IF($L92="","",IF(ISNUMBER($F92),$F92,IF(ISNUMBER($G92),$G92,""))) -> 46191 | AS92: =IF(OR($L92="",$AR92=""),"",DATE(YEAR($AR92),MONTH($AR92),1)) -> 46174 | AT92: =IF($L92="","",IF($AR92<>"",YEAR($AR92),IF(ISNUMBER($H92),YEAR($H92),""))) -> 2026
A93: Danelle | B93: Penni Black | C93: C | D93: 22004288 | E93: High Commission of Canada | F93: 46196 | H93: 46184 | I93: R | J93: Complete | K93: 75 | L93: 3329.3 | M93: =IF(OR($K93="",$L93=""),"",$L93/$K93) -> 44.390667 | N93: 0.2 | O93: =IF($L93="","",$L93*IF($N93="",Settings!$J$11,$N93)) -> 665.86 | P93: =IF($L93="","",$L93+$O93) -> 3995.16 | Q93: Yes | S93: =IF($L93="","",IF($Q93<>"Yes",0,IF($R93<>"",$R93,ROUND($L93*Settings!$J$4,2)))) -> 332.93 | T93: =IF($L93="","",$P93+$S93) -> 4328.09 | U93: =IF($L93="","",ROUND($P93/2,2)+$S93) -> 2330.51 | V93: 4328.09 | W93: CC | AE93: =IF($L93="","",SUM($V93,$Y93,$AB93)) -> 4328.09 | AF93: =IF(OR($L93="",$T93=0),"",IF(OR($J93="Complete",$J93="Paid in Full"),1,$AE93/$T93)) -> 1 | AG93: =IF($L93="","",IF(OR($J93="Cancelled",$J93="Complete",$J93="Paid in Full"),0,ROUND($T93-$AE93,2))) -> 0 | AH93: =IF(OR($L93="",$H93="",$AG93<=0),"",MAX(0,TODAY()-($H93+Settings!$J$6))) | AI93: 332.93 | AM93: CC | AN93: 46198 | AO93: =IF(OR($L93="",$S93=0,$AI93=""),0,ROUND($S93-$AI93,2)) -> 0 | AP93: =IF($L93="","",ROUND($L93+$AO93,2)) -> 3329.3 | AR93: =IF($L93="","",IF(ISNUMBER($F93),$F93,IF(ISNUMBER($G93),$G93,""))) -> 46196 | AS93: =IF(OR($L93="",$AR93=""),"",DATE(YEAR($AR93),MONTH($AR93),1)) -> 46174 | AT93: =IF($L93="","",IF($AR93<>"",YEAR($AR93),IF(ISNUMBER($H93),YEAR($H93),""))) -> 2026
A94: Danelle | B94: Penni Black | C94: C | D94: 22004289 | E94: House of Decant | H94: 46064 | I94: R | J94: Complete | K94: 95 | L94: 1508.5 | M94: =IF(OR($K94="",$L94=""),"",$L94/$K94) -> 15.878947 | N94: 0.2 | O94: =IF($L94="","",$L94*IF($N94="",Settings!$J$11,$N94)) -> 301.7 | P94: =IF($L94="","",$L94+$O94) -> 1810.2 | Q94: No | S94: =IF($L94="","",IF($Q94<>"Yes",0,IF($R94<>"",$R94,ROUND($L94*Settings!$J$4,2)))) -> 0 | T94: =IF($L94="","",$P94+$S94) -> 1810.2 | U94: =IF($L94="","",ROUND($P94/2,2)+$S94) -> 905.1 | V94: 1810.2 | W94: BACS | X94: 46192 | AE94: =IF($L94="","",SUM($V94,$Y94,$AB94)) -> 1810.2 | AF94: =IF(OR($L94="",$T94=0),"",IF(OR($J94="Complete",$J94="Paid in Full"),1,$AE94/$T94)) -> 1 | AG94: =IF($L94="","",IF(OR($J94="Cancelled",$J94="Complete",$J94="Paid in Full"),0,ROUND($T94-$AE94,2))) -> 0 | AH94: =IF(OR($L94="",$H94="",$AG94<=0),"",MAX(0,TODAY()-($H94+Settings!$J$6))) | AO94: =IF(OR($L94="",$S94=0,$AI94=""),0,ROUND($S94-$AI94,2)) -> 0 | AP94: =IF($L94="","",ROUND($L94+$AO94,2)) -> 1508.5 | AQ94: Event dates: 17 & 18 June. | AR94: =IF($L94="","",IF(ISNUMBER($F94),$F94,IF(ISNUMBER($G94),$G94,""))) | AS94: =IF(OR($L94="",$AR94=""),"",DATE(YEAR($AR94),MONTH($AR94),1)) | AT94: =IF($L94="","",IF($AR94<>"",YEAR($AR94),IF(ISNUMBER($H94),YEAR($H94),""))) -> 2026
A95: Danelle | B95: Penni Black | C95: C | D95: 22004290 | E95: Chew Events - Generator, Barista | F95: 46191 | H95: 46188 | I95: R | J95: Complete | K95: 1 | L95: 11272 | M95: =IF(OR($K95="",$L95=""),"",$L95/$K95) -> 11272 | N95: 0.2 | O95: =IF($L95="","",$L95*IF($N95="",Settings!$J$11,$N95)) -> 2254.4 | P95: =IF($L95="","",$L95+$O95) -> 13526.4 | Q95: No | S95: =IF($L95="","",IF($Q95<>"Yes",0,IF($R95<>"",$R95,ROUND($L95*Settings!$J$4,2)))) -> 0 | T95: =IF($L95="","",$P95+$S95) -> 13526.4 | U95: =IF($L95="","",ROUND($P95/2,2)+$S95) -> 6763.2 | V95: 13562.4 | W95: CC | X95: 46188 | AE95: =IF($L95="","",SUM($V95,$Y95,$AB95)) -> 13562.4 | AF95: =IF(OR($L95="",$T95=0),"",IF(OR($J95="Complete",$J95="Paid in Full"),1,$AE95/$T95)) -> 1 | AG95: =IF($L95="","",IF(OR($J95="Cancelled",$J95="Complete",$J95="Paid in Full"),0,ROUND($T95-$AE95,2))) -> 0 | AH95: =IF(OR($L95="",$H95="",$AG95<=0),"",MAX(0,TODAY()-($H95+Settings!$J$6))) | AO95: =IF(OR($L95="",$S95=0,$AI95=""),0,ROUND($S95-$AI95,2)) -> 0 | AP95: =IF($L95="","",ROUND($L95+$AO95,2)) -> 11272 | AR95: =IF($L95="","",IF(ISNUMBER($F95),$F95,IF(ISNUMBER($G95),$G95,""))) -> 46191 | AS95: =IF(OR($L95="",$AR95=""),"",DATE(YEAR($AR95),MONTH($AR95),1)) -> 46174 | AT95: =IF($L95="","",IF($AR95<>"",YEAR($AR95),IF(ISNUMBER($H95),YEAR($H95),""))) -> 2026
A96: Danelle | B96: Penni Black | C96: C | D96: 22004291 | E96: Chew Events - Additional guests | F96: 46191 | H96: 46188 | I96: R | J96: Complete | K96: 20 | L96: 2788 | M96: =IF(OR($K96="",$L96=""),"",$L96/$K96) -> 139.4 | N96: 0.2 | O96: =IF($L96="","",$L96*IF($N96="",Settings!$J$11,$N96)) -> 557.6 | P96: =IF($L96="","",$L96+$O96) -> 3345.6 | Q96: No | S96: =IF($L96="","",IF($Q96<>"Yes",0,IF($R96<>"",$R96,ROUND($L96*Settings!$J$4,2)))) -> 0 | T96: =IF($L96="","",$P96+$S96) -> 3345.6 | U96: =IF($L96="","",ROUND($P96/2,2)+$S96) -> 1672.8 | V96: 3345.6 | W96: CC | X96: 46188 | AE96: =IF($L96="","",SUM($V96,$Y96,$AB96)) -> 3345.6 | AF96: =IF(OR($L96="",$T96=0),"",IF(OR($J96="Complete",$J96="Paid in Full"),1,$AE96/$T96)) -> 1 | AG96: =IF($L96="","",IF(OR($J96="Cancelled",$J96="Complete",$J96="Paid in Full"),0,ROUND($T96-$AE96,2))) -> 0 | AH96: =IF(OR($L96="",$H96="",$AG96<=0),"",MAX(0,TODAY()-($H96+Settings!$J$6))) | AO96: =IF(OR($L96="",$S96=0,$AI96=""),0,ROUND($S96-$AI96,2)) -> 0 | AP96: =IF($L96="","",ROUND($L96+$AO96,2)) -> 2788 | AR96: =IF($L96="","",IF(ISNUMBER($F96),$F96,IF(ISNUMBER($G96),$G96,""))) -> 46191 | AS96: =IF(OR($L96="",$AR96=""),"",DATE(YEAR($AR96),MONTH($AR96),1)) -> 46174 | AT96: =IF($L96="","",IF($AR96<>"",YEAR($AR96),IF(ISNUMBER($H96),YEAR($H96),""))) -> 2026
A97: Danelle | B97: Penni Black | C97: C | D97: 22004292 | E97: Zenith Bank | F97: 46212 | H97: 46188 | I97: R | J97: Complete | K97: 20 | L97: 2294.5 | M97: =IF(OR($K97="",$L97=""),"",$L97/$K97) -> 114.725 | N97: 0.2 | O97: =IF($L97="","",$L97*IF($N97="",Settings!$J$11,$N97)) -> 458.9 | P97: =IF($L97="","",$L97+$O97) -> 2753.4 | Q97: Yes | S97: =IF($L97="","",IF($Q97<>"Yes",0,IF($R97<>"",$R97,ROUND($L97*Settings!$J$4,2)))) -> 229.45 | T97: =IF($L97="","",$P97+$S97) -> 2982.85 | U97: =IF($L97="","",ROUND($P97/2,2)+$S97) -> 1606.15 | V97: 2753.4 | W97: BACS | X97: 46185 | AE97: =IF($L97="","",SUM($V97,$Y97,$AB97)) -> 2753.4 | AF97: =IF(OR($L97="",$T97=0),"",IF(OR($J97="Complete",$J97="Paid in Full"),1,$AE97/$T97)) -> 1 | AG97: =IF($L97="","",IF(OR($J97="Cancelled",$J97="Complete",$J97="Paid in Full"),0,ROUND($T97-$AE97,2))) -> 0 | AH97: =IF(OR($L97="",$H97="",$AG97<=0),"",MAX(0,TODAY()-($H97+Settings!$J$6))) | AI97: 229.45 | AJ97: Zenith Bank UK Ltd | AK97: 40-02-50 | AL97: 81253972 | AM97: BACS | AN97: 46180 | AO97: =IF(OR($L97="",$S97=0,$AI97=""),0,ROUND($S97-$AI97,2)) -> 0 | AP97: =IF($L97="","",ROUND($L97+$AO97,2)) -> 2294.5 | AR97: =IF($L97="","",IF(ISNUMBER($F97),$F97,IF(ISNUMBER($G97),$G97,""))) -> 46212 | AS97: =IF(OR($L97="",$AR97=""),"",DATE(YEAR($AR97),MONTH($AR97),1)) -> 46204 | AT97: =IF($L97="","",IF($AR97<>"",YEAR($AR97),IF(ISNUMBER($H97),YEAR($H97),""))) -> 2026
A98: Danelle | B98: Penni Black | C98: C | D98: 22004293 | E98: Zenith Bank | F98: 46213 | H98: 46188 | I98: R | J98: Complete | K98: 10 | L98: 1583.1 | M98: =IF(OR($K98="",$L98=""),"",$L98/$K98) -> 158.31 | N98: 0.2 | O98: =IF($L98="","",$L98*IF($N98="",Settings!$J$11,$N98)) -> 316.62 | P98: =IF($L98="","",$L98+$O98) -> 1899.72 | Q98: Yes | S98: =IF($L98="","",IF($Q98<>"Yes",0,IF($R98<>"",$R98,ROUND($L98*Settings!$J$4,2)))) -> 158.31 | T98: =IF($L98="","",$P98+$S98) -> 2058.03 | U98: =IF($L98="","",ROUND($P98/2,2)+$S98) -> 1108.17 | V98: 1899.72 | W98: BACS | X98: 46185 | AE98: =IF($L98="","",SUM($V98,$Y98,$AB98)) -> 1899.72 | AF98: =IF(OR($L98="",$T98=0),"",IF(OR($J98="Complete",$J98="Paid in Full"),1,$AE98/$T98)) -> 1 | AG98: =IF($L98="","",IF(OR($J98="Cancelled",$J98="Complete",$J98="Paid in Full"),0,ROUND($T98-$AE98,2))) -> 0 | AH98: =IF(OR($L98="",$H98="",$AG98<=0),"",MAX(0,TODAY()-($H98+Settings!$J$6))) | AI98: 158.31 | AO98: =IF(OR($L98="",$S98=0,$AI98=""),0,ROUND($S98-$AI98,2)) -> 0 | AP98: =IF($L98="","",ROUND($L98+$AO98,2)) -> 1583.1 | AR98: =IF($L98="","",IF(ISNUMBER($F98),$F98,IF(ISNUMBER($G98),$G98,""))) -> 46213 | AS98: =IF(OR($L98="",$AR98=""),"",DATE(YEAR($AR98),MONTH($AR98),1)) -> 46204 | AT98: =IF($L98="","",IF($AR98<>"",YEAR($AR98),IF(ISNUMBER($H98),YEAR($H98),""))) -> 2026
A99: Danelle | B99: Penni Black | C99: C | D99: 22004294 | E99: Xero Day 1 | F99: 46217 | H99: 46188 | I99: R | J99: Complete | K99: 20 | L99: 1038 | M99: =IF(OR($K99="",$L99=""),"",$L99/$K99) -> 51.9 | N99: 0.2 | O99: =IF($L99="","",$L99*IF($N99="",Settings!$J$11,$N99)) -> 207.6 | P99: =IF($L99="","",$L99+$O99) -> 1245.6 | Q99: No | S99: =IF($L99="","",IF($Q99<>"Yes",0,IF($R99<>"",$R99,ROUND($L99*Settings!$J$4,2)))) -> 0 | T99: =IF($L99="","",$P99+$S99) -> 1245.6 | U99: =IF($L99="","",ROUND($P99/2,2)+$S99) -> 622.8 | V99: 1245.6 | W99: CC | X99: 46188 | AE99: =IF($L99="","",SUM($V99,$Y99,$AB99)) -> 1245.6 | AF99: =IF(OR($L99="",$T99=0),"",IF(OR($J99="Complete",$J99="Paid in Full"),1,$AE99/$T99)) -> 1 | AG99: =IF($L99="","",IF(OR($J99="Cancelled",$J99="Complete",$J99="Paid in Full"),0,ROUND($T99-$AE99,2))) -> 0 | AH99: =IF(OR($L99="",$H99="",$AG99<=0),"",MAX(0,TODAY()-($H99+Settings!$J$6))) | AO99: =IF(OR($L99="",$S99=0,$AI99=""),0,ROUND($S99-$AI99,2)) -> 0 | AP99: =IF($L99="","",ROUND($L99+$AO99,2)) -> 1038 | AR99: =IF($L99="","",IF(ISNUMBER($F99),$F99,IF(ISNUMBER($G99),$G99,""))) -> 46217 | AS99: =IF(OR($L99="",$AR99=""),"",DATE(YEAR($AR99),MONTH($AR99),1)) -> 46204 | AT99: =IF($L99="","",IF($AR99<>"",YEAR($AR99),IF(ISNUMBER($H99),YEAR($H99),""))) -> 2026
A100: Danelle | B100: Penni Black | C100: C | D100: 22004295 | E100: Xero Day 2 | F100: 46218 | H100: 46188 | I100: R | J100: Complete | K100: 20 | L100: 1048 | M100: =IF(OR($K100="",$L100=""),"",$L100/$K100) -> 52.4 | N100: 0.2 | O100: =IF($L100="","",$L100*IF($N100="",Settings!$J$11,$N100)) -> 209.6 | P100: =IF($L100="","",$L100+$O100) -> 1257.6 | Q100: No | S100: =IF($L100="","",IF($Q100<>"Yes",0,IF($R100<>"",$R100,ROUND($L100*Settings!$J$4,2)))) -> 0 | T100: =IF($L100="","",$P100+$S100) -> 1257.6 | U100: =IF($L100="","",ROUND($P100/2,2)+$S100) -> 628.8 | V100: 1257.6 | W100: CC | X100: 46188 | AE100: =IF($L100="","",SUM($V100,$Y100,$AB100)) -> 1257.6 | AF100: =IF(OR($L100="",$T100=0),"",IF(OR($J100="Complete",$J100="Paid in Full"),1,$AE100/$T100)) -> 1 | AG100: =IF($L100="","",IF(OR($J100="Cancelled",$J100="Complete",$J100="Paid in Full"),0,ROUND($T100-$AE100,2))) -> 0 | AH100: =IF(OR($L100="",$H100="",$AG100<=0),"",MAX(0,TODAY()-($H100+Settings!$J$6))) | AO100: =IF(OR($L100="",$S100=0,$AI100=""),0,ROUND($S100-$AI100,2)) -> 0 | AP100: =IF($L100="","",ROUND($L100+$AO100,2)) -> 1048 | AR100: =IF($L100="","",IF(ISNUMBER($F100),$F100,IF(ISNUMBER($G100),$G100,""))) -> 46218 | AS100: =IF(OR($L100="",$AR100=""),"",DATE(YEAR($AR100),MONTH($AR100),1)) -> 46204 | AT100: =IF($L100="","",IF($AR100<>"",YEAR($AR100),IF(ISNUMBER($H100),YEAR($H100),""))) -> 2026
...

Sheet Collective
A1: PENNI BLACK COLLECTIVE | E1: {=IFERROR("NEXT PAYMENT: "&TEXT(INDEX($J$7:$J$18,MATCH(1,$N$7:$N$18,0)),"£#,##0.00")&" for "&TEXT(INDEX($A$7:$A$18,MATCH(1,$N$7:$N$18,0)),"MMMM")&" - in by "&TEXT(INDEX($L$7:$L$18,MATCH(1,$N$7:$N$18,0)),"D MMMM"),"ALL PAID UP TO DATE")} -> NEXT PAYMENT: £17,576.25 for September - in by 25 October
A2: =Settings!$J$8*100&"% of turnover, month by month, by EVENT date, running from "&TEXT(Settings!$J$10,"D MMMM YYYY")&". Turnover is ex VAT and adjusted by whatever the deposit refund actually came to. Cancelled jobs are excluded." -> 20% of turnover, month by month, by EVENT date, running from 1 September 2026. Turnover is ex VAT and adjusted by whatever the deposit refund actually came to. Cancelled jobs are excluded. | E2: {=IFERROR(IF(TODAY()>INDEX($L$7:$L$18,MATCH(1,$N$7:$N$18,0)),"OVERDUE - this should already be with the Collective",INDEX($L$7:$L$18,MATCH(1,$N$7:$N$18,0))-TODAY()&" days to go"),"")} -> 23 days to go
A3: Counting everything up to and including: | B3: =TODAY() -> 46297 | C3: Nothing with a later event date is counted.
A5: MONTH BY MONTH
A6: Month | B6: Jobs | C6: Turnover (ex VAT) | D6: Deposit taken | E6: Refund actually paid | F6: Deposit +/- | G6: NET TURNOVER (ex VAT) | H6: 20% DUE TO COLLECTIVE | I6: Paid to collective | J6: Outstanding | K6: Refunds still to do | L6: Pay by | M6: Payment status | N6: owing
A7: =DATE(Settings!$J$7,1,1) -> 46023 | B7: =COUNTIFS('Invoice Log'!$AS$3:$AS$303,$A7,'Invoice Log'!$AR$3:$AR$303,"<="&$B$3,'Invoice Log'!$AR$3:$AR$303,">="&Settings!$J$10,'Invoice Log'!$J$3:$J$303,"<>Cancelled") -> 0 | C7: =SUMIFS('Invoice Log'!$L$3:$L$303,'Invoice Log'!$AS$3:$AS$303,$A7,'Invoice Log'!$AR$3:$AR$303,"<="&$B$3,'Invoice Log'!$AR$3:$AR$303,">="&Settings!$J$10,'Invoice Log'!$J$3:$J$303,"<>Cancelled") -> 0 | D7: =SUMIFS('Invoice Log'!$S$3:$S$303,'Invoice Log'!$AS$3:$AS$303,$A7,'Invoice Log'!$AR$3:$AR$303,"<="&$B$3,'Invoice Log'!$AR$3:$AR$303,">="&Settings!$J$10,'Invoice Log'!$J$3:$J$303,"<>Cancelled") -> 0 | E7: =SUMIFS('Invoice Log'!$AI$3:$AI$303,'Invoice Log'!$AS$3:$AS$303,$A7,'Invoice Log'!$AR$3:$AR$303,"<="&$B$3,'Invoice Log'!$AR$3:$AR$303,">="&Settings!$J$10,'Invoice Log'!$J$3:$J$303,"<>Cancelled") -> 0 | F7: =SUMIFS('Invoice Log'!$AO$3:$AO$303,'Invoice Log'!$AS$3:$AS$303,$A7,'Invoice Log'!$AR$3:$AR$303,"<="&$B$3,'Invoice Log'!$AR$3:$AR$303,">="&Settings!$J$10,'Invoice Log'!$J$3:$J$303,"<>Cancelled") -> 0 | G7: =SUMIFS('Invoice Log'!$AP$3:$AP$303,'Invoice Log'!$AS$3:$AS$303,$A7,'Invoice Log'!$AR$3:$AR$303,"<="&$B$3,'Invoice Log'!$AR$3:$AR$303,">="&Settings!$J$10,'Invoice Log'!$J$3:$J$303,"<>Cancelled") -> 0 | H7: =ROUND($G7*Settings!$J$8,2) -> 0 | J7: =IF($H7=0,0,ROUND($H7-N($I7),2)) -> 0 | K7: =COUNTIFS('Invoice Log'!$AS$3:$AS$303,$A7,'Invoice Log'!$AR$3:$AR$303,"<="&$B$3,'Invoice Log'!$AR$3:$AR$303,">="&Settings!$J$10,'Invoice Log'!$J$3:$J$303,"<>Cancelled",'Invoice Log'!$S$3:$S$303,">0",'Invoice Log'!$AN$3:$AN$303,"") -> 0 | L7: =DATE(Settings!$J$7,2,Settings!$J$9) -> 46078 | M7: =IF(EOMONTH($A7,0)<Settings!$J$10,"before the Collective",IF($H7=0,"",IF(N($I7)>=$H7,"PAID",IF(TODAY()>$L7,"OVERDUE","Due "&TEXT($L7,"D MMM"))))) -> before the Collective | N7: =IF(AND($H7>0,N($I7)<$H7),1,0) -> 0
A8: =DATE(Settings!$J$7,2,1) -> 46054 | B8: =COUNTIFS('Invoice Log'!$AS$3:$AS$303,$A8,'Invoice Log'!$AR$3:$AR$303,"<="&$B$3,'Invoice Log'!$AR$3:$AR$303,">="&Settings!$J$10,'Invoice Log'!$J$3:$J$303,"<>Cancelled") -> 0 | C8: =SUMIFS('Invoice Log'!$L$3:$L$303,'Invoice Log'!$AS$3:$AS$303,$A8,'Invoice Log'!$AR$3:$AR$303,"<="&$B$3,'Invoice Log'!$AR$3:$AR$303,">="&Settings!$J$10,'Invoice Log'!$J$3:$J$303,"<>Cancelled") -> 0 | D8: =SUMIFS('Invoice Log'!$S$3:$S$303,'Invoice Log'!$AS$3:$AS$303,$A8,'Invoice Log'!$AR$3:$AR$303,"<="&$B$3,'Invoice Log'!$AR$3:$AR$303,">="&Settings!$J$10,'Invoice Log'!$J$3:$J$303,"<>Cancelled") -> 0 | E8: =SUMIFS('Invoice Log'!$AI$3:$AI$303,'Invoice Log'!$AS$3:$AS$303,$A8,'Invoice Log'!$AR$3:$AR$303,"<="&$B$3,'Invoice Log'!$AR$3:$AR$303,">="&Settings!$J$10,'Invoice Log'!$J$3:$J$303,"<>Cancelled") -> 0 | F8: =SUMIFS('Invoice Log'!$AO$3:$AO$303,'Invoice Log'!$AS$3:$AS$303,$A8,'Invoice Log'!$AR$3:$AR$303,"<="&$B$3,'Invoice Log'!$AR$3:$AR$303,">="&Settings!$J$10,'Invoice Log'!$J$3:$J$303,"<>Cancelled") -> 0 | G8: =SUMIFS('Invoice Log'!$AP$3:$AP$303,'Invoice Log'!$AS$3:$AS$303,$A8,'Invoice Log'!$AR$3:$AR$303,"<="&$B$3,'Invoice Log'!$AR$3:$AR$303,">="&Settings!$J$10,'Invoice Log'!$J$3:$J$303,"<>Cancelled") -> 0 | H8: =ROUND($G8*Settings!$J$8,2) -> 0 | J8: =IF($H8=0,0,ROUND($H8-N($I8),2)) -> 0 | K8: =COUNTIFS('Invoice Log'!$AS$3:$AS$303,$A8,'Invoice Log'!$AR$3:$AR$303,"<="&$B$3,'Invoice Log'!$AR$3:$AR$303,">="&Settings!$J$10,'Invoice Log'!$J$3:$J$303,"<>Cancelled",'Invoice Log'!$S$3:$S$303,">0",'Invoice Log'!$AN$3:$AN$303,"") -> 0 | L8: =DATE(Settings!$J$7,3,Settings!$J$9) -> 46106 | M8: =IF(EOMONTH($A8,0)<Settings!$J$10,"before the Collective",IF($H8=0,"",IF(N($I8)>=$H8,"PAID",IF(TODAY()>$L8,"OVERDUE","Due "&TEXT($L8,"D MMM"))))) -> before the Collective | N8: =IF(AND($H8>0,N($I8)<$H8),1,0) -> 0
A9: =DATE(Settings!$J$7,3,1) -> 46082 | B9: =COUNTIFS('Invoice Log'!$AS$3:$AS$303,$A9,'Invoice Log'!$AR$3:$AR$303,"<="&$B$3,'Invoice Log'!$AR$3:$AR$303,">="&Settings!$J$10,'Invoice Log'!$J$3:$J$303,"<>Cancelled") -> 0 | C9: =SUMIFS('Invoice Log'!$L$3:$L$303,'Invoice Log'!$AS$3:$AS$303,$A9,'Invoice Log'!$AR$3:$AR$303,"<="&$B$3,'Invoice Log'!$AR$3:$AR$303,">="&Settings!$J$10,'Invoice Log'!$J$3:$J$303,"<>Cancelled") -> 0 | D9: =SUMIFS('Invoice Log'!$S$3:$S$303,'Invoice Log'!$AS$3:$AS$303,$A9,'Invoice Log'!$AR$3:$AR$303,"<="&$B$3,'Invoice Log'!$AR$3:$AR$303,">="&Settings!$J$10,'Invoice Log'!$J$3:$J$303,"<>Cancelled") -> 0 | E9: =SUMIFS('Invoice Log'!$AI$3:$AI$303,'Invoice Log'!$AS$3:$AS$303,$A9,'Invoice Log'!$AR$3:$AR$303,"<="&$B$3,'Invoice Log'!$AR$3:$AR$303,">="&Settings!$J$10,'Invoice Log'!$J$3:$J$303,"<>Cancelled") -> 0 | F9: =SUMIFS('Invoice Log'!$AO$3:$AO$303,'Invoice Log'!$AS$3:$AS$303,$A9,'Invoice Log'!$AR$3:$AR$303,"<="&$B$3,'Invoice Log'!$AR$3:$AR$303,">="&Settings!$J$10,'Invoice Log'!$J$3:$J$303,"<>Cancelled") -> 0 | G9: =SUMIFS('Invoice Log'!$AP$3:$AP$303,'Invoice Log'!$AS$3:$AS$303,$A9,'Invoice Log'!$AR$3:$AR$303,"<="&$B$3,'Invoice Log'!$AR$3:$AR$303,">="&Settings!$J$10,'Invoice Log'!$J$3:$J$303,"<>Cancelled") -> 0 | H9: =ROUND($G9*Settings!$J$8,2) -> 0 | J9: =IF($H9=0,0,ROUND($H9-N($I9),2)) -> 0 | K9: =COUNTIFS('Invoice Log'!$AS$3:$AS$303,$A9,'Invoice Log'!$AR$3:$AR$303,"<="&$B$3,'Invoice Log'!$AR$3:$AR$303,">="&Settings!$J$10,'Invoice Log'!$J$3:$J$303,"<>Cancelled",'Invoice Log'!$S$3:$S$303,">0",'Invoice Log'!$AN$3:$AN$303,"") -> 0 | L9: =DATE(Settings!$J$7,4,Settings!$J$9) -> 46137 | M9: =IF(EOMONTH($A9,0)<Settings!$J$10,"before the Collective",IF($H9=0,"",IF(N($I9)>=$H9,"PAID",IF(TODAY()>$L9,"OVERDUE","Due "&TEXT($L9,"D MMM"))))) -> before the Collective | N9: =IF(AND($H9>0,N($I9)<$H9),1,0) -> 0
A10: =DATE(Settings!$J$7,4,1) -> 46113 | B10: =COUNTIFS('Invoice Log'!$AS$3:$AS$303,$A10,'Invoice Log'!$AR$3:$AR$303,"<="&$B$3,'Invoice Log'!$AR$3:$AR$303,">="&Settings!$J$10,'Invoice Log'!$J$3:$J$303,"<>Cancelled") -> 0 | C10: =SUMIFS('Invoice Log'!$L$3:$L$303,'Invoice Log'!$AS$3:$AS$303,$A10,'Invoice Log'!$AR$3:$AR$303,"<="&$B$3,'Invoice Log'!$AR$3:$AR$303,">="&Settings!$J$10,'Invoice Log'!$J$3:$J$303,"<>Cancelled") -> 0 | D10: =SUMIFS('Invoice Log'!$S$3:$S$303,'Invoice Log'!$AS$3:$AS$303,$A10,'Invoice Log'!$AR$3:$AR$303,"<="&$B$3,'Invoice Log'!$AR$3:$AR$303,">="&Settings!$J$10,'Invoice Log'!$J$3:$J$303,"<>Cancelled") -> 0 | E10: =SUMIFS('Invoice Log'!$AI$3:$AI$303,'Invoice Log'!$AS$3:$AS$303,$A10,'Invoice Log'!$AR$3:$AR$303,"<="&$B$3,'Invoice Log'!$AR$3:$AR$303,">="&Settings!$J$10,'Invoice Log'!$J$3:$J$303,"<>Cancelled") -> 0 | F10: =SUMIFS('Invoice Log'!$AO$3:$AO$303,'Invoice Log'!$AS$3:$AS$303,$A10,'Invoice Log'!$AR$3:$AR$303,"<="&$B$3,'Invoice Log'!$AR$3:$AR$303,">="&Settings!$J$10,'Invoice Log'!$J$3:$J$303,"<>Cancelled") -> 0 | G10: =SUMIFS('Invoice Log'!$AP$3:$AP$303,'Invoice Log'!$AS$3:$AS$303,$A10,'Invoice Log'!$AR$3:$AR$303,"<="&$B$3,'Invoice Log'!$AR$3:$AR$303,">="&Settings!$J$10,'Invoice Log'!$J$3:$J$303,"<>Cancelled") -> 0 | H10: =ROUND($G10*Settings!$J$8,2) -> 0 | J10: =IF($H10=0,0,ROUND($H10-N($I10),2)) -> 0 | K10: =COUNTIFS('Invoice Log'!$AS$3:$AS$303,$A10,'Invoice Log'!$AR$3:$AR$303,"<="&$B$3,'Invoice Log'!$AR$3:$AR$303,">="&Settings!$J$10,'Invoice Log'!$J$3:$J$303,"<>Cancelled",'Invoice Log'!$S$3:$S$303,">0",'Invoice Log'!$AN$3:$AN$303,"") -> 0 | L10: =DATE(Settings!$J$7,5,Settings!$J$9) -> 46167 | M10: =IF(EOMONTH($A10,0)<Settings!$J$10,"before the Collective",IF($H10=0,"",IF(N($I10)>=$H10,"PAID",IF(TODAY()>$L10,"OVERDUE","Due "&TEXT($L10,"D MMM"))))) -> before the Collective | N10: =IF(AND($H10>0,N($I10)<$H10),1,0) -> 0
A11: =DATE(Settings!$J$7,5,1) -> 46143 | B11: =COUNTIFS('Invoice Log'!$AS$3:$AS$303,$A11,'Invoice Log'!$AR$3:$AR$303,"<="&$B$3,'Invoice Log'!$AR$3:$AR$303,">="&Settings!$J$10,'Invoice Log'!$J$3:$J$303,"<>Cancelled") -> 0 | C11: =SUMIFS('Invoice Log'!$L$3:$L$303,'Invoice Log'!$AS$3:$AS$303,$A11,'Invoice Log'!$AR$3:$AR$303,"<="&$B$3,'Invoice Log'!$AR$3:$AR$303,">="&Settings!$J$10,'Invoice Log'!$J$3:$J$303,"<>Cancelled") -> 0 | D11: =SUMIFS('Invoice Log'!$S$3:$S$303,'Invoice Log'!$AS$3:$AS$303,$A11,'Invoice Log'!$AR$3:$AR$303,"<="&$B$3,'Invoice Log'!$AR$3:$AR$303,">="&Settings!$J$10,'Invoice Log'!$J$3:$J$303,"<>Cancelled") -> 0 | E11: =SUMIFS('Invoice Log'!$AI$3:$AI$303,'Invoice Log'!$AS$3:$AS$303,$A11,'Invoice Log'!$AR$3:$AR$303,"<="&$B$3,'Invoice Log'!$AR$3:$AR$303,">="&Settings!$J$10,'Invoice Log'!$J$3:$J$303,"<>Cancelled") -> 0 | F11: =SUMIFS('Invoice Log'!$AO$3:$AO$303,'Invoice Log'!$AS$3:$AS$303,$A11,'Invoice Log'!$AR$3:$AR$303,"<="&$B$3,'Invoice Log'!$AR$3:$AR$303,">="&Settings!$J$10,'Invoice Log'!$J$3:$J$303,"<>Cancelled") -> 0 | G11: =SUMIFS('Invoice Log'!$AP$3:$AP$303,'Invoice Log'!$AS$3:$AS$303,$A11,'Invoice Log'!$AR$3:$AR$303,"<="&$B$3,'Invoice Log'!$AR$3:$AR$303,">="&Settings!$J$10,'Invoice Log'!$J$3:$J$303,"<>Cancelled") -> 0 | H11: =ROUND($G11*Settings!$J$8,2) -> 0 | J11: =IF($H11=0,0,ROUND($H11-N($I11),2)) -> 0 | K11: =COUNTIFS('Invoice Log'!$AS$3:$AS$303,$A11,'Invoice Log'!$AR$3:$AR$303,"<="&$B$3,'Invoice Log'!$AR$3:$AR$303,">="&Settings!$J$10,'Invoice Log'!$J$3:$J$303,"<>Cancelled",'Invoice Log'!$S$3:$S$303,">0",'Invoice Log'!$AN$3:$AN$303,"") -> 0 | L11: =DATE(Settings!$J$7,6,Settings!$J$9) -> 46198 | M11: =IF(EOMONTH($A11,0)<Settings!$J$10,"before the Collective",IF($H11=0,"",IF(N($I11)>=$H11,"PAID",IF(TODAY()>$L11,"OVERDUE","Due "&TEXT($L11,"D MMM"))))) -> before the Collective | N11: =IF(AND($H11>0,N($I11)<$H11),1,0) -> 0
A12: =DATE(Settings!$J$7,6,1) -> 46174 | B12: =COUNTIFS('Invoice Log'!$AS$3:$AS$303,$A12,'Invoice Log'!$AR$3:$AR$303,"<="&$B$3,'Invoice Log'!$AR$3:$AR$303,">="&Settings!$J$10,'Invoice Log'!$J$3:$J$303,"<>Cancelled") -> 0 | C12: =SUMIFS('Invoice Log'!$L$3:$L$303,'Invoice Log'!$AS$3:$AS$303,$A12,'Invoice Log'!$AR$3:$AR$303,"<="&$B$3,'Invoice Log'!$AR$3:$AR$303,">="&Settings!$J$10,'Invoice Log'!$J$3:$J$303,"<>Cancelled") -> 0 | D12: =SUMIFS('Invoice Log'!$S$3:$S$303,'Invoice Log'!$AS$3:$AS$303,$A12,'Invoice Log'!$AR$3:$AR$303,"<="&$B$3,'Invoice Log'!$AR$3:$AR$303,">="&Settings!$J$10,'Invoice Log'!$J$3:$J$303,"<>Cancelled") -> 0 | E12: =SUMIFS('Invoice Log'!$AI$3:$AI$303,'Invoice Log'!$AS$3:$AS$303,$A12,'Invoice Log'!$AR$3:$AR$303,"<="&$B$3,'Invoice Log'!$AR$3:$AR$303,">="&Settings!$J$10,'Invoice Log'!$J$3:$J$303,"<>Cancelled") -> 0 | F12: =SUMIFS('Invoice Log'!$AO$3:$AO$303,'Invoice Log'!$AS$3:$AS$303,$A12,'Invoice Log'!$AR$3:$AR$303,"<="&$B$3,'Invoice Log'!$AR$3:$AR$303,">="&Settings!$J$10,'Invoice Log'!$J$3:$J$303,"<>Cancelled") -> 0 | G12: =SUMIFS('Invoice Log'!$AP$3:$AP$303,'Invoice Log'!$AS$3:$AS$303,$A12,'Invoice Log'!$AR$3:$AR$303,"<="&$B$3,'Invoice Log'!$AR$3:$AR$303,">="&Settings!$J$10,'Invoice Log'!$J$3:$J$303,"<>Cancelled") -> 0 | H12: =ROUND($G12*Settings!$J$8,2) -> 0 | J12: =IF($H12=0,0,ROUND($H12-N($I12),2)) -> 0 | K12: =COUNTIFS('Invoice Log'!$AS$3:$AS$303,$A12,'Invoice Log'!$AR$3:$AR$303,"<="&$B$3,'Invoice Log'!$AR$3:$AR$303,">="&Settings!$J$10,'Invoice Log'!$J$3:$J$303,"<>Cancelled",'Invoice Log'!$S$3:$S$303,">0",'Invoice Log'!$AN$3:$AN$303,"") -> 0 | L12: =DATE(Settings!$J$7,7,Settings!$J$9) -> 46228 | M12: =IF(EOMONTH($A12,0)<Settings!$J$10,"before the Collective",IF($H12=0,"",IF(N($I12)>=$H12,"PAID",IF(TODAY()>$L12,"OVERDUE","Due "&TEXT($L12,"D MMM"))))) -> before the Collective | N12: =IF(AND($H12>0,N($I12)<$H12),1,0) -> 0
A13: =DATE(Settings!$J$7,7,1) -> 46204 | B13: =COUNTIFS('Invoice Log'!$AS$3:$AS$303,$A13,'Invoice Log'!$AR$3:$AR$303,"<="&$B$3,'Invoice Log'!$AR$3:$AR$303,">="&Settings!$J$10,'Invoice Log'!$J$3:$J$303,"<>Cancelled") -> 0 | C13: =SUMIFS('Invoice Log'!$L$3:$L$303,'Invoice Log'!$AS$3:$AS$303,$A13,'Invoice Log'!$AR$3:$AR$303,"<="&$B$3,'Invoice Log'!$AR$3:$AR$303,">="&Settings!$J$10,'Invoice Log'!$J$3:$J$303,"<>Cancelled") -> 0 | D13: =SUMIFS('Invoice Log'!$S$3:$S$303,'Invoice Log'!$AS$3:$AS$303,$A13,'Invoice Log'!$AR$3:$AR$303,"<="&$B$3,'Invoice Log'!$AR$3:$AR$303,">="&Settings!$J$10,'Invoice Log'!$J$3:$J$303,"<>Cancelled") -> 0 | E13: =SUMIFS('Invoice Log'!$AI$3:$AI$303,'Invoice Log'!$AS$3:$AS$303,$A13,'Invoice Log'!$AR$3:$AR$303,"<="&$B$3,'Invoice Log'!$AR$3:$AR$303,">="&Settings!$J$10,'Invoice Log'!$J$3:$J$303,"<>Cancelled") -> 0 | F13: =SUMIFS('Invoice Log'!$AO$3:$AO$303,'Invoice Log'!$AS$3:$AS$303,$A13,'Invoice Log'!$AR$3:$AR$303,"<="&$B$3,'Invoice Log'!$AR$3:$AR$303,">="&Settings!$J$10,'Invoice Log'!$J$3:$J$303,"<>Cancelled") -> 0 | G13: =SUMIFS('Invoice Log'!$AP$3:$AP$303,'Invoice Log'!$AS$3:$AS$303,$A13,'Invoice Log'!$AR$3:$AR$303,"<="&$B$3,'Invoice Log'!$AR$3:$AR$303,">="&Settings!$J$10,'Invoice Log'!$J$3:$J$303,"<>Cancelled") -> 0 | H13: =ROUND($G13*Settings!$J$8,2) -> 0 | J13: =IF($H13=0,0,ROUND($H13-N($I13),2)) -> 0 | K13: =COUNTIFS('Invoice Log'!$AS$3:$AS$303,$A13,'Invoice Log'!$AR$3:$AR$303,"<="&$B$3,'Invoice Log'!$AR$3:$AR$303,">="&Settings!$J$10,'Invoice Log'!$J$3:$J$303,"<>Cancelled",'Invoice Log'!$S$3:$S$303,">0",'Invoice Log'!$AN$3:$AN$303,"") -> 0 | L13: =DATE(Settings!$J$7,8,Settings!$J$9) -> 46259 | M13: =IF(EOMONTH($A13,0)<Settings!$J$10,"before the Collective",IF($H13=0,"",IF(N($I13)>=$H13,"PAID",IF(TODAY()>$L13,"OVERDUE","Due "&TEXT($L13,"D MMM"))))) -> before the Collective | N13: =IF(AND($H13>0,N($I13)<$H13),1,0) -> 0
A14: =DATE(Settings!$J$7,8,1) -> 46235 | B14: =COUNTIFS('Invoice Log'!$AS$3:$AS$303,$A14,'Invoice Log'!$AR$3:$AR$303,"<="&$B$3,'Invoice Log'!$AR$3:$AR$303,">="&Settings!$J$10,'Invoice Log'!$J$3:$J$303,"<>Cancelled") -> 0 | C14: =SUMIFS('Invoice Log'!$L$3:$L$303,'Invoice Log'!$AS$3:$AS$303,$A14,'Invoice Log'!$AR$3:$AR$303,"<="&$B$3,'Invoice Log'!$AR$3:$AR$303,">="&Settings!$J$10,'Invoice Log'!$J$3:$J$303,"<>Cancelled") -> 0 | D14: =SUMIFS('Invoice Log'!$S$3:$S$303,'Invoice Log'!$AS$3:$AS$303,$A14,'Invoice Log'!$AR$3:$AR$303,"<="&$B$3,'Invoice Log'!$AR$3:$AR$303,">="&Settings!$J$10,'Invoice Log'!$J$3:$J$303,"<>Cancelled") -> 0 | E14: =SUMIFS('Invoice Log'!$AI$3:$AI$303,'Invoice Log'!$AS$3:$AS$303,$A14,'Invoice Log'!$AR$3:$AR$303,"<="&$B$3,'Invoice Log'!$AR$3:$AR$303,">="&Settings!$J$10,'Invoice Log'!$J$3:$J$303,"<>Cancelled") -> 0 | F14: =SUMIFS('Invoice Log'!$AO$3:$AO$303,'Invoice Log'!$AS$3:$AS$303,$A14,'Invoice Log'!$AR$3:$AR$303,"<="&$B$3,'Invoice Log'!$AR$3:$AR$303,">="&Settings!$J$10,'Invoice Log'!$J$3:$J$303,"<>Cancelled") -> 0 | G14: =SUMIFS('Invoice Log'!$AP$3:$AP$303,'Invoice Log'!$AS$3:$AS$303,$A14,'Invoice Log'!$AR$3:$AR$303,"<="&$B$3,'Invoice Log'!$AR$3:$AR$303,">="&Settings!$J$10,'Invoice Log'!$J$3:$J$303,"<>Cancelled") -> 0 | H14: =ROUND($G14*Settings!$J$8,2) -> 0 | J14: =IF($H14=0,0,ROUND($H14-N($I14),2)) -> 0 | K14: =COUNTIFS('Invoice Log'!$AS$3:$AS$303,$A14,'Invoice Log'!$AR$3:$AR$303,"<="&$B$3,'Invoice Log'!$AR$3:$AR$303,">="&Settings!$J$10,'Invoice Log'!$J$3:$J$303,"<>Cancelled",'Invoice Log'!$S$3:$S$303,">0",'Invoice Log'!$AN$3:$AN$303,"") -> 0 | L14: =DATE(Settings!$J$7,9,Settings!$J$9) -> 46290 | M14: =IF(EOMONTH($A14,0)<Settings!$J$10,"before the Collective",IF($H14=0,"",IF(N($I14)>=$H14,"PAID",IF(TODAY()>$L14,"OVERDUE","Due "&TEXT($L14,"D MMM"))))) -> before the Collective | N14: =IF(AND($H14>0,N($I14)<$H14),1,0) -> 0
A15: =DATE(Settings!$J$7,9,1) -> 46266 | B15: =COUNTIFS('Invoice Log'!$AS$3:$AS$303,$A15,'Invoice Log'!$AR$3:$AR$303,"<="&$B$3,'Invoice Log'!$AR$3:$AR$303,">="&Settings!$J$10,'Invoice Log'!$J$3:$J$303,"<>Cancelled") -> 25 | C15: =SUMIFS('Invoice Log'!$L$3:$L$303,'Invoice Log'!$AS$3:$AS$303,$A15,'Invoice Log'!$AR$3:$AR$303,"<="&$B$3,'Invoice Log'!$AR$3:$AR$303,">="&Settings!$J$10,'Invoice Log'!$J$3:$J$303,"<>Cancelled") -> 87690.9 | D15: =SUMIFS('Invoice Log'!$S$3:$S$303,'Invoice Log'!$AS$3:$AS$303,$A15,'Invoice Log'!$AR$3:$AR$303,"<="&$B$3,'Invoice Log'!$AR$3:$AR$303,">="&Settings!$J$10,'Invoice Log'!$J$3:$J$303,"<>Cancelled") -> 6750.43 | E15: =SUMIFS('Invoice Log'!$AI$3:$AI$303,'Invoice Log'!$AS$3:$AS$303,$A15,'Invoice Log'!$AR$3:$AR$303,"<="&$B$3,'Invoice Log'!$AR$3:$AR$303,">="&Settings!$J$10,'Invoice Log'!$J$3:$J$303,"<>Cancelled") -> 7449.26 | F15: =SUMIFS('Invoice Log'!$AO$3:$AO$303,'Invoice Log'!$AS$3:$AS$303,$A15,'Invoice Log'!$AR$3:$AR$303,"<="&$B$3,'Invoice Log'!$AR$3:$AR$303,">="&Settings!$J$10,'Invoice Log'!$J$3:$J$303,"<>Cancelled") -> 190.37 | G15: =SUMIFS('Invoice Log'!$AP$3:$AP$303,'Invoice Log'!$AS$3:$AS$303,$A15,'Invoice Log'!$AR$3:$AR$303,"<="&$B$3,'Invoice Log'!$AR$3:$AR$303,">="&Settings!$J$10,'Invoice Log'!$J$3:$J$303,"<>Cancelled") -> 87881.27 | H15: =ROUND($G15*Settings!$J$8,2) -> 17576.25 | J15: =IF($H15=0,0,ROUND($H15-N($I15),2)) -> 17576.25 | K15: =COUNTIFS('Invoice Log'!$AS$3:$AS$303,$A15,'Invoice Log'!$AR$3:$AR$303,"<="&$B$3,'Invoice Log'!$AR$3:$AR$303,">="&Settings!$J$10,'Invoice Log'!$J$3:$J$303,"<>Cancelled",'Invoice Log'!$S$3:$S$303,">0",'Invoice Log'!$AN$3:$AN$303,"") -> 7 | L15: =DATE(Settings!$J$7,10,Settings!$J$9) -> 46320 | M15: =IF(EOMONTH($A15,0)<Settings!$J$10,"before the Collective",IF($H15=0,"",IF(N($I15)>=$H15,"PAID",IF(TODAY()>$L15,"OVERDUE","Due "&TEXT($L15,"D MMM"))))) -> Due 25 Oct | N15: =IF(AND($H15>0,N($I15)<$H15),1,0) -> 1
A16: =DATE(Settings!$J$7,10,1) -> 46296 | B16: =COUNTIFS('Invoice Log'!$AS$3:$AS$303,$A16,'Invoice Log'!$AR$3:$AR$303,"<="&$B$3,'Invoice Log'!$AR$3:$AR$303,">="&Settings!$J$10,'Invoice Log'!$J$3:$J$303,"<>Cancelled") -> 2 | C16: =SUMIFS('Invoice Log'!$L$3:$L$303,'Invoice Log'!$AS$3:$AS$303,$A16,'Invoice Log'!$AR$3:$AR$303,"<="&$B$3,'Invoice Log'!$AR$3:$AR$303,">="&Settings!$J$10,'Invoice Log'!$J$3:$J$303,"<>Cancelled") -> 5811.6 | D16: =SUMIFS('Invoice Log'!$S$3:$S$303,'Invoice Log'!$AS$3:$AS$303,$A16,'Invoice Log'!$AR$3:$AR$303,"<="&$B$3,'Invoice Log'!$AR$3:$AR$303,">="&Settings!$J$10,'Invoice Log'!$J$3:$J$303,"<>Cancelled") -> 581.16 | E16: =SUMIFS('Invoice Log'!$AI$3:$AI$303,'Invoice Log'!$AS$3:$AS$303,$A16,'Invoice Log'!$AR$3:$AR$303,"<="&$B$3,'Invoice Log'!$AR$3:$AR$303,">="&Settings!$J$10,'Invoice Log'!$J$3:$J$303,"<>Cancelled") -> 387.76 | F16: =SUMIFS('Invoice Log'!$AO$3:$AO$303,'Invoice Log'!$AS$3:$AS$303,$A16,'Invoice Log'!$AR$3:$AR$303,"<="&$B$3,'Invoice Log'!$AR$3:$AR$303,">="&Settings!$J$10,'Invoice Log'!$J$3:$J$303,"<>Cancelled") -> 0 | G16: =SUMIFS('Invoice Log'!$AP$3:$AP$303,'Invoice Log'!$AS$3:$AS$303,$A16,'Invoice Log'!$AR$3:$AR$303,"<="&$B$3,'Invoice Log'!$AR$3:$AR$303,">="&Settings!$J$10,'Invoice Log'!$J$3:$J$303,"<>Cancelled") -> 5811.6 | H16: =ROUND($G16*Settings!$J$8,2) -> 1162.32 | J16: =IF($H16=0,0,ROUND($H16-N($I16),2)) -> 1162.32 | K16: =COUNTIFS('Invoice Log'!$AS$3:$AS$303,$A16,'Invoice Log'!$AR$3:$AR$303,"<="&$B$3,'Invoice Log'!$AR$3:$AR$303,">="&Settings!$J$10,'Invoice Log'!$J$3:$J$303,"<>Cancelled",'Invoice Log'!$S$3:$S$303,">0",'Invoice Log'!$AN$3:$AN$303,"") -> 2 | L16: =DATE(Settings!$J$7,11,Settings!$J$9) -> 46351 | M16: =IF(EOMONTH($A16,0)<Settings!$J$10,"before the Collective",IF($H16=0,"",IF(N($I16)>=$H16,"PAID",IF(TODAY()>$L16,"OVERDUE","Due "&TEXT($L16,"D MMM"))))) -> Due 25 Nov | N16: =IF(AND($H16>0,N($I16)<$H16),1,0) -> 1
A17: =DATE(Settings!$J$7,11,1) -> 46327 | B17: =COUNTIFS('Invoice Log'!$AS$3:$AS$303,$A17,'Invoice Log'!$AR$3:$AR$303,"<="&$B$3,'Invoice Log'!$AR$3:$AR$303,">="&Settings!$J$10,'Invoice Log'!$J$3:$J$303,"<>Cancelled") -> 0 | C17: =SUMIFS('Invoice Log'!$L$3:$L$303,'Invoice Log'!$AS$3:$AS$303,$A17,'Invoice Log'!$AR$3:$AR$303,"<="&$B$3,'Invoice Log'!$AR$3:$AR$303,">="&Settings!$J$10,'Invoice Log'!$J$3:$J$303,"<>Cancelled") -> 0 | D17: =SUMIFS('Invoice Log'!$S$3:$S$303,'Invoice Log'!$AS$3:$AS$303,$A17,'Invoice Log'!$AR$3:$AR$303,"<="&$B$3,'Invoice Log'!$AR$3:$AR$303,">="&Settings!$J$10,'Invoice Log'!$J$3:$J$303,"<>Cancelled") -> 0 | E17: =SUMIFS('Invoice Log'!$AI$3:$AI$303,'Invoice Log'!$AS$3:$AS$303,$A17,'Invoice Log'!$AR$3:$AR$303,"<="&$B$3,'Invoice Log'!$AR$3:$AR$303,">="&Settings!$J$10,'Invoice Log'!$J$3:$J$303,"<>Cancelled") -> 0 | F17: =SUMIFS('Invoice Log'!$AO$3:$AO$303,'Invoice Log'!$AS$3:$AS$303,$A17,'Invoice Log'!$AR$3:$AR$303,"<="&$B$3,'Invoice Log'!$AR$3:$AR$303,">="&Settings!$J$10,'Invoice Log'!$J$3:$J$303,"<>Cancelled") -> 0 | G17: =SUMIFS('Invoice Log'!$AP$3:$AP$303,'Invoice Log'!$AS$3:$AS$303,$A17,'Invoice Log'!$AR$3:$AR$303,"<="&$B$3,'Invoice Log'!$AR$3:$AR$303,">="&Settings!$J$10,'Invoice Log'!$J$3:$J$303,"<>Cancelled") -> 0 | H17: =ROUND($G17*Settings!$J$8,2) -> 0 | J17: =IF($H17=0,0,ROUND($H17-N($I17),2)) -> 0 | K17: =COUNTIFS('Invoice Log'!$AS$3:$AS$303,$A17,'Invoice Log'!$AR$3:$AR$303,"<="&$B$3,'Invoice Log'!$AR$3:$AR$303,">="&Settings!$J$10,'Invoice Log'!$J$3:$J$303,"<>Cancelled",'Invoice Log'!$S$3:$S$303,">0",'Invoice Log'!$AN$3:$AN$303,"") -> 0 | L17: =DATE(Settings!$J$7,12,Settings!$J$9) -> 46381 | M17: =IF(EOMONTH($A17,0)<Settings!$J$10,"before the Collective",IF($H17=0,"",IF(N($I17)>=$H17,"PAID",IF(TODAY()>$L17,"OVERDUE","Due "&TEXT($L17,"D MMM"))))) | N17: =IF(AND($H17>0,N($I17)<$H17),1,0) -> 0
A18: =DATE(Settings!$J$7,12,1) -> 46357 | B18: =COUNTIFS('Invoice Log'!$AS$3:$AS$303,$A18,'Invoice Log'!$AR$3:$AR$303,"<="&$B$3,'Invoice Log'!$AR$3:$AR$303,">="&Settings!$J$10,'Invoice Log'!$J$3:$J$303,"<>Cancelled") -> 0 | C18: =SUMIFS('Invoice Log'!$L$3:$L$303,'Invoice Log'!$AS$3:$AS$303,$A18,'Invoice Log'!$AR$3:$AR$303,"<="&$B$3,'Invoice Log'!$AR$3:$AR$303,">="&Settings!$J$10,'Invoice Log'!$J$3:$J$303,"<>Cancelled") -> 0 | D18: =SUMIFS('Invoice Log'!$S$3:$S$303,'Invoice Log'!$AS$3:$AS$303,$A18,'Invoice Log'!$AR$3:$AR$303,"<="&$B$3,'Invoice Log'!$AR$3:$AR$303,">="&Settings!$J$10,'Invoice Log'!$J$3:$J$303,"<>Cancelled") -> 0 | E18: =SUMIFS('Invoice Log'!$AI$3:$AI$303,'Invoice Log'!$AS$3:$AS$303,$A18,'Invoice Log'!$AR$3:$AR$303,"<="&$B$3,'Invoice Log'!$AR$3:$AR$303,">="&Settings!$J$10,'Invoice Log'!$J$3:$J$303,"<>Cancelled") -> 0 | F18: =SUMIFS('Invoice Log'!$AO$3:$AO$303,'Invoice Log'!$AS$3:$AS$303,$A18,'Invoice Log'!$AR$3:$AR$303,"<="&$B$3,'Invoice Log'!$AR$3:$AR$303,">="&Settings!$J$10,'Invoice Log'!$J$3:$J$303,"<>Cancelled") -> 0 | G18: =SUMIFS('Invoice Log'!$AP$3:$AP$303,'Invoice Log'!$AS$3:$AS$303,$A18,'Invoice Log'!$AR$3:$AR$303,"<="&$B$3,'Invoice Log'!$AR$3:$AR$303,">="&Settings!$J$10,'Invoice Log'!$J$3:$J$303,"<>Cancelled") -> 0 | H18: =ROUND($G18*Settings!$J$8,2) -> 0 | J18: =IF($H18=0,0,ROUND($H18-N($I18),2)) -> 0 | K18: =COUNTIFS('Invoice Log'!$AS$3:$AS$303,$A18,'Invoice Log'!$AR$3:$AR$303,"<="&$B$3,'Invoice Log'!$AR$3:$AR$303,">="&Settings!$J$10,'Invoice Log'!$J$3:$J$303,"<>Cancelled",'Invoice Log'!$S$3:$S$303,">0",'Invoice Log'!$AN$3:$AN$303,"") -> 0 | L18: =DATE(Settings!$J$7,13,Settings!$J$9) -> 46412 | M18: =IF(EOMONTH($A18,0)<Settings!$J$10,"before the Collective",IF($H18=0,"",IF(N($I18)>=$H18,"PAID",IF(TODAY()>$L18,"OVERDUE","Due "&TEXT($L18,"D MMM"))))) | N18: =IF(AND($H18>0,N($I18)<$H18),1,0) -> 0
A19: TOTAL | B19: =SUM(B7:B18) -> 27 | C19: =SUM(C7:C18) -> 93502.5 | D19: =SUM(D7:D18) -> 7331.59 | E19: =SUM(E7:E18) -> 7837.02 | F19: =SUM(F7:F18) -> 190.37 | G19: =SUM(G7:G18) -> 93692.87 | H19: =SUM(H7:H18) -> 18738.57 | I19: =SUM(I7:I18) -> 0 | ... K19: =SUM(K7:K18) -> 9
A20: NO EVENT DATE | B20: =COUNTIFS('Invoice Log'!$AS$3:$AS$303,"",'Invoice Log'!$J$3:$J$303,"<>Cancelled",'Invoice Log'!$L$3:$L$303,">0") -> 8 | C20: =SUMIFS('Invoice Log'!$L$3:$L$303,'Invoice Log'!$AS$3:$AS$303,"",'Invoice Log'!$J$3:$J$303,"<>Cancelled",'Invoice Log'!$L$3:$L$303,">0") -> 20763.3 | G20: =SUMIFS('Invoice Log'!$AP$3:$AP$303,'Invoice Log'!$AS$3:$AS$303,"",'Invoice Log'!$J$3:$J$303,"<>Cancelled",'Invoice Log'!$L$3:$L$303,">0") -> 20763.3 | H20: =ROUND($G20*Settings!$J$8,2) -> 4152.66 | L20: Whole year. Put a real date in Event Start - only those dated on or after the start count
A23: JOB BY JOB - every job behind the figures above. Filter or sort on Month to check a single month.
A24: Month | B24: Event date | C24: INV Number | D24: Client / Booking Name | E24: Status | F24: Deposit? | G24: Turnover (ex VAT) | H24: Deposit taken | I24: Refund actually paid | J24: Deposit +/- | K24: FINAL (ex VAT) | L24: 20% share | M24: Counted?
A25: =IF('Invoice Log'!$AS3="","",TEXT('Invoice Log'!$AS3,"YYYY-MM")) -> 2026-01 | B25: =IF('Invoice Log'!$AR3="","",'Invoice Log'!$AR3) -> 46037 | C25: =IF('Invoice Log'!$D3="","",'Invoice Log'!$D3) -> 22004198 | D25: =IF('Invoice Log'!$L3="","",'Invoice Log'!$E3) -> JUST | E25: =IF('Invoice Log'!$L3="","",'Invoice Log'!$J3) -> Complete | F25: =IF('Invoice Log'!$L3="","",'Invoice Log'!$Q3) -> Yes | G25: =IF($M25="Yes",'Invoice Log'!$L3,"") | H25: =IF($M25="Yes",'Invoice Log'!$S3,"") | I25: =IF($M25="Yes",'Invoice Log'!$AI3,"") | J25: =IF($M25="Yes",'Invoice Log'!$AO3,"") | K25: =IF($M25="Yes",'Invoice Log'!$AP3,"") | L25: =IF($M25="Yes",ROUND('Invoice Log'!$AP3*Settings!$J$8,2),"") | M25: =IF(OR('Invoice Log'!$L3="",'Invoice Log'!$AS3=""),"",IF(AND('Invoice Log'!$AR3<=$B$3,'Invoice Log'!$AR3>=Settings!$J$10,'Invoice Log'!$J3<>"Cancelled"),"Yes","No")) -> No
A26: =IF('Invoice Log'!$AS4="","",TEXT('Invoice Log'!$AS4,"YYYY-MM")) -> 2026-01 | B26: =IF('Invoice Log'!$AR4="","",'Invoice Log'!$AR4) -> 46038 | C26: =IF('Invoice Log'!$D4="","",'Invoice Log'!$D4) -> 22004199 | D26: =IF('Invoice Log'!$L4="","",'Invoice Log'!$E4) -> London Review of Books | E26: =IF('Invoice Log'!$L4="","",'Invoice Log'!$J4) -> Complete | F26: =IF('Invoice Log'!$L4="","",'Invoice Log'!$Q4) -> Yes | G26: =IF($M26="Yes",'Invoice Log'!$L4,"") | H26: =IF($M26="Yes",'Invoice Log'!$S4,"") | I26: =IF($M26="Yes",'Invoice Log'!$AI4,"") | J26: =IF($M26="Yes",'Invoice Log'!$AO4,"") | K26: =IF($M26="Yes",'Invoice Log'!$AP4,"") | L26: =IF($M26="Yes",ROUND('Invoice Log'!$AP4*Settings!$J$8,2),"") | M26: =IF(OR('Invoice Log'!$L4="",'Invoice Log'!$AS4=""),"",IF(AND('Invoice Log'!$AR4<=$B$3,'Invoice Log'!$AR4>=Settings!$J$10,'Invoice Log'!$J4<>"Cancelled"),"Yes","No")) -> No
A27: =IF('Invoice Log'!$AS5="","",TEXT('Invoice Log'!$AS5,"YYYY-MM")) -> 2026-01 | B27: =IF('Invoice Log'!$AR5="","",'Invoice Log'!$AR5) -> 46044 | C27: =IF('Invoice Log'!$D5="","",'Invoice Log'!$D5) -> 22004200 | D27: =IF('Invoice Log'!$L5="","",'Invoice Log'!$E5) -> Berkeley Homes Capital | E27: =IF('Invoice Log'!$L5="","",'Invoice Log'!$J5) -> Complete | F27: =IF('Invoice Log'!$L5="","",'Invoice Log'!$Q5) -> No | G27: =IF($M27="Yes",'Invoice Log'!$L5,"") | H27: =IF($M27="Yes",'Invoice Log'!$S5,"") | I27: =IF($M27="Yes",'Invoice Log'!$AI5,"") | J27: =IF($M27="Yes",'Invoice Log'!$AO5,"") | K27: =IF($M27="Yes",'Invoice Log'!$AP5,"") | L27: =IF($M27="Yes",ROUND('Invoice Log'!$AP5*Settings!$J$8,2),"") | M27: =IF(OR('Invoice Log'!$L5="",'Invoice Log'!$AS5=""),"",IF(AND('Invoice Log'!$AR5<=$B$3,'Invoice Log'!$AR5>=Settings!$J$10,'Invoice Log'!$J5<>"Cancelled"),"Yes","No")) -> No
A28: =IF('Invoice Log'!$AS6="","",TEXT('Invoice Log'!$AS6,"YYYY-MM")) -> 2026-01 | B28: =IF('Invoice Log'!$AR6="","",'Invoice Log'!$AR6) -> 46044 | C28: =IF('Invoice Log'!$D6="","",'Invoice Log'!$D6) -> 22004201 | D28: =IF('Invoice Log'!$L6="","",'Invoice Log'!$E6) -> Helaba Landesbank Hessen-Thüringen | E28: =IF('Invoice Log'!$L6="","",'Invoice Log'!$J6) -> Complete | F28: =IF('Invoice Log'!$L6="","",'Invoice Log'!$Q6) -> Yes | G28: =IF($M28="Yes",'Invoice Log'!$L6,"") | H28: =IF($M28="Yes",'Invoice Log'!$S6,"") | I28: =IF($M28="Yes",'Invoice Log'!$AI6,"") | J28: =IF($M28="Yes",'Invoice Log'!$AO6,"") | K28: =IF($M28="Yes",'Invoice Log'!$AP6,"") | L28: =IF($M28="Yes",ROUND('Invoice Log'!$AP6*Settings!$J$8,2),"") | M28: =IF(OR('Invoice Log'!$L6="",'Invoice Log'!$AS6=""),"",IF(AND('Invoice Log'!$AR6<=$B$3,'Invoice Log'!$AR6>=Settings!$J$10,'Invoice Log'!$J6<>"Cancelled"),"Yes","No")) -> No
A29: =IF('Invoice Log'!$AS7="","",TEXT('Invoice Log'!$AS7,"YYYY-MM")) -> 2026-02 | B29: =IF('Invoice Log'!$AR7="","",'Invoice Log'!$AR7) -> 46069 | C29: =IF('Invoice Log'!$D7="","",'Invoice Log'!$D7) -> 22004202 | D29: =IF('Invoice Log'!$L7="","",'Invoice Log'!$E7) -> AngloGold - Day 1 | E29: =IF('Invoice Log'!$L7="","",'Invoice Log'!$J7) -> Complete | F29: =IF('Invoice Log'!$L7="","",'Invoice Log'!$Q7) -> Yes | G29: =IF($M29="Yes",'Invoice Log'!$L7,"") | H29: =IF($M29="Yes",'Invoice Log'!$S7,"") | I29: =IF($M29="Yes",'Invoice Log'!$AI7,"") | J29: =IF($M29="Yes",'Invoice Log'!$AO7,"") | K29: =IF($M29="Yes",'Invoice Log'!$AP7,"") | L29: =IF($M29="Yes",ROUND('Invoice Log'!$AP7*Settings!$J$8,2),"") | M29: =IF(OR('Invoice Log'!$L7="",'Invoice Log'!$AS7=""),"",IF(AND('Invoice Log'!$AR7<=$B$3,'Invoice Log'!$AR7>=Settings!$J$10,'Invoice Log'!$J7<>"Cancelled"),"Yes","No")) -> No
A30: =IF('Invoice Log'!$AS8="","",TEXT('Invoice Log'!$AS8,"YYYY-MM")) -> 2026-02 | B30: =IF('Invoice Log'!$AR8="","",'Invoice Log'!$AR8) -> 46070 | C30: =IF('Invoice Log'!$D8="","",'Invoice Log'!$D8) -> 22004203 | D30: =IF('Invoice Log'!$L8="","",'Invoice Log'!$E8) -> AngloGold - Day 2 | E30: =IF('Invoice Log'!$L8="","",'Invoice Log'!$J8) -> Complete | F30: =IF('Invoice Log'!$L8="","",'Invoice Log'!$Q8) -> Yes | G30: =IF($M30="Yes",'Invoice Log'!$L8,"") | H30: =IF($M30="Yes",'Invoice Log'!$S8,"") | I30: =IF($M30="Yes",'Invoice Log'!$AI8,"") | J30: =IF($M30="Yes",'Invoice Log'!$AO8,"") | K30: =IF($M30="Yes",'Invoice Log'!$AP8,"") | L30: =IF($M30="Yes",ROUND('Invoice Log'!$AP8*Settings!$J$8,2),"") | M30: =IF(OR('Invoice Log'!$L8="",'Invoice Log'!$AS8=""),"",IF(AND('Invoice Log'!$AR8<=$B$3,'Invoice Log'!$AR8>=Settings!$J$10,'Invoice Log'!$J8<>"Cancelled"),"Yes","No")) -> No
A31: =IF('Invoice Log'!$AS9="","",TEXT('Invoice Log'!$AS9,"YYYY-MM")) -> 2026-02 | B31: =IF('Invoice Log'!$AR9="","",'Invoice Log'!$AR9) -> 46071 | C31: =IF('Invoice Log'!$D9="","",'Invoice Log'!$D9) -> 22004204 | D31: =IF('Invoice Log'!$L9="","",'Invoice Log'!$E9) -> AngloGold - Day 3 | E31: =IF('Invoice Log'!$L9="","",'Invoice Log'!$J9) -> Complete | F31: =IF('Invoice Log'!$L9="","",'Invoice Log'!$Q9) -> Yes | G31: =IF($M31="Yes",'Invoice Log'!$L9,"") | H31: =IF($M31="Yes",'Invoice Log'!$S9,"") | I31: =IF($M31="Yes",'Invoice Log'!$AI9,"") | J31: =IF($M31="Yes",'Invoice Log'!$AO9,"") | K31: =IF($M31="Yes",'Invoice Log'!$AP9,"") | L31: =IF($M31="Yes",ROUND('Invoice Log'!$AP9*Settings!$J$8,2),"") | M31: =IF(OR('Invoice Log'!$L9="",'Invoice Log'!$AS9=""),"",IF(AND('Invoice Log'!$AR9<=$B$3,'Invoice Log'!$AR9>=Settings!$J$10,'Invoice Log'!$J9<>"Cancelled"),"Yes","No")) -> No
A32: =IF('Invoice Log'!$AS10="","",TEXT('Invoice Log'!$AS10,"YYYY-MM")) -> 2026-01 | B32: =IF('Invoice Log'!$AR10="","",'Invoice Log'!$AR10) -> 46044 | C32: =IF('Invoice Log'!$D10="","",'Invoice Log'!$D10) -> 22004205 | D32: =IF('Invoice Log'!$L10="","",'Invoice Log'!$E10) -> Aesop | E32: =IF('Invoice Log'!$L10="","",'Invoice Log'!$J10) -> Complete | F32: =IF('Invoice Log'!$L10="","",'Invoice Log'!$Q10) -> Yes | G32: =IF($M32="Yes",'Invoice Log'!$L10,"") | H32: =IF($M32="Yes",'Invoice Log'!$S10,"") | I32: =IF($M32="Yes",'Invoice Log'!$AI10,"") | J32: =IF($M32="Yes",'Invoice Log'!$AO10,"") | K32: =IF($M32="Yes",'Invoice Log'!$AP10,"") | L32: =IF($M32="Yes",ROUND('Invoice Log'!$AP10*Settings!$J$8,2),"") | M32: =IF(OR('Invoice Log'!$L10="",'Invoice Log'!$AS10=""),"",IF(AND('Invoice Log'!$AR10<=$B$3,'Invoice Log'!$AR10>=Settings!$J$10,'Invoice Log'!$J10<>"Cancelled"),"Yes","No")) -> No
A33: =IF('Invoice Log'!$AS11="","",TEXT('Invoice Log'!$AS11,"YYYY-MM")) -> 2026-08 | B33: =IF('Invoice Log'!$AR11="","",'Invoice Log'!$AR11) -> 46241 | C33: =IF('Invoice Log'!$D11="","",'Invoice Log'!$D11) -> 22004206 | D33: =IF('Invoice Log'!$L11="","",'Invoice Log'!$E11) -> The Payment Association (Emerging Payments Ventures) | E33: =IF('Invoice Log'!$L11="","",'Invoice Log'!$J11) -> Complete | F33: =IF('Invoice Log'!$L11="","",'Invoice Log'!$Q11) -> Yes | G33: =IF($M33="Yes",'Invoice Log'!$L11,"") | H33: =IF($M33="Yes",'Invoice Log'!$S11,"") | I33: =IF($M33="Yes",'Invoice Log'!$AI11,"") | J33: =IF($M33="Yes",'Invoice Log'!$AO11,"") | K33: =IF($M33="Yes",'Invoice Log'!$AP11,"") | L33: =IF($M33="Yes",ROUND('Invoice Log'!$AP11*Settings!$J$8,2),"") | M33: =IF(OR('Invoice Log'!$L11="",'Invoice Log'!$AS11=""),"",IF(AND('Invoice Log'!$AR11<=$B$3,'Invoice Log'!$AR11>=Settings!$J$10,'Invoice Log'!$J11<>"Cancelled"),"Yes","No")) -> No
A34: =IF('Invoice Log'!$AS12="","",TEXT('Invoice Log'!$AS12,"YYYY-MM")) -> 2026-02 | B34: =IF('Invoice Log'!$AR12="","",'Invoice Log'!$AR12) -> 46077 | C34: =IF('Invoice Log'!$D12="","",'Invoice Log'!$D12) -> 22004207 | D34: =IF('Invoice Log'!$L12="","",'Invoice Log'!$E12) -> George Jensen Limited | E34: =IF('Invoice Log'!$L12="","",'Invoice Log'!$J12) -> Complete | F34: =IF('Invoice Log'!$L12="","",'Invoice Log'!$Q12) -> Yes | G34: =IF($M34="Yes",'Invoice Log'!$L12,"") | H34: =IF($M34="Yes",'Invoice Log'!$S12,"") | I34: =IF($M34="Yes",'Invoice Log'!$AI12,"") | J34: =IF($M34="Yes",'Invoice Log'!$AO12,"") | K34: =IF($M34="Yes",'Invoice Log'!$AP12,"") | L34: =IF($M34="Yes",ROUND('Invoice Log'!$AP12*Settings!$J$8,2),"") | M34: =IF(OR('Invoice Log'!$L12="",'Invoice Log'!$AS12=""),"",IF(AND('Invoice Log'!$AR12<=$B$3,'Invoice Log'!$AR12>=Settings!$J$10,'Invoice Log'!$J12<>"Cancelled"),"Yes","No")) -> No
A35: =IF('Invoice Log'!$AS13="","",TEXT('Invoice Log'!$AS13,"YYYY-MM")) -> 2026-01 | B35: =IF('Invoice Log'!$AR13="","",'Invoice Log'!$AR13) -> 46050 | C35: =IF('Invoice Log'!$D13="","",'Invoice Log'!$D13) -> 22004208 | D35: =IF('Invoice Log'!$L13="","",'Invoice Log'!$E13) -> SGN - Day 1 | E35: =IF('Invoice Log'!$L13="","",'Invoice Log'!$J13) -> Complete | F35: =IF('Invoice Log'!$L13="","",'Invoice Log'!$Q13) -> No | G35: =IF($M35="Yes",'Invoice Log'!$L13,"") | H35: =IF($M35="Yes",'Invoice Log'!$S13,"") | I35: =IF($M35="Yes",'Invoice Log'!$AI13,"") | J35: =IF($M35="Yes",'Invoice Log'!$AO13,"") | K35: =IF($M35="Yes",'Invoice Log'!$AP13,"") | L35: =IF($M35="Yes",ROUND('Invoice Log'!$AP13*Settings!$J$8,2),"") | M35: =IF(OR('Invoice Log'!$L13="",'Invoice Log'!$AS13=""),"",IF(AND('Invoice Log'!$AR13<=$B$3,'Invoice Log'!$AR13>=Settings!$J$10,'Invoice Log'!$J13<>"Cancelled"),"Yes","No")) -> No
A36: =IF('Invoice Log'!$AS14="","",TEXT('Invoice Log'!$AS14,"YYYY-MM")) -> 2026-01 | B36: =IF('Invoice Log'!$AR14="","",'Invoice Log'!$AR14) -> 46051 | C36: =IF('Invoice Log'!$D14="","",'Invoice Log'!$D14) -> 22004209 | D36: =IF('Invoice Log'!$L14="","",'Invoice Log'!$E14) -> SGN - Day 2 | E36: =IF('Invoice Log'!$L14="","",'Invoice Log'!$J14) -> Complete | F36: =IF('Invoice Log'!$L14="","",'Invoice Log'!$Q14) -> No | G36: =IF($M36="Yes",'Invoice Log'!$L14,"") | H36: =IF($M36="Yes",'Invoice Log'!$S14,"") | I36: =IF($M36="Yes",'Invoice Log'!$AI14,"") | J36: =IF($M36="Yes",'Invoice Log'!$AO14,"") | K36: =IF($M36="Yes",'Invoice Log'!$AP14,"") | L36: =IF($M36="Yes",ROUND('Invoice Log'!$AP14*Settings!$J$8,2),"") | M36: =IF(OR('Invoice Log'!$L14="",'Invoice Log'!$AS14=""),"",IF(AND('Invoice Log'!$AR14<=$B$3,'Invoice Log'!$AR14>=Settings!$J$10,'Invoice Log'!$J14<>"Cancelled"),"Yes","No")) -> No
... A325: =IF('Invoice Log'!$AS303="","",TEXT('Invoice Log'!$AS303,"YYYY-MM")) | B325: =IF('Invoice Log'!$AR303="","",'Invoice Log'!$AR303) | C325: =IF('Invoice Log'!$D303="","",'Invoice Log'!$D303) | D325: =IF('Invoice Log'!$L303="","",'Invoice Log'!$E303) | E325: =IF('Invoice Log'!$L303="","",'Invoice Log'!$J303) | F325: =IF('Invoice Log'!$L303="","",'Invoice Log'!$Q303) | G325: =IF($M325="Yes",'Invoice Log'!$L303,"") | H325: =IF($M325="Yes",'Invoice Log'!$S303,"") | I325: =IF($M325="Yes",'Invoice Log'!$AI303,"") | J325: =IF($M325="Yes",'Invoice Log'!$AO303,"") | K325: =IF($M325="Yes",'Invoice Log'!$AP303,"") | L325: =IF($M325="Yes",ROUND('Invoice Log'!$AP303*Settings!$J$8,2),"") | M325: =IF(OR('Invoice Log'!$L303="",'Invoice Log'!$AS303=""),"",IF(AND('Invoice Log'!$AR303<=$B$3,'Invoice Log'!$AR303>=Settings!$J$10,'Invoice Log'!$J303<>"Cancelled"),"Yes","No"))

Sheet VAT
A1: ="VAT TALLY "&Settings!$J$7 -> VAT TALLY 2026
A2: Output VAT you have charged. Grouped by INVOICE date, which is the tax point HMRC and Xero work to.
A3: Refundable deposits carry no VAT, so nothing here moves when a deposit is adjusted. Cancelled jobs are excluded.
A4: ="Every event is standard-rated, so a blank VAT Rate is treated as "&TEXT(Settings!$J$11,"0%")&" automatically. Type a rate in only when a job is genuinely different. Deposits carry no VAT." -> Every event is standard-rated, so a blank VAT Rate is treated as 20% automatically. Type a rate in only when a job is genuinely different. Deposits carry no VAT.
A6: MONTH BY MONTH | G6: Cross-check
A7: Month | B7: Jobs | C7: Net (ex VAT) | D7: VAT CHARGED | E7: Gross (inc VAT) | G7: VAT by event date
A8: =DATE(Settings!$J$7,1,1) -> 46023 | B8: =COUNTIFS('Invoice Log'!$H$3:$H$303,">="&$A8,'Invoice Log'!$H$3:$H$303,"<="&EOMONTH($A8,0),'Invoice Log'!$J$3:$J$303,"<>Cancelled") -> 21 | C8: =SUMIFS('Invoice Log'!$L$3:$L$303,'Invoice Log'!$H$3:$H$303,">="&$A8,'Invoice Log'!$H$3:$H$303,"<="&EOMONTH($A8,0),'Invoice Log'!$J$3:$J$303,"<>Cancelled") -> 76594.71 | D8: =SUMIFS('Invoice Log'!$O$3:$O$303,'Invoice Log'!$H$3:$H$303,">="&$A8,'Invoice Log'!$H$3:$H$303,"<="&EOMONTH($A8,0),'Invoice Log'!$J$3:$J$303,"<>Cancelled") -> 15318.942 | E8: =ROUND($C8+$D8,2) -> 91913.65 | G8: =SUMIFS('Invoice Log'!$O$3:$O$303,'Invoice Log'!$AS$3:$AS$303,$A8,'Invoice Log'!$J$3:$J$303,"<>Cancelled") -> 7762.24
A9: =DATE(Settings!$J$7,2,1) -> 46054 | B9: =COUNTIFS('Invoice Log'!$H$3:$H$303,">="&$A9,'Invoice Log'!$H$3:$H$303,"<="&EOMONTH($A9,0),'Invoice Log'!$J$3:$J$303,"<>Cancelled") -> 14 | C9: =SUMIFS('Invoice Log'!$L$3:$L$303,'Invoice Log'!$H$3:$H$303,">="&$A9,'Invoice Log'!$H$3:$H$303,"<="&EOMONTH($A9,0),'Invoice Log'!$J$3:$J$303,"<>Cancelled") -> 35261.6 | D9: =SUMIFS('Invoice Log'!$O$3:$O$303,'Invoice Log'!$H$3:$H$303,">="&$A9,'Invoice Log'!$H$3:$H$303,"<="&EOMONTH($A9,0),'Invoice Log'!$J$3:$J$303,"<>Cancelled") -> 7052.32 | E9: =ROUND($C9+$D9,2) -> 42313.92 | G9: =SUMIFS('Invoice Log'!$O$3:$O$303,'Invoice Log'!$AS$3:$AS$303,$A9,'Invoice Log'!$J$3:$J$303,"<>Cancelled") -> 7106.836
A10: =DATE(Settings!$J$7,3,1) -> 46082 | B10: =COUNTIFS('Invoice Log'!$H$3:$H$303,">="&$A10,'Invoice Log'!$H$3:$H$303,"<="&EOMONTH($A10,0),'Invoice Log'!$J$3:$J$303,"<>Cancelled") -> 22 | C10: =SUMIFS('Invoice Log'!$L$3:$L$303,'Invoice Log'!$H$3:$H$303,">="&$A10,'Invoice Log'!$H$3:$H$303,"<="&EOMONTH($A10,0),'Invoice Log'!$J$3:$J$303,"<>Cancelled") -> 42918.7 | D10: =SUMIFS('Invoice Log'!$O$3:$O$303,'Invoice Log'!$H$3:$H$303,">="&$A10,'Invoice Log'!$H$3:$H$303,"<="&EOMONTH($A10,0),'Invoice Log'!$J$3:$J$303,"<>Cancelled") -> 8297.74 | E10: =ROUND($C10+$D10,2) -> 51216.44 | G10: =SUMIFS('Invoice Log'!$O$3:$O$303,'Invoice Log'!$AS$3:$AS$303,$A10,'Invoice Log'!$J$3:$J$303,"<>Cancelled") -> 8150.626
A11: =DATE(Settings!$J$7,4,1) -> 46113 | B11: =COUNTIFS('Invoice Log'!$H$3:$H$303,">="&$A11,'Invoice Log'!$H$3:$H$303,"<="&EOMONTH($A11,0),'Invoice Log'!$J$3:$J$303,"<>Cancelled") -> 14 | C11: =SUMIFS('Invoice Log'!$L$3:$L$303,'Invoice Log'!$H$3:$H$303,">="&$A11,'Invoice Log'!$H$3:$H$303,"<="&EOMONTH($A11,0),'Invoice Log'!$J$3:$J$303,"<>Cancelled") -> 90718.75 | D11: =SUMIFS('Invoice Log'!$O$3:$O$303,'Invoice Log'!$H$3:$H$303,">="&$A11,'Invoice Log'!$H$3:$H$303,"<="&EOMONTH($A11,0),'Invoice Log'!$J$3:$J$303,"<>Cancelled") -> 18143.75 | E11: =ROUND($C11+$D11,2) -> 108862.5 | G11: =SUMIFS('Invoice Log'!$O$3:$O$303,'Invoice Log'!$AS$3:$AS$303,$A11,'Invoice Log'!$J$3:$J$303,"<>Cancelled") -> 4737.82
A12: =DATE(Settings!$J$7,5,1) -> 46143 | B12: =COUNTIFS('Invoice Log'!$H$3:$H$303,">="&$A12,'Invoice Log'!$H$3:$H$303,"<="&EOMONTH($A12,0),'Invoice Log'!$J$3:$J$303,"<>Cancelled") -> 9 | C12: =SUMIFS('Invoice Log'!$L$3:$L$303,'Invoice Log'!$H$3:$H$303,">="&$A12,'Invoice Log'!$H$3:$H$303,"<="&EOMONTH($A12,0),'Invoice Log'!$J$3:$J$303,"<>Cancelled") -> 57141.3 | D12: =SUMIFS('Invoice Log'!$O$3:$O$303,'Invoice Log'!$H$3:$H$303,">="&$A12,'Invoice Log'!$H$3:$H$303,"<="&EOMONTH($A12,0),'Invoice Log'!$J$3:$J$303,"<>Cancelled") -> 11428.26 | E12: =ROUND($C12+$D12,2) -> 68569.56 | G12: =SUMIFS('Invoice Log'!$O$3:$O$303,'Invoice Log'!$AS$3:$AS$303,$A12,'Invoice Log'!$J$3:$J$303,"<>Cancelled") -> 3093.1
A13: =DATE(Settings!$J$7,6,1) -> 46174 | B13: =COUNTIFS('Invoice Log'!$H$3:$H$303,">="&$A13,'Invoice Log'!$H$3:$H$303,"<="&EOMONTH($A13,0),'Invoice Log'!$J$3:$J$303,"<>Cancelled") -> 25 | C13: =SUMIFS('Invoice Log'!$L$3:$L$303,'Invoice Log'!$H$3:$H$303,">="&$A13,'Invoice Log'!$H$3:$H$303,"<="&EOMONTH($A13,0),'Invoice Log'!$J$3:$J$303,"<>Cancelled") -> 72924.69 | D13: =SUMIFS('Invoice Log'!$O$3:$O$303,'Invoice Log'!$H$3:$H$303,">="&$A13,'Invoice Log'!$H$3:$H$303,"<="&EOMONTH($A13,0),'Invoice Log'!$J$3:$J$303,"<>Cancelled") -> 14584.938 | E13: =ROUND($C13+$D13,2) -> 87509.63 | G13: =SUMIFS('Invoice Log'!$O$3:$O$303,'Invoice Log'!$AS$3:$AS$303,$A13,'Invoice Log'!$J$3:$J$303,"<>Cancelled") -> 28384.418
A14: =DATE(Settings!$J$7,7,1) -> 46204 | B14: =COUNTIFS('Invoice Log'!$H$3:$H$303,">="&$A14,'Invoice Log'!$H$3:$H$303,"<="&EOMONTH($A14,0),'Invoice Log'!$J$3:$J$303,"<>Cancelled") -> 5 | C14: =SUMIFS('Invoice Log'!$L$3:$L$303,'Invoice Log'!$H$3:$H$303,">="&$A14,'Invoice Log'!$H$3:$H$303,"<="&EOMONTH($A14,0),'Invoice Log'!$J$3:$J$303,"<>Cancelled") -> 11479.8 | D14: =SUMIFS('Invoice Log'!$O$3:$O$303,'Invoice Log'!$H$3:$H$303,">="&$A14,'Invoice Log'!$H$3:$H$303,"<="&EOMONTH($A14,0),'Invoice Log'!$J$3:$J$303,"<>Cancelled") -> 2295.96 | E14: =ROUND($C14+$D14,2) -> 13775.76 | G14: =SUMIFS('Invoice Log'!$O$3:$O$303,'Invoice Log'!$AS$3:$AS$303,$A14,'Invoice Log'!$J$3:$J$303,"<>Cancelled") -> 13437.12
A15: =DATE(Settings!$J$7,8,1) -> 46235 | B15: =COUNTIFS('Invoice Log'!$H$3:$H$303,">="&$A15,'Invoice Log'!$H$3:$H$303,"<="&EOMONTH($A15,0),'Invoice Log'!$J$3:$J$303,"<>Cancelled") -> 16 | C15: =SUMIFS('Invoice Log'!$L$3:$L$303,'Invoice Log'!$H$3:$H$303,">="&$A15,'Invoice Log'!$H$3:$H$303,"<="&EOMONTH($A15,0),'Invoice Log'!$J$3:$J$303,"<>Cancelled") -> 42446.2 | D15: =SUMIFS('Invoice Log'!$O$3:$O$303,'Invoice Log'!$H$3:$H$303,">="&$A15,'Invoice Log'!$H$3:$H$303,"<="&EOMONTH($A15,0),'Invoice Log'!$J$3:$J$303,"<>Cancelled") -> 8489.24 | E15: =ROUND($C15+$D15,2) -> 50935.44 | G15: =SUMIFS('Invoice Log'!$O$3:$O$303,'Invoice Log'!$AS$3:$AS$303,$A15,'Invoice Log'!$J$3:$J$303,"<>Cancelled") -> 2373.09
A16: =DATE(Settings!$J$7,9,1) -> 46266 | B16: =COUNTIFS('Invoice Log'!$H$3:$H$303,">="&$A16,'Invoice Log'!$H$3:$H$303,"<="&EOMONTH($A16,0),'Invoice Log'!$J$3:$J$303,"<>Cancelled") -> 24 | C16: =SUMIFS('Invoice Log'!$L$3:$L$303,'Invoice Log'!$H$3:$H$303,">="&$A16,'Invoice Log'!$H$3:$H$303,"<="&EOMONTH($A16,0),'Invoice Log'!$J$3:$J$303,"<>Cancelled") -> 99485.6 | D16: =SUMIFS('Invoice Log'!$O$3:$O$303,'Invoice Log'!$H$3:$H$303,">="&$A16,'Invoice Log'!$H$3:$H$303,"<="&EOMONTH($A16,0),'Invoice Log'!$J$3:$J$303,"<>Cancelled") -> 19897.12 | E16: =ROUND($C16+$D16,2) -> 119382.72 | G16: =SUMIFS('Invoice Log'!$O$3:$O$303,'Invoice Log'!$AS$3:$AS$303,$A16,'Invoice Log'!$J$3:$J$303,"<>Cancelled") -> 17538.18
A17: =DATE(Settings!$J$7,10,1) -> 46296 | B17: =COUNTIFS('Invoice Log'!$H$3:$H$303,">="&$A17,'Invoice Log'!$H$3:$H$303,"<="&EOMONTH($A17,0),'Invoice Log'!$J$3:$J$303,"<>Cancelled") -> 2 | C17: =SUMIFS('Invoice Log'!$L$3:$L$303,'Invoice Log'!$H$3:$H$303,">="&$A17,'Invoice Log'!$H$3:$H$303,"<="&EOMONTH($A17,0),'Invoice Log'!$J$3:$J$303,"<>Cancelled") -> 6705.9 | D17: =SUMIFS('Invoice Log'!$O$3:$O$303,'Invoice Log'!$H$3:$H$303,">="&$A17,'Invoice Log'!$H$3:$H$303,"<="&EOMONTH($A17,0),'Invoice Log'!$J$3:$J$303,"<>Cancelled") -> 1341.18 | E17: =ROUND($C17+$D17,2) -> 8047.08 | G17: =SUMIFS('Invoice Log'!$O$3:$O$303,'Invoice Log'!$AS$3:$AS$303,$A17,'Invoice Log'!$J$3:$J$303,"<>Cancelled") -> 5178.11
A18: =DATE(Settings!$J$7,11,1) -> 46327 | B18: =COUNTIFS('Invoice Log'!$H$3:$H$303,">="&$A18,'Invoice Log'!$H$3:$H$303,"<="&EOMONTH($A18,0),'Invoice Log'!$J$3:$J$303,"<>Cancelled") -> 0 | C18: =SUMIFS('Invoice Log'!$L$3:$L$303,'Invoice Log'!$H$3:$H$303,">="&$A18,'Invoice Log'!$H$3:$H$303,"<="&EOMONTH($A18,0),'Invoice Log'!$J$3:$J$303,"<>Cancelled") -> 0 | D18: =SUMIFS('Invoice Log'!$O$3:$O$303,'Invoice Log'!$H$3:$H$303,">="&$A18,'Invoice Log'!$H$3:$H$303,"<="&EOMONTH($A18,0),'Invoice Log'!$J$3:$J$303,"<>Cancelled") -> 0 | E18: =ROUND($C18+$D18,2) -> 0 | G18: =SUMIFS('Invoice Log'!$O$3:$O$303,'Invoice Log'!$AS$3:$AS$303,$A18,'Invoice Log'!$J$3:$J$303,"<>Cancelled") -> 1573.87
A19: =DATE(Settings!$J$7,12,1) -> 46357 | B19: =COUNTIFS('Invoice Log'!$H$3:$H$303,">="&$A19,'Invoice Log'!$H$3:$H$303,"<="&EOMONTH($A19,0),'Invoice Log'!$J$3:$J$303,"<>Cancelled") -> 0 | C19: =SUMIFS('Invoice Log'!$L$3:$L$303,'Invoice Log'!$H$3:$H$303,">="&$A19,'Invoice Log'!$H$3:$H$303,"<="&EOMONTH($A19,0),'Invoice Log'!$J$3:$J$303,"<>Cancelled") -> 0 | D19: =SUMIFS('Invoice Log'!$O$3:$O$303,'Invoice Log'!$H$3:$H$303,">="&$A19,'Invoice Log'!$H$3:$H$303,"<="&EOMONTH($A19,0),'Invoice Log'!$J$3:$J$303,"<>Cancelled") -> 0 | E19: =ROUND($C19+$D19,2) -> 0 | G19: =SUMIFS('Invoice Log'!$O$3:$O$303,'Invoice Log'!$AS$3:$AS$303,$A19,'Invoice Log'!$J$3:$J$303,"<>Cancelled") -> 4490.98
A20: TOTAL | B20: =SUM(B8:B19) -> 152 | C20: =SUM(C8:C19) -> 535677.25 | D20: =SUM(D8:D19) -> 106849.45 | E20: =SUM(E8:E19) -> 642526.7
A23: BY QUARTER - what to set aside
A24: Quarter | B24: Jobs | C24: Net (ex VAT) | D24: VAT CHARGED | E24: Gross (inc VAT)
A25: Q1 Jan-Mar | B25: =SUM(B8:B10) -> 57 | C25: =SUM(C8:C10) -> 154775.01 | D25: =SUM(D8:D10) -> 30669.002 | E25: =SUM(E8:E10) -> 185444.01
A26: Q2 Apr-Jun | B26: =SUM(B11:B13) -> 48 | C26: =SUM(C11:C13) -> 220784.74 | D26: =SUM(D11:D13) -> 44156.948 | E26: =SUM(E11:E13) -> 264941.69
A27: Q3 Jul-Sep | B27: =SUM(B14:B16) -> 45 | C27: =SUM(C14:C16) -> 153411.6 | D27: =SUM(D14:D16) -> 30682.32 | E27: =SUM(E14:E16) -> 184093.92
A28: Q4 Oct-Dec | B28: =SUM(B17:B19) -> 2 | C28: =SUM(C17:C19) -> 6705.9 | D28: =SUM(D17:D19) -> 1341.18 | E28: =SUM(E17:E19) -> 8047.08
A29: Calendar quarters. If your VAT quarters run differently, tell me and I will reset them.

Sheet Dashboard
A1: ="QUOTE & INVOICE LOG "&Settings!$J$7&" - Dashboard" -> QUOTE & INVOICE LOG 2026 - Dashboard
A2: ="Everything here updates itself - showing "&Settings!$J$7&". Change the Reporting year on Settings to look at another year." -> Everything here updates itself - showing 2026. Change the Reporting year on Settings to look at another year.
A4: INVOICED THIS YEAR | C4: RECEIVED | F4: COLOUR KEY
A5: =SUMIFS('Invoice Log'!$T$3:$T$303,'Invoice Log'!$J$3:$J$303,"<>Cancelled",'Invoice Log'!$AT$3:$AT$303,Settings!$J$7) -> 691446.46 | C5: =SUMIFS('Invoice Log'!$AE$3:$AE$303,'Invoice Log'!$AT$3:$AT$303,Settings!$J$7) -> 614090.51 | F5: Quote Sent | G5: Quote out, not confirmed yet
F6: Confirmed - Awaiting Payment | G6: Booked in - they still owe us
F7: Part Paid | G7: Some money in, balance outstanding
F8: Paid in Full | G8: All money in - deposit still held
A9: STILL OWED TO US | C9: OF WHICH OVERDUE | F9: Refund Due | G9: ACTION: put the deposit back
A10: =SUMIFS('Invoice Log'!$AG$3:$AG$303,'Invoice Log'!$AT$3:$AT$303,Settings!$J$7) -> 61962.01 | C10: =SUMIFS('Invoice Log'!$AG$3:$AG$303,'Invoice Log'!$AH$3:$AH$303,">0",'Invoice Log'!$AT$3:$AT$303,Settings!$J$7) -> 4128.22 | F10: Complete | G10: Paid, done, deposit returned
F11: Cancelled | G11: Row greys out, nothing owed
A12: Red column on the log | C12: Past 30 day terms
F13: BY MONTH (by event date)
A14: DEPOSITS STILL TO REFUND | C14: JOBS WITH NO STATUS | F14: Month | G14: Jobs | H14: Invoiced
A15: =SUMIFS('Invoice Log'!$AI$3:$AI$303,'Invoice Log'!$AN$3:$AN$303,"",'Invoice Log'!$AT$3:$AT$303,Settings!$J$7) -> 11704.65 | C15: =COUNTIFS('Invoice Log'!$L$3:$L$303,">0",'Invoice Log'!$J$3:$J$303,"") -> 7 | F15: =DATE(Settings!$J$7,1,1) -> 46023 | G15: =COUNTIFS('Invoice Log'!$AS$3:$AS$303,$F15) -> 11 | H15: =SUMIFS('Invoice Log'!$T$3:$T$303,'Invoice Log'!$AS$3:$AS$303,$F15,'Invoice Log'!$J$3:$J$303,"<>Cancelled") -> 49666.03
F16: =DATE(Settings!$J$7,2,1) -> 46054 | G16: =COUNTIFS('Invoice Log'!$AS$3:$AS$303,$F16) -> 14 | H16: =SUMIFS('Invoice Log'!$T$3:$T$303,'Invoice Log'!$AS$3:$AS$303,$F16,'Invoice Log'!$J$3:$J$303,"<>Cancelled") -> 47275.736
A17: =COUNTIFS('Invoice Log'!$AI$3:$AI$303,">0",'Invoice Log'!$AN$3:$AN$303,"",'Invoice Log'!$AT$3:$AT$303,Settings!$J$7)&" jobs waiting" -> 19 jobs waiting | C17: Pink rows on the log | F17: =DATE(Settings!$J$7,3,1) -> 46082 | G17: =COUNTIFS('Invoice Log'!$AS$3:$AS$303,$F17) -> 22 | H17: =SUMIFS('Invoice Log'!$T$3:$T$303,'Invoice Log'!$AS$3:$AS$303,$F17,'Invoice Log'!$J$3:$J$303,"<>Cancelled") -> 50725.116
F18: =DATE(Settings!$J$7,4,1) -> 46113 | G18: =COUNTIFS('Invoice Log'!$AS$3:$AS$303,$F18) -> 9 | H18: =SUMIFS('Invoice Log'!$T$3:$T$303,'Invoice Log'!$AS$3:$AS$303,$F18,'Invoice Log'!$J$3:$J$303,"<>Cancelled") -> 29168.91
A19: DUE TO THE COLLECTIVE | C19: PAID TO THE COLLECTIVE | F19: =DATE(Settings!$J$7,5,1) -> 46143 | G19: =COUNTIFS('Invoice Log'!$AS$3:$AS$303,$F19) -> 7 | H19: =SUMIFS('Invoice Log'!$T$3:$T$303,'Invoice Log'!$AS$3:$AS$303,$F19,'Invoice Log'!$J$3:$J$303,"<>Cancelled") -> 19543.34
A20: =SUM(Collective!$H$7:$H$18) -> 18738.57 | C20: =SUM(Collective!$I$7:$I$18) -> 0 | F20: =DATE(Settings!$J$7,6,1) -> 46174 | G20: =COUNTIFS('Invoice Log'!$AS$3:$AS$303,$F20) -> 25 | H20: =SUMIFS('Invoice Log'!$T$3:$T$303,'Invoice Log'!$AS$3:$AS$303,$F20,'Invoice Log'!$J$3:$J$303,"<>Cancelled") -> 181689.4
F21: =DATE(Settings!$J$7,7,1) -> 46204 | G21: =COUNTIFS('Invoice Log'!$AS$3:$AS$303,$F21) -> 14 | H21: =SUMIFS('Invoice Log'!$T$3:$T$303,'Invoice Log'!$AS$3:$AS$303,$F21,'Invoice Log'!$J$3:$J$303,"<>Cancelled") -> 87042.19
A22: 20% of net turnover, year to date | C22: =TEXT(SUM(Collective!$J$7:$J$18),"£#,##0.00")&" still outstanding" -> £18,738.57 still outstanding | F22: =DATE(Settings!$J$7,8,1) -> 46235 | G22: =COUNTIFS('Invoice Log'!$AS$3:$AS$303,$F22) -> 7 | H22: =SUMIFS('Invoice Log'!$T$3:$T$303,'Invoice Log'!$AS$3:$AS$303,$F22,'Invoice Log'!$J$3:$J$303,"<>Cancelled") -> 15207.04
F23: =DATE(Settings!$J$7,9,1) -> 46266 | G23: =COUNTIFS('Invoice Log'!$AS$3:$AS$303,$F23) -> 26 | H23: =SUMIFS('Invoice Log'!$T$3:$T$303,'Invoice Log'!$AS$3:$AS$303,$F23,'Invoice Log'!$J$3:$J$303,"<>Cancelled") -> 111979.51
F24: =DATE(Settings!$J$7,10,1) -> 46296 | G24: =COUNTIFS('Invoice Log'!$AS$3:$AS$303,$F24) -> 7 | H24: =SUMIFS('Invoice Log'!$T$3:$T$303,'Invoice Log'!$AS$3:$AS$303,$F24,'Invoice Log'!$J$3:$J$303,"<>Cancelled") -> 33197.8
A25: BY COMPANY | F25: =DATE(Settings!$J$7,11,1) -> 46327 | G25: =COUNTIFS('Invoice Log'!$AS$3:$AS$303,$F25) -> 2 | H25: =SUMIFS('Invoice Log'!$T$3:$T$303,'Invoice Log'!$AS$3:$AS$303,$F25,'Invoice Log'!$J$3:$J$303,"<>Cancelled") -> 10230.16
A26: Company | B26: Invoiced | C26: Still owed | D26: Refunds due | F26: =DATE(Settings!$J$7,12,1) -> 46357 | G26: =COUNTIFS('Invoice Log'!$AS$3:$AS$303,$F26) -> 2 | H26: =SUMIFS('Invoice Log'!$T$3:$T$303,'Invoice Log'!$AS$3:$AS$303,$F26,'Invoice Log'!$J$3:$J$303,"<>Cancelled") -> 29191.37
A27: =IF(Settings!$B$4="","",Settings!$B$4) -> Penni Black | B27: =IF($A27="","",SUMIFS('Invoice Log'!$T$3:$T$303,'Invoice Log'!$B$3:$B$303,$A27,'Invoice Log'!$J$3:$J$303,"<>Cancelled",'Invoice Log'!$AT$3:$AT$303,Settings!$J$7)) -> 691072.06 | C27: =IF($A27="","",SUMIFS('Invoice Log'!$AG$3:$AG$303,'Invoice Log'!$B$3:$B$303,$A27,'Invoice Log'!$AT$3:$AT$303,Settings!$J$7)) -> 61962.01 | D27: =IF($A27="","",SUMIFS('Invoice Log'!$AI$3:$AI$303,'Invoice Log'!$B$3:$B$303,$A27,'Invoice Log'!$AN$3:$AN$303,"",'Invoice Log'!$AT$3:$AT$303,Settings!$J$7)) -> 11704.65
A28: =IF(Settings!$B$5="","",Settings!$B$5) -> Venn | B28: =IF($A28="","",SUMIFS('Invoice Log'!$T$3:$T$303,'Invoice Log'!$B$3:$B$303,$A28,'Invoice Log'!$J$3:$J$303,"<>Cancelled",'Invoice Log'!$AT$3:$AT$303,Settings!$J$7)) -> 0 | C28: =IF($A28="","",SUMIFS('Invoice Log'!$AG$3:$AG$303,'Invoice Log'!$B$3:$B$303,$A28,'Invoice Log'!$AT$3:$AT$303,Settings!$J$7)) -> 0 | D28: =IF($A28="","",SUMIFS('Invoice Log'!$AI$3:$AI$303,'Invoice Log'!$B$3:$B$303,$A28,'Invoice Log'!$AN$3:$AN$303,"",'Invoice Log'!$AT$3:$AT$303,Settings!$J$7)) -> 0
A29: =IF(Settings!$B$6="","",Settings!$B$6) -> Raquel's | B29: =IF($A29="","",SUMIFS('Invoice Log'!$T$3:$T$303,'Invoice Log'!$B$3:$B$303,$A29,'Invoice Log'!$J$3:$J$303,"<>Cancelled",'Invoice Log'!$AT$3:$AT$303,Settings!$J$7)) -> 374.4 | C29: =IF($A29="","",SUMIFS('Invoice Log'!$AG$3:$AG$303,'Invoice Log'!$B$3:$B$303,$A29,'Invoice Log'!$AT$3:$AT$303,Settings!$J$7)) -> 0 | D29: =IF($A29="","",SUMIFS('Invoice Log'!$AI$3:$AI$303,'Invoice Log'!$B$3:$B$303,$A29,'Invoice Log'!$AN$3:$AN$303,"",'Invoice Log'!$AT$3:$AT$303,Settings!$J$7)) -> 0
A30: =IF(Settings!$B$7="","",Settings!$B$7) -> Free Spirit | B30: =IF($A30="","",SUMIFS('Invoice Log'!$T$3:$T$303,'Invoice Log'!$B$3:$B$303,$A30,'Invoice Log'!$J$3:$J$303,"<>Cancelled",'Invoice Log'!$AT$3:$AT$303,Settings!$J$7)) -> 0 | C30: =IF($A30="","",SUMIFS('Invoice Log'!$AG$3:$AG$303,'Invoice Log'!$B$3:$B$303,$A30,'Invoice Log'!$AT$3:$AT$303,Settings!$J$7)) -> 0 | D30: =IF($A30="","",SUMIFS('Invoice Log'!$AI$3:$AI$303,'Invoice Log'!$B$3:$B$303,$A30,'Invoice Log'!$AN$3:$AN$303,"",'Invoice Log'!$AT$3:$AT$303,Settings!$J$7)) -> 0
A31: =IF(Settings!$B$8="","",Settings!$B$8) | B31: =IF($A31="","",SUMIFS('Invoice Log'!$T$3:$T$303,'Invoice Log'!$B$3:$B$303,$A31,'Invoice Log'!$J$3:$J$303,"<>Cancelled",'Invoice Log'!$AT$3:$AT$303,Settings!$J$7)) | C31: =IF($A31="","",SUMIFS('Invoice Log'!$AG$3:$AG$303,'Invoice Log'!$B$3:$B$303,$A31,'Invoice Log'!$AT$3:$AT$303,Settings!$J$7)) | D31: =IF($A31="","",SUMIFS('Invoice Log'!$AI$3:$AI$303,'Invoice Log'!$B$3:$B$303,$A31,'Invoice Log'!$AN$3:$AN$303,"",'Invoice Log'!$AT$3:$AT$303,Settings!$J$7))
A32: =IF(Settings!$B$9="","",Settings!$B$9) | B32: =IF($A32="","",SUMIFS('Invoice Log'!$T$3:$T$303,'Invoice Log'!$B$3:$B$303,$A32,'Invoice Log'!$J$3:$J$303,"<>Cancelled",'Invoice Log'!$AT$3:$AT$303,Settings!$J$7)) | C32: =IF($A32="","",SUMIFS('Invoice Log'!$AG$3:$AG$303,'Invoice Log'!$B$3:$B$303,$A32,'Invoice Log'!$AT$3:$AT$303,Settings!$J$7)) | D32: =IF($A32="","",SUMIFS('Invoice Log'!$AI$3:$AI$303,'Invoice Log'!$B$3:$B$303,$A32,'Invoice Log'!$AN$3:$AN$303,"",'Invoice Log'!$AT$3:$AT$303,Settings!$J$7))
A35: JOBS BY STATUS
A36: Status | B36: Jobs | C36: Value invoiced
A37: Quote Sent | B37: =COUNTIFS('Invoice Log'!$J$3:$J$303,$A37,'Invoice Log'!$AT$3:$AT$303,Settings!$J$7) -> 0 | C37: =SUMIFS('Invoice Log'!$T$3:$T$303,'Invoice Log'!$J$3:$J$303,$A37,'Invoice Log'!$AT$3:$AT$303,Settings!$J$7) -> 0
A38: Confirmed - Awaiting Payment | B38: =COUNTIFS('Invoice Log'!$J$3:$J$303,$A38,'Invoice Log'!$AT$3:$AT$303,Settings!$J$7) -> 0 | C38: =SUMIFS('Invoice Log'!$T$3:$T$303,'Invoice Log'!$J$3:$J$303,$A38,'Invoice Log'!$AT$3:$AT$303,Settings!$J$7) -> 0
A39: Part Paid | B39: =COUNTIFS('Invoice Log'!$J$3:$J$303,$A39,'Invoice Log'!$AT$3:$AT$303,Settings!$J$7) -> 0 | C39: =SUMIFS('Invoice Log'!$T$3:$T$303,'Invoice Log'!$J$3:$J$303,$A39,'Invoice Log'!$AT$3:$AT$303,Settings!$J$7) -> 0
A40: Paid in Full | B40: =COUNTIFS('Invoice Log'!$J$3:$J$303,$A40,'Invoice Log'!$AT$3:$AT$303,Settings!$J$7) -> 2 | C40: =SUMIFS('Invoice Log'!$T$3:$T$303,'Invoice Log'!$J$3:$J$303,$A40,'Invoice Log'!$AT$3:$AT$303,Settings!$J$7) -> 7555.08
A41: Refund Due | B41: =COUNTIFS('Invoice Log'!$J$3:$J$303,$A41,'Invoice Log'!$AT$3:$AT$303,Settings!$J$7) -> 1 | C41: =SUMIFS('Invoice Log'!$T$3:$T$303,'Invoice Log'!$J$3:$J$303,$A41,'Invoice Log'!$AT$3:$AT$303,Settings!$J$7) -> 1632.8
A42: Complete | B42: =COUNTIFS('Invoice Log'!$J$3:$J$303,$A42,'Invoice Log'!$AT$3:$AT$303,Settings!$J$7) -> 141 | C42: =SUMIFS('Invoice Log'!$T$3:$T$303,'Invoice Log'!$J$3:$J$303,$A42,'Invoice Log'!$AT$3:$AT$303,Settings!$J$7) -> 620296.57
A43: Cancelled | B43: =COUNTIFS('Invoice Log'!$J$3:$J$303,$A43,'Invoice Log'!$AT$3:$AT$303,Settings!$J$7) -> 3 | C43: =SUMIFS('Invoice Log'!$T$3:$T$303,'Invoice Log'!$J$3:$J$303,$A43,'Invoice Log'!$AT$3:$AT$303,Settings!$J$7) -> 6531.62
A46: BY TEAM MEMBER
A47: Owner | B47: Invoiced | C47: Still owed
A48: =IF(Settings!$A$4="","",Settings!$A$4) -> Charlotte | B48: =IF($A48="","",SUMIFS('Invoice Log'!$T$3:$T$303,'Invoice Log'!$A$3:$A$303,$A48,'Invoice Log'!$J$3:$J$303,"<>Cancelled",'Invoice Log'!$AT$3:$AT$303,Settings!$J$7)) -> 28015.548 | C48: =IF($A48="","",SUMIFS('Invoice Log'!$AG$3:$AG$303,'Invoice Log'!$A$3:$A$303,$A48,'Invoice Log'!$AT$3:$AT$303,Settings!$J$7)) -> 0
A49: =IF(Settings!$A$5="","",Settings!$A$5) -> Danelle | B49: =IF($A49="","",SUMIFS('Invoice Log'!$T$3:$T$303,'Invoice Log'!$A$3:$A$303,$A49,'Invoice Log'!$J$3:$J$303,"<>Cancelled",'Invoice Log'!$AT$3:$AT$303,Settings!$J$7)) -> 663430.91 | C49: =IF($A49="","",SUMIFS('Invoice Log'!$AG$3:$AG$303,'Invoice Log'!$A$3:$A$303,$A49,'Invoice Log'!$AT$3:$AT$303,Settings!$J$7)) -> 61962.01
A50: =IF(Settings!$A$6="","",Settings!$A$6) -> Raquel | B50: =IF($A50="","",SUMIFS('Invoice Log'!$T$3:$T$303,'Invoice Log'!$A$3:$A$303,$A50,'Invoice Log'!$J$3:$J$303,"<>Cancelled",'Invoice Log'!$AT$3:$AT$303,Settings!$J$7)) -> 0 | C50: =IF($A50="","",SUMIFS('Invoice Log'!$AG$3:$AG$303,'Invoice Log'!$A$3:$A$303,$A50,'Invoice Log'!$AT$3:$AT$303,Settings!$J$7)) -> 0
A51: =IF(Settings!$A$7="","",Settings!$A$7) | B51: =IF($A51="","",SUMIFS('Invoice Log'!$T$3:$T$303,'Invoice Log'!$A$3:$A$303,$A51,'Invoice Log'!$J$3:$J$303,"<>Cancelled",'Invoice Log'!$AT$3:$AT$303,Settings!$J$7)) | C51: =IF($A51="","",SUMIFS('Invoice Log'!$AG$3:$AG$303,'Invoice Log'!$A$3:$A$303,$A51,'Invoice Log'!$AT$3:$AT$303,Settings!$J$7))
A52: =IF(Settings!$A$8="","",Settings!$A$8) | B52: =IF($A52="","",SUMIFS('Invoice Log'!$T$3:$T$303,'Invoice Log'!$A$3:$A$303,$A52,'Invoice Log'!$J$3:$J$303,"<>Cancelled",'Invoice Log'!$AT$3:$AT$303,Settings!$J$7)) | C52: =IF($A52="","",SUMIFS('Invoice Log'!$AG$3:$AG$303,'Invoice Log'!$A$3:$A$303,$A52,'Invoice Log'!$AT$3:$AT$303,Settings!$J$7))
A53: =IF(Settings!$A$9="","",Settings!$A$9) | B53: =IF($A53="","",SUMIFS('Invoice Log'!$T$3:$T$303,'Invoice Log'!$A$3:$A$303,$A53,'Invoice Log'!$J$3:$J$303,"<>Cancelled",'Invoice Log'!$AT$3:$AT$303,Settings!$J$7)) | C53: =IF($A53="","",SUMIFS('Invoice Log'!$AG$3:$AG$303,'Invoice Log'!$A$3:$A$303,$A53,'Invoice Log'!$AT$3:$AT$303,Settings!$J$7))
A56: THE ARCHIVE (2022-2025)
A57: Jobs on record | B57: =COUNTA('Archive 2022-2025'!$E$3:$E$572) -> 570
A58: Invoiced across those years | B58: =SUM('Archive 2022-2025'!$R$3:$R$572) -> 2361835.3
A59: Cancelled jobs | B59: =COUNTIF('Archive 2022-2025'!$I$3:$I$572,"Cancelled") -> 39

Sheet Fix List
A1: FIX LIST - what needs a human decision
A2: 80 items. Nothing here was guessed at or auto-corrected.
A4: INV Number | B4: Client | C4: Owner | D4: What needs sorting
A5: 22004225 | B5: Zenith Bank Ltd - Day 1 & 2 | C5: Danelle | D5: No event date - the Collective tab works off event dates, so this job falls into the wrong month
A6: 22004254 | B6: House of Decant | C6: Danelle | D6: No event date - the Collective tab works off event dates, so this job falls into the wrong month
A7: 22004261 | B7: Zenith Bank Ltd - Day 7 & 8 | C7: Danelle | D7: No event date - the Collective tab works off event dates, so this job falls into the wrong month
A8: 22004273 | B8: Orbit Design Studio Ltd | C8: Danelle | D8: No event date - the Collective tab works off event dates, so this job falls into the wrong month
A9: 22004281 | B9: House of Decant - June | C9: Danelle | D9: No event date - the Collective tab works off event dates, so this job falls into the wrong month
A10: 22004289 | B10: House of Decant | C10: Danelle | D10: No event date - the Collective tab works off event dates, so this job falls into the wrong month
A11: 22004306 | B11: House of Decant - July | C11: Danelle | D11: No event date - the Collective tab works off event dates, so this job falls into the wrong month
A12: 22004312 | B12: Xero - Additional picnic boxes | C12: Danelle | D12: No event date - the Collective tab works off event dates, so this job falls into the wrong month
A13: 22004279 | B13: TGB | C13: Danelle | D13: No invoice date
A14: 22004307 | B14: Europe House | C14: Danelle | D14: No invoice date
A15: 22004268 | B15: Salt Productions | C15: Danelle | D15: No quote total - every money column on this row is blank
A16: 22004283 | B16: Pontoon | C16: Danelle | D16: No quote total - every money column on this row is blank
... A84: 22004347 | B84: Samantha Armstrong | C84: Danelle | D84: Status is blank - nobody set where this job got to

Sheet Archive 2022-2025
A1: ARCHIVE - everything before 01/01/2026. Figures exactly as they were entered, nothing recalculated. Closed off as Complete unless cancelled. Add new work on the Invoice Log tab.
A2: Owner | B2: Our Company | C2: Type | D2: INV Number | E2: Client / Booking Name | F2: Event Date | G2: Invoice Date | H2: New / Repeat | I2: STATUS | J2: Covers | K2: Cost per Head | L2: Quote Total (ex VAT) | M2: VAT Rate | N2: VAT | O2: Total (inc VAT) | P2: Deposit Req? | Q2: Damage Deposit | R2: Invoice Total | S2: 1st Invoice | T2: Payment 1 | U2: Method | V2: Date | W2: Payment 2 | X2: Method | Y2: Date | Z2: Payment 3 | AA2: Method | AB2: Date | AC2: Refund Amount | AD2: Refund Method | AE2: Refund Paid Date | AF2: Account Name | AG2: Sort Code | AH2: Account Number | AI2: Comments
A3: Danelle | B3: Penni Black | C3: C | D3: 220019 | E3: Canada House | F3: 45001 | G3: 44995 | H3: R | I3: Complete | J3: 65 | K3: 42.369231 | L3: 2754 | M3: 0.2 | N3: 550.8 | O3: 3304.8 | P3: Yes | Q3: 293.4 | R3: 3598.2 | S3: 1945.8 | T3: 3598.2 | U3: CC | V3: 44995 | AC3: 293.4 | AD3: CC | AE3: 44995
A4: Danelle | B4: Penni Black | C4: C | D4: 220020 | E4: House of Greenland | F4: 45001 | G4: 44999 | H4: N | I4: Complete | J4: 150 | K4: 1.8 | L4: 270 | M4: 0.2 | N4: 54 | O4: 324 | P4: Yes | Q4: 27 | R4: 351 | S4: 189 | T4: 1266.81 | U4: BACS | V4: 45000 | AC4: 2193.42 | AE4: 45005
A5: Pierre | B5: Penni Black | C5: C | D5: 220021 | E5: Laura Kellett Lunch delivery | F5: 45015 | G5: 45005 | H5: N | I5: Complete | J5: 15 | K5: 61.2 | L5: 918 | M5: 0.2 | N5: 183.6 | O5: 1101.6 | P5: No | Q5: 91.8 | R5: 1101.6 | S5: 642.6 | T5: 1101.6 | U5: CC | V5: 45008
A6: Pierre | B6: Penni Black | C6: C | D6: 220022 | E6: Maayan Keinan lunch boxes delivery | F6: 45034 | G6: 45006 | H6: N | I6: Complete | J6: 80 | K6: 31.21875 | L6: 2497.5 | M6: 0.2 | N6: 499.5 | O6: 2997 | P6: No | Q6: 249.75 | R6: 2997 | S6: 1748.25
A7: Charlotte | B7: Penni Black | C7: C | D7: 220023 | E7: James - IMC Experience | F7: 45020 | G7: 45007 | H7: R | I7: Complete | J7: 50 | K7: 33.55 | L7: 1677.5 | M7: 0.2 | N7: 335.5 | O7: 2013 | P7: No | Q7: 167.75 | R7: 2013 | S7: 1174.25 | T7: 2013 | U7: CC | V7: 45016
A8: Raquel | B8: Penni Black | C8: C | D8: 220024 | E8: Veronica Trentadue - Omaze | F8: 45021 | G8: 45016 | H8: N | I8: Complete | J8: 26 | K8: 116.64231 | L8: 3032.7 | M8: 0.2 | N8: 606.54 | O8: 3639.24 | P8: No | Q8: 303.27 | R8: 3639.24 | S8: 2122.89 | AC8: 250.52 | AE8: 45035
A9: Raquel | B9: Penni Black | C9: C | D9: 220025 | E9: Michaela Longo - Helaba | F9: 45099 | G9: 45019 | H9: R | I9: Complete | J9: 60 | K9: 72.066667 | L9: 4324 | M9: 0.2 | N9: 864.8 | O9: 5188.8 | Q9: 432.4 | S9: 3026.8 | T9: 5707.68 | U9: BACS | V9: 45076 | AC9: 410.88 | AD9: BACS | AE9: 45114 | AF9: waiting for bank details
A10: Charlotte | B10: Penni Black | C10: C | D10: 220026 | E10: Delegation european union | F10: 45015 | G10: 45020 | H10: R | I10: Complete | J10: 55 | K10: 50 | L10: 2750 | M10: 0.2 | N10: 550 | O10: 3300 | P10: No | Q10: 275 | R10: 3300 | S10: 1925 | T10: 3300 | U10: BACS | V10: 45035
A11: Raquel | B11: Penni Black | D11: 220027 | E11: Allena Stanford - Tottum Partners | F11: 45035 | G11: 45027 | H11: R | I11: Complete | J11: 20 | K11: 67.275 | L11: 1345.5 | M11: 0.2 | N11: 269.1 | O11: 1614.6 | P11: Yes | Q11: 134.55 | R11: 1749.15 | S11: 941.85 | T11: 1776.06 | U11: BACS | V11: 45028 | AC11: 161.46 | AE11: 45069
A12: Raquel | B12: Penni Black | D12: 220028 | E12: Melanie Holroyd - The Investment Association | F12: 45041 | H12: R | I12: Complete | J12: 50 | K12: 26.52 | L12: 1326 | M12: 0.2 | N12: 265.2 | O12: 1944.6 | Q12: 132.6 | S12: 1104.9
A13: Raquel | B13: Penni Black | D13: 220029 | E13: Ian Scott - Humanists Uk | G13: 45029 | H13: R | I13: Complete | J13: 60 | K13: 58.681667 | L13: 3520.9 | M13: 0.2 | N13: 704.18 | O13: 4225.08 | P13: No | Q13: 352.09 | R13: 4225.08 | S13: 2464.63 | AC13: 598.21 | AD13: CC | AE13: 45041 | AI13: Event dates: 17/04/0223.
A14: Charlotte | B14: Penni Black | D14: 220030 | E14: We Are Family | F14: 45042 | G14: 45033 | H14: R | I14: Complete | J14: 200 | K14: 116.26 | L14: 23252 | M14: 0.2 | N14: 4650.4 | O14: 27902.4 | P14: No | Q14: 2325.2 | R14: 27902.4 | S14: 16276.4
A15: Charlotte | B15: Penni Black | D15: 220031 | E15: Europe | F15: 45041 | G15: 45041 | H15: R | I15: Complete | J15: 30 | K15: 50 | L15: 1500 | M15: 0.2 | N15: 300 | O15: 1800 | Q15: 150 | S15: 1050 | T15: 1800 | U15: BACS | V15: 45056
A16: Charlotte | B16: Penni Black | D16: 220032 | E16: Birgitte Goethe | F16: 45045 | G16: 45041 | H16: R | I16: Complete | J16: 12 | K16: 101.2 | L16: 1214.4 | M16: 0.2 | N16: 242.88 | O16: 1457.28 | P16: Yes | Q16: 121.44 | R16: 1578.72 | S16: 850.08
A17: Pierre | B17: Penni Black | C17: C | D17: 220033 | E17: Tasting Britannia - Manjeet Dhaliwal (non-refundable) | F17: 45049 | G17: 45042 | H17: R | I17: Complete | J17: 5 | K17: 56.6 | L17: 283 | M17: 0.2 | N17: 56.6 | O17: 339.6 | Q17: 28.3 | S17: 198.1 | T17: 339.6 | U17: BACS | V17: 45069
A18: Charlotte | B18: Penni Black | D18: 220034 | E18: Europe | F18: 45048 | G18: 45048 | H18: R | I18: Complete | J18: 40 | K18: 50 | L18: 2000 | M18: 0.2 | N18: 400 | O18: 2400 | P18: No | Q18: 200 | R18: 2400 | S18: 1400 | T18: 2400 | U18: BACS | V18: 45056
A19: Danelle | B19: Penni Black | C19: C | D19: 220035 | E19: Totum Partners | F19: 45057 | G19: 45049 | H19: R | I19: Complete | J19: 30 | K19: 40.05 | L19: 1201.5 | M19: 0.2 | N19: 240.3 | O19: 1441.8 | Q19: 0 | S19: 720.9 | T19: 1441.8 | U19: BACS | V19: 45049
A20: Gabriella | B20: Penni Black | D20: 220036 | E20: Brands At Work | F20: 45071 | G20: 45049 | H20: N | I20: Complete | J20: 120 | K20: 91.38 | L20: 9137.8 | M20: 0.2 | N20: 1827.56 | O20: 10965.36 | P20: Yes | Q20: 913.78 | R20: 11879.14 | S20: 6396.46 | T20: 6251 | U20: BACS | V20: 45056 | W20: 5607.36 | X20: BACS | Y20: 45068 | AC20: 913.78 | AE20: 45078 | AF20: Brands at Work Limited | AG20: Sort Code: 20-69-17 | AH20: Account no: 9389 1682 | AI20: Barclays Bank plc
A21: Pierre | B21: Penni Black | C21: C | D21: 220037 | E21: Fasten Seatbelt Group | F21: 45085 | G21: 45050 | H21: N | I21: Complete | J21: 50 | K21: 79.66 | L21: 3983 | M21: 0.2 | N21: 796.6 | O21: 4779.6 | Q21: 398.3 | S21: 2788.1 | T21: 5164.9 | U21: BACS | V21: 45082 | AC21: 139.3 | AD21: CC | AE21: 45090
A22: Raquel | B22: Penni Black | D22: 220038 | E22: Alston & Bird | F22: 45105 | G22: 45051 | H22: N | I22: Complete | J22: 50 | K22: 122.482 | L22: 6124.1 | M22: 0.2 | N22: 1224.82 | O22: 7348.92 | Q22: 612.41 | S22: 4286.87 | T22: 7816.51 | U22: BACS | V22: 45100 | W22: 222.82 | X22: BACS | Y22: 45103 | AC22: 1138.73 | AD22: BACS | AE22: 45114 | AF22: Alston & Bird (City) LLP | AG22: 308012 | AH22: 19644460
A23: Danelle | B23: Penni Black | C23: P | D23: 220039 | E23: Kristina Sitnikaite | F23: 45057 | G23: 45051 | H23: N | I23: Complete | J23: 25 | K23: 52.23 | L23: 1305.75 | M23: 0.2 | N23: 261.15 | O23: 1566.9 | Q23: 130.575 | S23: 914.025 | T23: 1697.47 | U23: CC | V23: 45051 | AC23: 130.57 | AD23: CC | AE23: 45063
A24: Danelle | B24: Penni Black | C24: C | D24: 220040 | E24: Gairdner | F24: 45112 | G24: 45053 | H24: N | I24: Complete | J24: 50 | K24: 77.882 | L24: 3894.1 | M24: 0.2 | N24: 778.82 | O24: 4672.92 | Q24: 389.41 | S24: 2725.87 | T24: 6119.2 | U24: BACS | V24: 45062 | AC24: 1660.36 | AE24: 45131 | AF24: The Gairdner Foundation | AG24: Bank code: #004 Transit: #12242 | AH24: 5241783 (Swift: TDOMCATTTOR) | AI24: TD Canada Trust (Bank Name)
A25: Danelle | B25: Penni Black | C25: C | D25: 220041 | E25: Winston & Strawn | F25: 45120 | G25: 45053 | H25: N | I25: Complete | J25: 60 | K25: 107.555 | L25: 6453.3 | M25: 0.2 | N25: 1290.66 | O25: 7743.96 | Q25: 645.33 | S25: 4517.31 | T25: 3780.77 | V25: 45061 | W25: 3963.19 | X25: CC | Y25: 45117 | AC25: 783.35 | AD25: CC | AE25: 45126
A26: Charlotte | B26: Penni Black | C26: C | D26: 220042 | E26: Andrew & Jane Black | F26: 45061 | G26: 45053 | H26: R | I26: Complete | J26: 80 | K26: 84.3775 | L26: 6750.2 | M26: 0.2 | N26: 1350.04 | O26: 8100.24 | P26: no | Q26: 675.02 | R26: 8100.24 | S26: 4725.14
A27: Danelle | B27: Penni Black | C27: C | D27: 220043 | E27: IHS Towers | F27: 45063 | G27: 45056 | H27: R | I27: Complete | J27: 15 | K27: 132.96667 | L27: 1994.5 | M27: 0.2 | N27: 398.9 | O27: 2393.4 | Q27: 199.45 | S27: 1396.15 | T27: 2592.85 | U27: CC | V27: 45056 | AC27: 199.45 | AD27: CC | AE27: 45069
A28: Danelle | B28: Penni Black | C28: P | D28: 220044 | E28: Mia Clarke | F28: 45164 | G28: 45062 | H28: N | I28: Complete | J28: 31 | K28: 99.540323 | L28: 3085.75 | M28: 0.2 | N28: 617.15 | O28: 3702.9 | P28: Yes | Q28: 308.575 | R28: 4011.475 | S28: 2160.025 | T28: 1902.9 | U28: CC | V28: 45067 | W28: 2000 | X28: BACS | Y28: 45160 | AC28: 353.63 | AD28: CC | AE28: 45176
